Workbook

Sheet DANH SACH
A1: =SUBTOTAL(3,A3:A2991) -> 1387 | B1: Đơn vị | C1: Tên đơn vị | D1: Loại KHách hàng | E1: Thông tin đơn hàng | U1: Đặc điểm đơn hàng | AJ1: Công nợ | AM1: Yêu cầu thu gom | AS1: Lịch sử chăm sóc KHách hàng | AW1: KPI & mục tiêu Đã cam kết | AY1: Nhóm KHách hàng | BD1: Doanh thu tháng 12/2025 | BE1: Doanh thu tháng 01/2026 | BF1: Doanh thu tháng 02/2026 (01/02-22/02) | BG1: Doanh thu 3 tháng | BH1: THÔNG TIN CHI TIẾT | BI1: GHI CHÚ | BJ1: Mã BC | BK1: Tên BC/VHX | BL1: BĐP/X | BM1: Cước đặc thù | BN1: Người rà soát bàn giao TTKD | BO1: Người rà soát bàn giao TTVH | BP1: Đơn vị đã gắn HĐ trên CMS | BQ1: Đã gửi HĐ vật lý lên TTKD | BR1: Tên đơn vị
A2: TT | E2: Mã CRM/CMS | F2: Tên KHách hàng | G2: Địa chỉ | H2: Điện thoại | I2: Người liên hệ | J2: Mã CRM/CMS | K2: Mã số thuế | L2: Số hợp đồng | M2: Thời hạn hợp đồng | N2: Thời hạn kết thúc | O2: Phụ lục, thoả thuận bổ sung Hợp đồng | P2: Thời gian, quy định việc thanh toán cước BCCP ghi nợ | Q2: Hình thức, thời gian thanh toán tiền thu hộ COD | R2: Số tài KHoản nhận tiền thu hộ COD, phí ship | S2: Trạng thái hoạt động | T2: Người quản lý KHách hàng (Họ tên, số điện thoại, email) | U2: Dịch vụ sử dụng | V2: Dịch vụ GTGT KHác | W2: Nội dung hàng hóa gửi | X2: KHối lượng dự kiến/bưu gửi | Y2: Sản lượng bình quân/ngày | Z2: Doanh thu bình quân/ngày | AA2: Hình thức phát hành: KH dùng My VNP/exel/thủ công…. | AB2: Bưu cục ghi nhận doanh thu (số hiệu bưu cục, tên bưu cục) | AC2: Tài KHoản trên Portal KHL ghi nhận doanh thu | AD2: Chú dẫn yêu cầu chuyển phát | AE2: Chỉ tiêu thời gian toàn trình dịch vụ | AF2: Yêu cầu KHác: - Gia công, đóng gói - Thuê KHo,... (nếu có) - KHác biệt về thời gian cutoff (nếu có) - ......(nếu có) | AG2: KHiếu nại, chốt phạt bồi thường (KHác biệt nếu có) | AH2: [ ] KHách hàng có cấu hình hệ thống đặc biệt cần duy trì? | AI2: [ ] Có dịch vụ tuỳ chỉnh hay tích hợp đặc thù? | AJ2: [ ] KHách hàng còn công nợ chưa thanh toán? | AK2: [ ] Có lịch trình thu hồi hoặc xử lý công nợ? | AL2: Hình thức phạt đối với chậm trả nợ | AM2: Địa chỉ thu gom (chi tiết đến phường/xã, quận/huyện,..) | AN2: Thời gian thu gom | AO2: Tần suất thu gom | AP2: Sản lượng thu gom | AQ2: Phương tiện thu gom | AR2: KHác biệt thu gom (nếu có) | AS2: [ ] Tương tác gần nhất với KHách hàng | AT2: [ ] Ghi chú yêu cầu đặc biệt hoặc sự cố đang xử lý | AU2: [ ] Cam kết dịch vụ Đã thực hiện | AV2: [ ] Kế hoạch chăm sóc định kỳ | AW2: [ ] Cam kết chất lượng hoặc KPI giữa KHách hàng và Trung tâm Kinh doanh | AX2: [ ] Theo dõi mức độ hoàn thành và kế hoạch tiếp tục | AY2: KHách hàng sàn TMĐT | AZ2: KH tạo đơn bằng phần mềm bán hàng | BA2: KH tạo đơn và gửi thông tin qua API cho BĐVN | BB2: Tạo đơn trên PM MyVNP | BC2: Tạo đơn trên phần mềm Portal KHL | BH2: THÔNG TIN CHI TIẾT
A3: 1 | B3: 5310 | C3: Bưu điện TT Thuận Hóa - Phú Xuân | D3: SME | E3: T004890545 | F3: Công Ty Cổ Phần Toyota Huế | G3: Lô C, KĐT Phú Mỹ An, Đường Tố Hữu, An Đông, TP Huế | H3: 02436299696 | I3: Lê Thế Vỹ | J3: T004890545 | K3: 3301635376 | L3: HĐ54-2022_HĐBC_BĐTPH-MTL | M3: 01/5/2022 | N3: Không xác định | P3: 1-2 lần/tháng | S3: Đang hoạt động | T3: HỒ VĂN KỲ | U3: ETN001 | W3: Thư | X3: 17.14 | Y3: 2 | Z3: 51292 | AB3: 533810 | AC3: 533810_dungntt | AE3: Thực hiện theo quy định của TCT | AJ3: 3181837 | AK3: Đang liên hệ thanh toán | AM3: Lô C, KĐT Phú Mỹ An, Đường Tố Hữu, An Đông, TP Huế | AN3: 14h00-17h00 | AO3: 1 lần/ngày | AP3: 66 | AQ3: xe máy | AS3: 45855 | BB3: X | BD3: 1862866 | BE3: 2425140 | BF3: 813058 | BG3: =SUM(BD3:BF3) -> 5101064 | BH3: Hồ sơ vật lý và hồ sơ điện tử | BI3: Phát - Long | BJ3: 533810 | BK3: Thuỷ An | BL3: Phường An Cựu | BP3: X | BQ3: X | BR3: Bưu điện TT Thuận Hóa - Phú Xuân
A4: 2 | B4: 5310 | C4: Bưu điện TT Thuận Hóa - Phú Xuân | D4: Shop | E4: C001395675 | F4: VÕ HOÀNG MINH | G4: Đường số 7, An Cựu City, P An Đông, TP Huế | H4: 0932436536 | I4: VÕ HOÀNG MINH | J4: C001395675 | L4: 151/HĐBC-BĐTP/VHM | M4: 43685 | N4: Không xác định | P4: Thanh toán ngay khi gửi | S4: Đang hoạt động | T4: PHẠM THỊ THANH UYÊN | U4: ETN011 | W4: TRANH VE | X4: 3.5743333 | Y4: 0.1 | Z4: 6994.4 | AB4: 533810 | AC4: 533810_dungntt | AE4: Theo quy định TCT | AF4: Không có yêu cầu khác. | AJ4: đã thanh toán | AM4: Đường số 7, An Cựu City, P An Đông, TP Huế | AN4: 09h00-11h00; 15h00-17h00 | AO4: 1-2 lần/tuần | AP4: 3 | AQ4: Xe máy | AS4: 45782 | BB4: X | BD4: 232290 | BE4: 175356 | BF4: 0 | BG4: =SUM(BD4:BF4) -> 407646 | BH4: Hồ sơ vật lý và hồ sơ điện tử | BI4: Phát - Long | BJ4: 533810 | BK4: Thuỷ An | BL4: Phường An Cựu | BP4: X | BQ4: X | BR4: Bưu điện TT Thuận Hóa - Phú Xuân
A5: 3 | B5: 5310 | C5: Bưu điện TT Thuận Hóa - Phú Xuân | D5: SME | E5: T001799661 | F5: CÔNG TY TNHH TM QUỐC HÙNG | G5: 86 HÙNG VƯƠNG, TP HUẾ | H5: 0989020237 | I5: Nguyễn Trần Như Ý | J5: T001799661 | K5: 3300338476 | L5: 384/HĐBC/BĐTPH-CTQUOCHUNG | M5: 44169 | N5: Không xác định | O5: Không có | P5: 01 tháng/lần Thanh toán tại địa chỉ bên A | S5: Đang hoạt động | T5: HỒ VĂN KỲ | U5: ETN011, ETN011 | W5: Phụ tùng xe máy | X5: 0.41 | Y5: 0.33 | Z5: 13125.6 | AB5: 533810 | AD5: SỐ ĐT NTO GHI TRÊN ĐƠN HÀNG.TSK | AE5: Theo quy định TCT | AF5: Không có yêu cầu khác. | AJ5: 759.888 | AK5: đang thanh toán | AM5: 86 HÙNG VƯƠNG, TP HUẾ | AN5: 09h00-11h00; 15h00-17h00 | AO5: 1-2 lần/tuần | AP5: 10 | AQ5: Xe máy | AS5: 45869 | BC5: X | BD5: 0 | BE5: 0 | BF5: 18000 | BG5: =SUM(BD5:BF5) -> 18000 | BH5: Hồ sơ vật lý và hồ sơ điện tử | BI5: Phát - Long | BJ5: 533810 | BK5: Thuỷ An | BL5: Phường An Cựu | BP5: X | BQ5: X | BR5: Bưu điện TT Thuận Hóa - Phú Xuân
A6: 4 | B6: 5310 | C6: Bưu điện TT Thuận Hóa - Phú Xuân | D6: SME | E6: T001456556 | F6: Công ty luật TNHH Nhật Nam và cộng sự | G6: 52 Hoàng Văn Thụ, P An Đông, TP Huế | H6: 0234.3936155 | I6: Trần Nhật Nam | J6: T001456556 | K6: 3301516202 | L6: 149/HĐBC-BĐTP/TNN | M6: 43685 | N6: Không xác định | O6: Không có | P6: Thanh toán vào tháng sau | S6: Đang hoạt động | T6: PHẠM THỊ THANH UYÊN | U6: ETN001 | X6: 0.07 | Y6: 0.87 | Z6: 12283.2 | AB6: 533810 | AC6: 533810_dungntt | AD6: SỐ ĐT NTO GHI TRÊN ĐƠN HÀNG.TKS | AE6: Theo quy định TCT | AF6: Không có yêu cầu khác. | AJ6: 2,605,824 | AK6: khách hàng chậm trả | AM6: 52 Hoàng Văn Thụ, P An Đông, TP Huế | AN6: 09h00-11h00; 15h00-17h00 | AO6: 1-2 lần/tuần | AP6: 26 | AQ6: Xe máy | AS6: 45869 | BC6: X | BD6: 459600 | BE6: 223200 | BF6: 138400 | BG6: =SUM(BD6:BF6) -> 821200 | BH6: Hồ sơ vật lý và hồ sơ điện tử | BI6: Phát - Long | BJ6: 533810 | BK6: Thuỷ An | BL6: Phường An Cựu | BP6: X | BQ6: X | BR6: Bưu điện TT Thuận Hóa - Phú Xuân
A7: 5 | B7: 5310 | C7: Bưu điện TT Thuận Hóa - Phú Xuân | D7: SME | E7: T001799967 | F7: CÔNG TY TNHH MTV PHÁT LÊ | G7: 108 TRƯỜNG CHINH, P. An Đông TP. Huế Tỉnh Thừa Thiên Huế | H7: 0234.3934999 | I7: Trần Thị Thúy Nhi | J7: T001799967 | K7: 3301335118 | L7: 391/HĐBC/BĐTPH-PL | M7: 44168 | N7: Không xác định | O7: Không có | P7: Thanh toán vào tháng sau | Q7: Ngay khi sử dụng dịch vụ Thanh toán tại địa chỉ bên A | S7: Đang hoạt động | T7: HỒ VĂN KỲ | U7: ETN001, CTN001 | W7: Tài liệu | X7: 1.12 | Y7: 0.27 | Z7: 7325.63 | AB7: 533810 | AC7: 533810_dungntt | AD7: SỐ ĐT NTO GHI TRÊN ĐƠN HÀNG.TKS | AE7: Theo quy định TCT | AF7: Không có yêu cầu khác. | AJ7: đã thanh toán | AM7: 108 TRƯỜNG CHINH, P. An Đông TP. Huế Tỉnh Thừa Thiên Huế | AN7: 09h00-11h00; 15h00-17h00 | AO7: 1-2 lần/tuần | AP7: 8 | AQ7: Xe máy | AS7: 45869 | BC7: X | BD7: 334254 | BE7: 226908 | BF7: 179175 | BG7: =SUM(BD7:BF7) -> 740337 | BH7: Hồ sơ vật lý và hồ sơ điện tử | BI7: Phát - Long | BJ7: 533810 | BK7: Thuỷ An | BL7: Phường An Cựu | BP7: X | BQ7: X | BR7: Bưu điện TT Thuận Hóa - Phú Xuân
A8: 6 | B8: 5310 | C8: Bưu điện TT Thuận Hóa - Phú Xuân | D8: SME | E8: C001929335 | F8: Công Ty Tnhh Tm Tân Quốc Hùng | G8: 128 hùng vương, P. Phú Hội TP. Huế Tỉnh Thừa Thiên Huế | H8: 02343811015 | I8: Võ Văn Hùng | J8: C001929335 | K8: 3300556058 | L8: 389/HĐBC | M8: 44228 | N8: Không xác định | O8: Không có | P8: Thanh toán vào tháng sau | S8: Đang hoạt động | T8: PHẠM THỊ THANH UYÊN | U8: ETN001 | X8: 0.05 | Y8: 0.17 | Z8: 2376 | AB8: 533810 | AC8: 533810_dungntt | AD8: SỐ ĐT NTO GHI TRÊN ĐƠN HÀNG.TKS | AE8: Theo quy định TCT | AF8: Không có yêu cầu khác. | AJ8: đã thanh toán | AM8: 128 hùng vương, P. Phú Hội TP. Huế Tỉnh Thừa Thiên Huế | AN8: 09h00-11h00; 15h00-17h00 | AO8: 1-2 lần/tuần | AP8: 5 | AQ8: Xe máy | AS8: 45869 | BC8: X | BD8: 82200 | BE8: 100200 | BF8: 0 | BG8: =SUM(BD8:BF8) -> 182400 | BH8: Hồ sơ vật lý và hồ sơ điện tử | BI8: Phát - Long | BJ8: 533810 | BK8: Thuỷ An | BL8: Phường An Cựu | BP8: X | BQ8: x | BR8: Bưu điện TT Thuận Hóa - Phú Xuân
A9: 7 | B9: 5310 | C9: Bưu điện TT Thuận Hóa - Phú Xuân | D9: SME | E9: T002490015 | F9: Công Ty Cổ Phần Tập Đoàn IUC | G9: Tầng 3, Tòa nhà Vinaconex 7, số 64 Đường Nguyễn Văn Giáp , phường Cầu Diễn, Quận Nam Từ Liêm, Hà Nội | H9: 0908576568 | I9: Nguyễn Thành Công | J9: T002490015 | K9: 0104230537 | L9: 383.2021/HĐBC-BĐTPH-IUC | M9: 44389 | N9: Không xác định | O9: Không có | P9: Thanh toán vào tháng sau | S9: Đang hoạt động | T9: HỒ VĂN KỲ | U9: ETN001 | X9: 0.07 | Y9: 0.1 | Z9: 2008.8 | AB9: 533810 | AC9: 533810_dungntt | AD9: SỐ ĐT NTO GHI TRÊN ĐƠN HÀNG.TKS | AE9: Theo quy định TCT | AF9: Không có yêu cầu khác. | AJ9: đã thanh toán | AM9: Tầng 3, Tòa nhà Vinaconex 7, số 64 Đường Nguyễn Văn Giáp , phường Cầu Diễn, Quận Nam Từ Liêm, Hà Nội | AN9: 09h00-11h00; 15h00-17h00 | AO9: 1-2 lần/tuần | AP9: 3 | AQ9: Xe máy | AS9: 45869 | BC9: X | BD9: 96600 | BE9: 84600 | BF9: 245158 | BG9: =SUM(BD9:BF9) -> 426358 | BH9: Hồ sơ vật lý và hồ sơ điện tử | BI9: Phát - Long | BJ9: 533810 | BK9: Thuỷ An | BL9: Phường An Cựu | BP9: X | BQ9: X | BR9: Bưu điện TT Thuận Hóa - Phú Xuân
A10: 8 | B10: 5310 | C10: Bưu điện TT Thuận Hóa - Phú Xuân | D10: Shop | E10: C005695891 | F10: Lê Thị Mỹ Hiền | G10: 04 Hoàng Văn Thụ, P. Xuân Phú TP. Huế Tỉnh Thừa Thiên Huế | H10: 0775555986 | J10: C005695891 | L10: HĐ170-HĐBC-BĐTP-LTMH | M10: 44890 | N10: Không xác định | O10: Không có | P10: 01 tháng/lần Thanh toán tại địa chỉ bên A | S10: Đang hoạt động | T10: PHẠM THỊ THANH UYÊN | U10: ETN037 | V10: GTG021 | W10: thư | X10: 0.05 | Y10: 0.07 | Z10: 1188 | AB10: 533810 | AC10: 533810_dungntt | AE10: Theo quy định TCT | AF10: Không có yêu cầu khác. | AJ10: đã thanh toán | AM10: 04 Hoàng Văn Thụ, P. Xuân Phú TP. Huế Tỉnh Thừa Thiên Huế | AP10: 2 | AR10: Khách hàng tự mang đến bưu cục | AS10: 45869 | BB10: X | BD10: 51200 | BE10: 1182500 | BF10: 986000 | BG10: =SUM(BD10:BF10) -> 2219700 | BH10: Hồ sơ vật lý và hồ sơ điện tử | BI10: Phát - Long | BJ10: 533810 | BK10: Thuỷ An | BL10: Phường An Cựu | BP10: X | BQ10: X | BR10: Bưu điện TT Thuận Hóa - Phú Xuân
A11: 9 | B11: 5310 | C11: Bưu điện TT Thuận Hóa - Phú Xuân | D11: SME | E11: T001799573 | F11: CTY CP BĐS MINH ĐIỀN VITAL | G11: Khu đô thị The Manor Crown, Xuân Phú, TP huế | H11: 0907024029 | I11: Đặng Mạnh Cường | J11: T001799573 | K11: 3301350500 | L11: HĐ394-HĐBC-BĐTPH-VITAL | M11: 44169 | N11: Không xác định | O11: Không có | P11: Thanh toán vào tháng sau | S11: Đang hoạt động | T11: HỒ VĂN KỲ | U11: ETN001 | X11: 0.06 | Y11: 0.07 | Z11: 820.8 | AB11: 533810 | AC11: 533810_dungntt | AD11: SỐ ĐT NTO GHI TRÊN ĐƠN HÀNG.TKS | AE11: Theo quy định TCT | AF11: Không có yêu cầu khác. | AJ11: 157.464 | AK11: đang làm thanh toán | AM11: Khu đô thị The Manor Crown, Xuân Phú, TP huế | AN11: 09h00-11h00; 15h00-17h00 | AO11: 1-2 lần/tuần | AP11: 2 | AQ11: Xe máy | AS11: 45869 | BC11: X | BD11: 357000 | BE11: 365200 | BF11: 208800 | BG11: =SUM(BD11:BF11) -> 931000 | BH11: Hồ sơ vật lý và hồ sơ điện tử | BI11: Phát - Long | BJ11: 533810 | BK11: Thuỷ An | BL11: Phường An Cựu | BP11: X | BQ11: X | BR11: Bưu điện TT Thuận Hóa - Phú Xuân
A12: 10 | B12: 5310 | C12: Bưu điện TT Thuận Hóa - Phú Xuân | D12: SME | E12: T001399385 | F12: CÔNG TY CỔ PHẦN VẬN TẢI VÀ DỊCH VỤ PETROLIMEX THỪA THIÊN HUẾ | H12: 02343812117 | I12: Chị Trang | J12: T001399385 | L12: 100/HĐBC-BĐTP/CTY PERTOLIMEX | M12: 06/06/2017 | N12: Không xác định | P12: 1 lần/ tháng | S12: Đang hoạt động | T12: PHẠM THỊ THANH UYÊN | U12: ETN013 | W12: TÀI LIỆU | X12: 0.14375 | Y12: 32 | Z12: 32150 | AB12: 533810 | AC12: 533810_dungntt | AD12: BƯU TÁ VUI LÒNG LH SĐT NGƯỜI NHẬN TRÊN BG ĐỂ PHÁT HÀNH | AE12: Theo quy định của TCT | AJ12: 1,983,636 | AK12: đang thanh toán | AM12: 13 Trần Thanh Mại, phường An Cựu | AN12: 14h00-16h00 | AO12: 1 lân / ngày | AP12: 35 | AQ12: Xe máy | AS12: 45862 | AV12: Khi có yêu cầu | BC12: X | BD12: 4097925 | BE12: 1407542 | BF12: 222700 | BG12: =SUM(BD12:BF12) -> 5728167 | BH12: Hồ sơ vật lý và hồ sơ điện tử | BI12: vũ - lan | BJ12: 533810 | BK12: Thuỷ An | BL12: Phường An Cựu | BP12: X | BQ12: X | BR12: Bưu điện TT Thuận Hóa - Phú Xuân
A13: 11 | B13: 5310 | C13: Bưu điện TT Thuận Hóa - Phú Xuân | D13: SME | E13: T001799834 | F13: CÔNG TY CỔ PHẦN XÂY DỰNG VÀ ĐẦU TƯ XUÂN PHÚ | G13: NHÀ 17 ĐƯỜNG SỐ 4 AN CỰU CITY, P. An Cựu TP. Huế Tỉnh Thừa Thiên Huế | H13: 0705358292 | I13: Lê Thanh Hà | J13: T001799834 | K13: 3301545034 | L13: HĐ377-HĐBC-BĐTPH-CTCPVXDĐTXP | M13: 44169 | N13: Không xác định | O13: Không có | P13: Thanh toán trong tháng sau | S13: Đang hoạt động | T13: HỒ VĂN KỲ | U13: ETN001 | X13: 0.58 | Y13: 0.1 | Z13: 5335.2 | AB13: 533810 | AC13: 533810_dungntt | AD13: BƯU TÁ LIÊN HỆ SĐT TRÊN BG ĐỂ PHÁT HÀNG | AE13: Theo quy định TCT | AF13: Không có yêu cầu khác. | AJ13: đã thanh toán | AM13: NHÀ 17 ĐƯỜNG SỐ 4 AN CỰU CITY, P. An Cựu TP. Huế Tỉnh Thừa Thiên Huế | AN13: 14h00-17h00 | AO13: 1-2 lần/tháng | AP13: 3 | AQ13: Xe máy | AS13: 45869 | BC13: X | BD13: 0 | BE13: 9600 | BF13: 37200 | BG13: =SUM(BD13:BF13) -> 46800 | BH13: Hồ sơ vật lý và hồ sơ điện tử | BI13: Bảo + Hương | BJ13: 533810 | BK13: Thuỷ An | BL13: Phường An Cựu | BP13: X | BQ13: x | BR13: Bưu điện TT Thuận Hóa - Phú Xuân
A14: 12 | B14: 5310 | C14: Bưu điện TT Thuận Hóa - Phú Xuân | D14: SME | E14: T001800268 | F14: TRƯỜNG CAO ĐẲNG Y TẾ | G14: 1 NGUYỄN TRƯỜNG TỘ, TP HUẾ | H14: 0234.3822414 | I14: Văn Thư | J14: T001800268 | K14: 3300369717 | L14: 253/2021/HĐBC/BĐTP-CĐYTE | M14: 44272 | N14: Không xác định | P14: 1 lần/ tháng | S14: Đang hoạt động | T14: HỒ VĂN KỲ | U14: ETN001, ETN013 | W14: Tài liệu | X14: 0.04 | Y14: 0.97 | Z14: 18101 | AB14: 533810 | AC14: 533810_dungntt | AD14: BƯU TÁ VUI LÒNG LIÊN HỆ SĐT NGƯỜI NHẬN TRÊN BƯU GỬI ĐỂ PHÁT HÀNG | AE14: Theo quy định của TCT | AJ14: đã thanh toán | AM14: 1 NGUYỄN TRƯỜNG TỘ, TP HUẾ | AN14: 14h-15h | AO14: 1 lần/ ngày | AP14: 29 | AQ14: xe máy | AS14: hằng ngày | AT14: BƯU TÁ VUI LÒNG LIÊN HỆ SĐT NGƯỜI NHẬN TRÊN BƯU GỬI ĐỂ PHÁT HÀNG | AU14: KHÔNG ĐƯỢC CẬP NHẬT KHỐNG TT PHÁT , NHẬP ĐẦY ĐỦ TT NGƯỜI NHẬN , NGƯỜI NHẬN THAY | BC14: X | BD14: 26000 | BE14: 0 | BF14: 0 | BG14: =SUM(BD14:BF14) -> 26000 | BH14: Hồ sơ vật lý và hồ sơ điện tử | BI14: Rà soát để điều chỉnh lại bàn giao trên CMS | BJ14: 533810 | BK14: Thuỷ An | BL14: Phường An Cựu | BP14: X | BQ14: X | BR14: Bưu điện TT Thuận Hóa - Phú Xuân
A15: 13 | B15: 5310 | C15: Bưu điện TT Thuận Hóa - Phú Xuân | D15: Shop | E15: C016607629 | F15: Cánh Buồm | G15: Lô A34 Đường số 2 KĐT An Cựu City, P. An Đông TP. Huế Tỉnh Thừa Thiên Huế | I15: Cánh Buồm | J15: C016607629 | P15: 1 lần/1 tháng | S15: Đang hoạt động | T15: PHẠM THỊ THANH UYÊN | U15: ETN011 | V15: GTG021 | W15: Tài liệu | X15: 0.077638889 | Y15: 2.4 | Z15: 65123.5 | AB15: 533810 | AC15: 533810_dungntt | AE15: Thực hiện theo quy định của TCT | AJ15: Đã thanh toán công nợ | AM15: Lô A34 Đường số 2 KĐT An Cựu City, P. An Đông TP. Huế Tỉnh Thừa Thiên Huế | AN15: 15h00-17h00 | AO15: 1 lần/ngày | AP15: 72 | AQ15: xe máy | AS15: 45856 | BC15: X | BD15: 741025 | BE15: 481435 | BF15: 0 | BG15: =SUM(BD15:BF15) -> 1222460 | BH15: Hồ sơ vật lý và hồ sơ điện tử | BI15: Phát - Long | BJ15: 533810 | BK15: Thuỷ An | BL15: Phường An Cựu | BP15: X | BQ15: R | BR15: Bưu điện TT Thuận Hóa - Phú Xuân
A16: 14 | B16: 5310 | C16: Bưu điện TT Thuận Hóa - Phú Xuân | D16: SME | E16: T005217327 | F16: Công Ty Cổ Phần BWB-chi Nhánh Huế | G16: Tầng 6 tháp The Manor Crown | I16: Tuyết | J16: T005217327 | K16: 0107763981-002 | P16: Thanh toán vào tháng sau | S16: Đang hoạt động | T16: PHẠM THỊ THANH UYÊN | U16: ETN001 | X16: 0.065 | Y16: 0.066666667 | Z16: 1231.2 | AB16: 533810 | AC16: 533810_dungntt | AE16: Theo quy định TCT | AF16: Không có yêu cầu khác. | AJ16: 31.752 | AK16: đang làm thanh toán | AM16: Tầng 6 tháp The Manor Crown | AN16: 09h00-11h00; 15h00-17h00 | AO16: 1-2 lần/tuần | AP16: 2 | AQ16: Xe máy | AS16: 45869 | BC16: X | BD16: 0 | BE16: 18000 | BF16: 0 | BG16: =SUM(BD16:BF16) -> 18000 | BH16: Hồ sơ vật lý và hồ sơ điện tử | BI16: Phát - Long | BJ16: 533810 | BK16: Thuỷ An | BL16: Phường An Cựu | BP16: X | BQ16: R | BR16: Bưu điện TT Thuận Hóa - Phú Xuân
A17: 15 | B17: 5310 | C17: Bưu điện TT Thuận Hóa - Phú Xuân | D17: Cá Nhân | E17: C018726221 | F17: Nguyễn Huyền Tôn Nữ Ái Vân | G17: 08 Tố Hữu, P. Xuân Phú , Quận Thuận Hóa, TP. Huế | H17: 0899489952 | J17: C018726221 | L17: 259.202TH5/HĐBC/BĐKVTHPX-NHTNAV | M17: 45952 | S17: Đang hoạt động | T17: NGUYỄN BÁ TRÀ MI | AB17: 533810 | AC17: 533810_dungntt | BD17: 204518 | BE17: 117295 | BF17: 79036 | BG17: =SUM(BD17:BF17) -> 400849 | BI17: Rà soát để bàn giao trên CMS | BJ17: 533810 | BK17: Thuỷ An | BL17: Phường An Cựu | BM17: X | BP17: X | BQ17: R | BR17: Bưu điện TT Thuận Hóa - Phú Xuân
A18: 16 | B18: 5310 | C18: Bưu điện TT Thuận Hóa - Phú Xuân | D18: Cá Nhân | E18: C018656707 | F18: Nguyễn Ngọc Phú | G18: 189 Bà Triệu - Thuận Hóa - Thành Phố Huế | H18: 0898254999 | J18: C018656707 | S18: Đang hoạt động | T18: NGUYỄN BÁ TRÀ MI | AB18: 533810 | AC18: 533810_dungntt | BD18: 59000 | BE18: 0 | BF18: 0 | BG18: =SUM(BD18:BF18) -> 59000 | BI18: Lan - Thắm | BJ18: 533810 | BK18: Thuỷ An | BL18: Phường An Cựu | BP18: X | BQ18: R | BR18: Bưu điện TT Thuận Hóa - Phú Xuân
A19: 17 | B19: 5310 | C19: Bưu điện TT Thuận Hóa - Phú Xuân | D19: Cá Nhân | E19: C018477419 | F19: Nhà May Duy Tuấn | G19: 134 Trường Chinh - Phường An Cựu - Thành Phố Huế | H19: 0908680906 | J19: C018477419 | T19: NGUYỄN BÁ TRÀ MI | AB19: 533810 | AC19: 533810_dungntt | BD19: 143523 | BE19: 145703 | BF19: 144945 | BG19: =SUM(BD19:BF19) -> 434171 | BI19: Lan - Thắm/Phát - Long | BJ19: 533810 | BK19: Thuỷ An | BL19: Phường An Cựu | BP19: X | BQ19: R | BR19: Bưu điện TT Thuận Hóa - Phú Xuân
A20: 18 | B20: 5310 | C20: Bưu điện TT Thuận Hóa - Phú Xuân | D20: Tổ Chức | E20: T018318911 | F20: CÔNG AN PHƯỜNG AN CỰU | G20: 18 Hoàng Quốc Việt | H20: 02343817234 | J20: T018318911 | L20: HĐ230.2025-HĐBC-PHBC-BĐTP-CAPHUONGANCUU | M20: 45887 | S20: Đang thực hiện | T20: NGUYỄN BÁ TRÀ MI | AB20: 533810 | AC20: 533810_dungntt | BD20: 135200 | BE20: 502345 | BF20: 249172 | BG20: =SUM(BD20:BF20) -> 886717 | BI20: Phát - Long | BJ20: 533810 | BK20: Thuỷ An | BL20: Phường An Cựu | BP20: X | BQ20: R | BR20: Bưu điện TT Thuận Hóa - Phú Xuân
A21: 19 | B21: 5310 | C21: Bưu điện TT Thuận Hóa - Phú Xuân | D21: Cá Nhân | E21: C018568551 | F21: CÔNG TY CỔ PHẦN TẬP ĐOÀN BẢO HIỂM DBV - CN HUẾ | G21: Tầng 2 tòa nhà 189 Phạm Văn Đồng, Phường Vỹ Dạ, Thành Phố Huế | H21: 097258523 | J21: C018568551 | L21: 249.202TH5/HĐBC/BĐKVTHPX-DBV | M21: 45931 | S21: Đang thực hiện | T21: NGUYỄN BÁ TRÀ MI | AB21: 533810 | AC21: 533810_dungntt | BD21: 493600 | BE21: 574300 | BF21: 215000 | BG21: =SUM(BD21:BF21) -> 1282900 | BI21: Rà soát để bàn giao trên CMS | BJ21: 533810 | BK21: Thuỷ An | BL21: Phường An Cựu | BP21: X | BQ21: R | BR21: Bưu điện TT Thuận Hóa - Phú Xuân
A22: 20 | B22: 5310 | C22: Bưu điện TT Thuận Hóa - Phú Xuân | D22: Cá Nhân | E22: C018388055 | F22: Shin shop | G22: phong chương phong điền | H22: 0764768555 | J22: C018388055 | L22: HĐ235.2025_HĐBC-BĐH_HTN | M22: 45908 | S22: Đang thực hiện | T22: NGUYỄN BÁ TRÀ MI | AB22: 533810 | AC22: 533810_dungntt | BD22: 94495 | BE22: 16400 | BF22: 28259 | BG22: =SUM(BD22:BF22) -> 139154 | BI22: Rà soát để bàn giao trên CMS | BJ22: 533810 | BK22: Thuỷ An | BL22: Phường An Cựu | BM22: X | BP22: X | BQ22: R | BR22: Bưu điện TT Thuận Hóa - Phú Xuân
A23: 21 | B23: 5310 | C23: Bưu điện TT Thuận Hóa - Phú Xuân | D23: Cá Nhân | E23: C018272260 | F23: đinh thị phượng | G23: bến xe phía nam phường an cựu | H23: 0814767134 | J23: C018272260 | L23: HĐ232.2025_HĐBC_BĐH_ĐTP | M23: 45887 | S23: Đang thực hiện | T23: NGUYỄN BÁ TRÀ MI | AB23: 533810 | AC23: 533810_dungntt | BD23: 0 | BE23: 601000 | BF23: 0 | BG23: =SUM(BD23:BF23) -> 601000 | BI23: Rà soát để bàn giao trên CMS | BJ23: 533810 | BK23: Thuỷ An | BL23: Phường An Cựu | BP23: X | BQ23: R | BR23: Bưu điện TT Thuận Hóa - Phú Xuân
A24: 22 | B24: 5310 | C24: Bưu điện TT Thuận Hóa - Phú Xuân | D24: Tổ Chức | E24: T018411531 | F24: Phú Xuân Travel | G24: 51 Bà Triệu, Vỹ Dạ, Thành Phố Huế | H24: 0902882168 | J24: T018411531 | L24: 239.2025/HĐBC/BĐKVTHPX-PXT | M24: 45909 | S24: Đang thực hiện | T24: NGUYỄN BÁ TRÀ MI | AB24: 533810 | AC24: 533810_dungntt | BD24: 45100 | BE24: 0 | BF24: 0 | BG24: =SUM(BD24:BF24) -> 45100 | BI24: Lan - Thắm | BJ24: 533810 | BK24: Thuỷ An | BL24: Phường An Cựu | BP24: X | BQ24: R | BR24: Bưu điện TT Thuận Hóa - Phú Xuân
A25: 23 | B25: 5310 | C25: Bưu điện TT Thuận Hóa - Phú Xuân | D25: Cá Nhân | E25: C018894162 | F25: ÁO DÀI ĐAN PHƯƠNG | G25: 08 Đường Bà Triệu, P. Phú Hội, Quận Phú Xuân | H25: 0914478999 | J25: C018894162 | L25: 264.2025/HĐBC/BĐKVTHPX-ADĐP | M25: 45976 | S25: Đang hoạt động | U25: ETN011 | V25: GTG071 | X25: 4373 | Y25: 2 | Z25: 208290 | AB25: 533810 | AC25: 533810_dungntt | AD25: hỗ trợ phát ngay khi đến, cám ơn. | BD25: 801395 | BE25: 694351 | BF25: 448215 | BG25: =SUM(BD25:BF25) -> 1943961 | BH25: Chưa có thông tin | BI25: Rà soát để điều chỉnh lại bàn giao trên CMS | BJ25: 533810 | BK25: Thuỷ An | BL25: Phường An Cựu | BP25: X | BQ25: R | BR25: Bưu điện TT Thuận Hóa - Phú Xuân
A26: 24 | B26: 5310 | C26: Bưu điện TT Thuận Hóa - Phú Xuân | D26: Tổ Chức | E26: T018894468 | F26: Văn Phòng HĐND Và UBND Phường An Cựu | G26: 67A Đường Hoàng Quốc Việt, P. An Cựu, Quận Phú Xuân | J26: T018894468 | L26: 262.2025/HĐBC/BĐKVTHPX-HĐN-UBNDPAC | M26: 45976 | S26: Đang hoạt động | U26: ETN001 | V26: 0 | X26: 120 | Y26: 3 | Z26: 32500 | AB26: 533810 | AC26: 533810_dungntt | AD26: 0 | BD26: 168600 | BE26: 498745 | BF26: 89200 | BG26: =SUM(BD26:BF26) -> 756545 | BI26: Rà soát để bàn giao trên CMS | BJ26: 533810 | BK26: Thuỷ An | BL26: Phường An Cựu | BP26: X | BQ26: R | BR26: Bưu điện TT Thuận Hóa - Phú Xuân
A27: 25 | B27: 5310 | C27: Bưu điện TT Thuận Hóa - Phú Xuân | D27: Cá Nhân | E27: C019136875 | F27: May store | G27: số nhà 18 kiệt 154 bà triệu, Phường Thuận Hóa, TP Huế | H27: 0365156019 | J27: C019136875 | L27: 285/2025/HĐ_BC-PHBC/BĐTP-MAYSTORE | M27: 46023 | S27: Đang hoạt động | T27: NGUYỄN BÁ TRÀ MI | U27: CTN009; CTN007 | V27: GTG021; GTG047;GTG021 | X27: 774.02914 | Y27: 398 | Z27: 8262457 | AB27: 533810 | AC27: 533810_dungntt | AD27: Không cho xem hàng, gọi cho người gửi trước khi chuyển hoàn | BD27: 0 | BE27: 8262457 | BF27: 4628564 | BG27: =SUM(BD27:BF27) -> 12891021 | BI27: Rà soát để bàn giao trên CMS | BJ27: 533810 | BK27: Thuỷ An | BL27: Phường An Cựu | BM27: X | BP27: X | BR27: Bưu điện TT Thuận Hóa - Phú Xuân
A28: 26 | B28: 5310 | C28: Bưu điện TT Thuận Hóa - Phú Xuân | D28: Cá Nhân | E28: C001395300 | F28: Cô Lộc | G28: 4/4/4 Kiệt 33 An Dương Vương An Cựu TP Huế | H28: 0918581215 | J28: C001395300 | L28: 49/HĐBC/BĐTPH-CL | M28: 44256 | S28: Đang hoạt động | T28: PHẠM THỊ THANH UYÊN | U28: CTN001; CTN007 | V28: GTG021; GTG071 | X28: 861.35211 | Y28: 41 | Z28: 1974993 | AB28: 533810 | AC28: 533810_dungntt | AD28: gọi sđt trên đơn hàng | BD28: 0 | BE28: 1974993 | BF28: 848485 | BG28: =SUM(BD28:BF28) -> 2823478 | BI28: Phát - Long | BJ28: 533810 | BK28: Thuỷ An | BL28: Phường An Cựu | BP28: X | BR28: Bưu điện TT Thuận Hóa - Phú Xuân
A29: 27 | B29: 5310 | C29: Bưu điện TT Thuận Hóa - Phú Xuân | D29: Cá Nhân | E29: C019370201 | F29: Võ Nhật Bình | G29: Thôn Bằng Lãng, Thuỷ Bằng, Phường Thủy Xuân, TP Huế | H29: 0867676257 | J29: C019370201 | L29: 01/2026-HĐ/BCCP/BDTPHUE-BDAC-DNB | M29: 46050 | S29: Đang hoạt động | T29: NGUYỄN BÁ TRÀ MI | U29: CTN009 | V29: GTG021 | X29: 1300 | Y29: 5 | Z29: 166668 | AB29: 533810 | AC29: 533810_dungntt | AD29: Hàng dễ vỡ, vui lòng nhẹ tay; Cho xem hàng không cho đụng vào hàng | BD29: 0 | BE29: 166668 | BF29: 277780 | BG29: =SUM(BD29:BF29) -> 444448 | BI29: Rà soát để bàn giao trên CMS | BJ29: 533810 | BK29: Thuỷ An | BL29: Phường An Cựu | BM29: X | BP29: X | BR29: Bưu điện TT Thuận Hóa - Phú Xuân
A30: 28 | B30: 5310 | C30: Bưu điện TT Thuận Hóa - Phú Xuân | D30: Key Account | E30: T017963860 | F30: Trung Tâm HCC Phường An Cựu | G30: 67A Hoàng Quốc Việt, Phường An Cựu, TP Huế | I30: Phan Đăng Phú Khánh | J30: T017963860 | L30: 175/2025/HĐ_BC-PHBC/BĐTT-TTPVHCCPAC | M30: 45839 | N30: Không xác định | O30: Không có | P30: 01 tháng/lần Trong 03 - 05 ngày làm việc tiếp theo kể từ ngày nhận được hoá đơn GTGT hợp lệ | S30: Đang hoạt động | T30: ĐẶNG TUẤN VŨ | U30: Dịch vụ HCC, luân chuyển hồ sơ HCC, KT1, EMS, Chuyển phát bưu phẩm trong nước và quốc tế | W30: Tài liệu | X30: 0.05125 | Y30: 0.4 | Z30: 11000 | AA30: My VNP | AB30: 533810 | AC30: 533810_dungntt | AE30: Thực hiện theo quy định của TCT | AJ30: 356400 | AK30: Đang làm thanh toán | BB30: X | BD30: 1091340 | BE30: 1058397 | BF30: 399441 | BG30: =SUM(BD30:BF30) -> 2549178 | BH30: Hồ sơ vật lý và hồ sơ điện tử | BI30: Lan - Thắm | BJ30: 533810 | BK30: Thuỷ An | BL30: Phường An Cựu | BM30: X | BP30: X | BQ30: X | BR30: Bưu điện TT Thuận Hóa - Phú Xuân
A31: 29 | B31: 5310 | C31: Bưu điện TT Thuận Hóa - Phú Xuân | D31: Tổ Chức | E31: T019531120 | F31: CÔNG TY TNHH DỊCH VỤ SẢN XUẤT PDM VIỆT NAM | G31: 314 Văn Thánh, phường Kim Long, Thành Phố Huế, Việt Nam | J31: T019531120 | L31: 18 /2026/ HĐ¬BC-PHBC/BĐTPHUE-PDM | M31: 46079 | S31: Đang hoạt động | T31: NGUYỄN BÁ TRÀ MI | AB31: 533810 | BD31: 0 | BE31: 0 | BF31: 0 | BG31: =SUM(BD31:BF31) -> 0 | BI31: Rà soát để bàn giao trên CMS | BJ31: 533810 | BK31: Thuỷ An | BL31: Phường An Cựu | BR31: Bưu điện TT Thuận Hóa - Phú Xuân
A32: 30 | B32: 5310 | C32: Bưu điện TT Thuận Hóa - Phú Xuân | D32: Shop | E32: C017177801 | F32: Duyên Trần | G32: xóm 11, X. Phú Mậu H. Phú Vang Tỉnh Thừa Thiên Huế | H32: 0775875875 | I32: Trần Thị Ái Duyên | J32: C017177801 | L32: HĐ56.2025.HĐBC-BĐTTTHPX-DT | M32: 45740 | N32: Không xác định | O32: Không có | P32: Thanh toán vào tháng sau | Q32: Thứ 2,4,6 hàng tuần Chuyển khoản | R32: 0825898192 MBBank Trần Thị Ái Duyên | S32: Đang hoạt động | T32: PHẠM THỊ THANH UYÊN | U32: CTN007, CTN009 | V32: GTG021 | W32: Mỹ phẩm | X32: 0.46 | Y32: 0.57 | Z32: 8420 | AB32: 536790 | AC32: 536790_menpt | AE32: Theo quy định TCT | AF32: Không có yêu cầu khác. | AJ32: Đã thanh toán | AM32: xóm 11, X. Phú Mậu H. Phú Vang Tỉnh Thừa Thiên Huế | AP32: 17 | AR32: Khách hàng tự mang đến bưu cục | AS32: 45869 | BB32: X | BD32: 19000 | BE32: 82834 | BF32: 0 | BG32: =SUM(BD32:BF32) -> 101834 | BH32: Chưa có thông tin | BI32: Bảo + Ni | BJ32: 536790 | BK32: Phú Mậu | BL32: Phường Dương Nỗ | BM32: X | BP32: X | BQ32: X | BR32: Bưu điện TT Thuận Hóa - Phú Xuân
A33: 31 | B33: 5310 | C33: Bưu điện TT Thuận Hóa - Phú Xuân | D33: Shop | E33: C016429937 | F33: Nguyễn Thị Phương Thảo | G33: xóm 11, làng Thanh Tiên, xã Phú Mậu, TP Huế | H33: 0898194881 | J33: C016429937 | L33: HĐ221-HĐBC-BĐTP-NTPT | M33: 45637 | N33: Không xác định | O33: Không có | P33: Trong 03 - 05 ngày làm việc tiếp theo kể từ ngày nhận được hoá đơn GTGT hợp lệ | S33: Đang hoạt động | T33: PHẠM THỊ THANH UYÊN | U33: CTN001, CTN007 | V33: GTG021 | W33: hoa giấy, chông | X33: 1.27 | Y33: 0.2 | Z33: 8039.87 | AB33: 536790 | AC33: 536790_menpt | AE33: Theo quy định TCT | AF33: Không có yêu cầu khác. | AJ33: Đã thanh toán | AM33: xóm 11, làng Thanh Tiên, xã Phú Mậu, TP Huế | AP33: 6 | AR33: Khách hàng tự mang đến bưu cục | AS33: 45869 | BB33: X | BD33: 9237000 | BE33: 5179300 | BF33: 2331600 | BG33: =SUM(BD33:BF33) -> 16747900 | BH33: Hồ sơ vật lý và hồ sơ điện tử | BI33: Bảo + Ni | BJ33: 536790 | BK33: Phú Mậu | BL33: Phường Dương Nỗ | BP33: X | BQ33: X | BR33: Bưu điện TT Thuận Hóa - Phú Xuân
A34: 32 | B34: 5310 | C34: Bưu điện TT Thuận Hóa - Phú Xuân | D34: Shop | E34: C016227458 | F34: Võ Thị Mỹ Phố | G34: kiệt 5 nguyễn hữu cảnh | H34: 0346429532 | I34: Võ Thị Mỹ Phố | J34: C016227458 | L34: HĐ190.2024_HĐBC_BĐTPH-VTMP | M34: 45607 | N34: Không xác định | P34: Thanh toán cước khi chi trả cod | Q34: CK qua ngân hàng (2,4,6 hằng tuần) | R34: 88184868 MB Bank | S34: Đang hoạt động | T34: PHẠM THỊ THANH UYÊN | U34: CTN007 | V34: GTG021 | W34: Ti Giả Avent | X34: 1.5175 | Y34: 0.066666667 | Z34: 1089.3333 | AB34: 536790 | AC34: 536790_menpt | AE34: Theo quy định TCT | AF34: Không có yêu cầu khác. | AJ34: 139512 | AK34: đang làm thanh toán | AM34: kiệt 5 nguyễn hữu cảnh | AN34: 15h00-16h00 | AO34: 2-3 lần/tuần | AP34: 2 | AQ34: Xe máy | AS34: 45869 | BB34: X | BD34: 161807 | BE34: 0 | BF34: 0 | BG34: =SUM(BD34:BF34) -> 161807 | BH34: Hồ sơ vật lý và hồ sơ điện tử | BI34: Rà soát để điều chỉnh lại bàn giao trên CMS | BJ34: 536790 | BK34: Phú Mậu | BL34: Phường Dương Nỗ | BM34: X | BP34: X | BQ34: X | BR34: Bưu điện TT Thuận Hóa - Phú Xuân
A35: 33 | B35: 5310 | C35: Bưu điện TT Thuận Hóa - Phú Xuân | D35: Cá Nhân | E35: C018988315 | F35: Hoài Trinh | G35: Đối diện xóm 6, Mậu Tài, P. Dương Nỗ, Quận Thuận Hóa | H35: 0774507105 | J35: C018988315 | S35: Đang hoạt động | U35: CTN007 | V35: GTG021 | X35: 162300 | Y35: 76 | Z35: 3073500 | AB35: 536790 | AC35: 536790_menpt | AD35: 0 | BD35: 4095235 | BE35: 3533867 | BF35: 665366 | BG35: =SUM(BD35:BF35) -> 8294468 | BI35: Rà soát để bàn giao trên CMS | BJ35: 536790 | BK35: Phú Mậu | BL35: Phường Dương Nỗ | BR35: Bưu điện TT Thuận Hóa - Phú Xuân
A36: 34 | B36: 5310 | C36: Bưu điện TT Thuận Hóa - Phú Xuân | D36: Cá Nhân | E36: C019314788 | F36: Nguyễn Hiếu | G36: Thanh Vinh, phường Dương Nỗ, TP Huế | H36: 0343318436 | J36: C019314788 | L36: HĐ08-2026-HĐBC-BĐKVTHPX- NH | M36: 46042 | S36: Đang hoạt động | T36: HOÀNG VĂN DUY | U36: CTN007; ETN031 | V36: GTG021 | X36: 1606.25 | Y36: 8 | Z36: 4279200 | AB36: 536790 | AC36: 536790_menpt | AD36: 0 | BD36: 0 | BE36: 4279200 | BF36: 371000 | BG36: =SUM(BD36:BF36) -> 4650200 | BI36: Rà soát để bàn giao trên CMS | BJ36: 536790 | BK36: Phú Mậu | BL36: Phường Dương Nỗ | BP36: X | BR36: Bưu điện TT Thuận Hóa - Phú Xuân
A37: 35 | B37: 5310 | C37: Bưu điện TT Thuận Hóa - Phú Xuân | D37: Cá Nhân | E37: C019416597 | F37: nguyễn hữu thảo | G37: kiệt 19, trung đông, phú thượng, tp huế | H37: 0777550775 | J37: C019416597 | L37: C019416597 | M37: 46056 | S37: Đang hoạt động | T37: HOÀNG VĂN DUY | X37: 900 | Y37: 1 | Z37: 36000 | AB37: 536790 | BD37: 0 | BE37: 0 | BF37: 36000 | BG37: =SUM(BD37:BF37) -> 36000 | BI37: Rà soát để bàn giao trên CMS | BJ37: 536790 | BK37: Phú Mậu | BL37: Phường Dương Nỗ | BP37: X | BR37: Bưu điện TT Thuận Hóa - Phú Xuân
A38: 36 | B38: 5310 | C38: Bưu điện TT Thuận Hóa - Phú Xuân | D38: Key Account | E38: T017963459 | F38: Trung Tâm HCC Phường Dương Nỗ | G38: Tổ dân phố Mậu Tài, phường Dương Nỗ, TP. Huế | H38: 0234676722 | I38: Trần Quang Dũng | J38: T017963459 | L38: 172/2025/HĐ_BC-PHBC/BĐTT-TTPVHCCPDN | M38: 45839 | N38: Không xác định | O38: Không có | P38: 01 tháng/lần Trong 03 - 05 ngày làm việc tiếp theo kể từ ngày nhận được hoá đơn GTGT hợp lệ | S38: Đang hoạt động | T38: ĐẶNG TUẤN VŨ | U38: Dịch vụ HCC, luân chuyển hồ sơ HCC, KT1, EMS, Chuyển phát bưu phẩm trong nước và quốc tế | W38: Tài liệu | X38: 0.067714286 | Y38: 0.46666667 | Z38: 12133.333 | AA38: My VNP | AB38: 536790 | AC38: 536790_menpt | AE38: Thực hiện theo quy định của TCT | AJ38: 393120 | AK38: Đang làm thanh toán | BB38: X | BD38: 952200 | BE38: 768500 | BF38: 271500 | BG38: =SUM(BD38:BF38) -> 1992200 | BH38: Hồ sơ vật lý và hồ sơ điện tử | BI38: Bảo + Ni | BJ38: 536790 | BK38: Phú Mậu | BL38: Phường Dương Nỗ | BP38: X | BQ38: X | BR38: Bưu điện TT Thuận Hóa - Phú Xuân
A39: 37 | B39: 5310 | C39: Bưu điện TT Thuận Hóa - Phú Xuân | D39: Tổ Chức | E39: T018859231 | F39: Công An Phường Hoá Châu | G39: TDP Vân Quật Thượng, X. Hương Phong, TX. Hương Trà | H39: 0986244166 | J39: T018859231 | S39: Đang hoạt động | U39: KT1007 | V39: 0 | X39: 210 | Y39: 10 | Z39: 274763 | AB39: 535350 | AC39: 535350_lannh | AD39: 0 | BD39: 557275 | BE39: 572124 | BF39: 185990 | BG39: =SUM(BD39:BF39) -> 1315389 | BH39: Hồ sơ vật lý | BI39: Rà soát để điều chỉnh lại bàn giao trên CMS | BJ39: 535350 | BK39: Hương Vinh | BL39: Phường Hóa Châu | BM39: X | BR39: Bưu điện TT Thuận Hóa - Phú Xuân
A40: 38 | B40: 5310 | C40: Bưu điện TT Thuận Hóa - Phú Xuân | D40: Key Account | E40: T017963122 | F40: UBND Phường Hóa Châu | G40: đường Thanh Hà, TDP Tây Thành, phường Hóa Châu, TP. Huế | I40: Võ Việt Đức | J40: T017963122 | L40: 191/2025/HĐ_BC-PHBC/BĐTT-VPUBHC | M40: 45839 | N40: Không xác định | O40: Không có | P40: 01 tháng/lần Trong 03 - 05 ngày làm việc tiếp theo kể từ ngày nhận được hoá đơn GTGT hợp lệ | S40: Đang hoạt động | T40: ĐẶNG TUẤN VŨ | U40: Dịch vụ HCC, luân chuyển hồ sơ HCC, KT1, EMS, Chuyển phát bưu phẩm trong nước và quốc tế | W40: Tài liệu | X40: 0 | Y40: 0.033333333 | Z40: 0 | AA40: My VNP | AB40: 535350 | AC40: 535350_lannh | AE40: Thực hiện theo quy định của TCT | AJ40: Không có | AK40: Đang làm thanh toán | BB40: X | BD40: 195745 | BE40: 0 | BF40: 0 | BG40: =SUM(BD40:BF40) -> 195745 | BH40: Hồ sơ vật lý và hồ sơ điện tử | BI40: Bảo + Ni | BJ40: 535350 | BK40: Hương Vinh | BL40: Phường Hóa Châu | BP40: X | BQ40: X | BR40: Bưu điện TT Thuận Hóa - Phú Xuân
A41: 39 | B41: 5310 | C41: Bưu điện TT Thuận Hóa - Phú Xuân | D41: Key Account | E41: T017963286 | F41: Trung Tâm HCC Phường Hóa Châu | G41: đường Thanh Hà, TDP Tây Thành, phường Hóa Châu, TP. Huế | I41: Võ Việt Đức | J41: T017963286 | L41: 170/2025/HĐ_BC-PHBC/BĐTT-TTPVHCCPHC | M41: 45839 | N41: Không xác định | O41: Không có | P41: 01 tháng/lần Trong 03 - 05 ngày làm việc tiếp theo kể từ ngày nhận được hoá đơn GTGT hợp lệ | S41: Đang hoạt động | T41: ĐẶNG TUẤN VŨ | U41: Dịch vụ HCC, luân chuyển hồ sơ HCC, KT1, EMS, Chuyển phát bưu phẩm trong nước và quốc tế | W41: Tài liệu | X41: 0 | Y41: 1.8333333 | Z41: 0 | AA41: My VNP | AB41: 530000 | AC41: 530000_miennt | AE41: Thực hiện theo quy định của TCT | AJ41: Không có | AK41: Đang làm thanh toán | BB41: X | BD41: 470045 | BE41: 31000 | BF41: 0 | BG41: =SUM(BD41:BF41) -> 501045 | BH41: Hồ sơ vật lý và hồ sơ điện tử | BI41: Bảo + Ni | BJ41: 535350 | BK41: Hương Vinh | BL41: Phường Hóa Châu | BP41: X | BQ41: X | BR41: Bưu điện TT Thuận Hóa - Phú Xuân
A42: 40 | B42: 5310 | C42: Bưu điện TT Thuận Hóa - Phú Xuân | D42: Key Account | E42: T001800047 | F42: Trung Tâm Pháp Y Tâm Thần Khu Vực Miền Trung | G42: 39 Phạm Thị Liên, Phường Kim Long, TP Huế | H42: 0935772389 | J42: T001800047 | L42: 160/2021/HĐBC/BĐTP-TTPHAPY | M42: 15/03/2021 | N42: Không xác định | P42: Thanh toán vào tháng sau | T42: HỒ VĂN KỲ | U42: ETN001 | W42: Tài liệu | X42: 0.04 | Y42: 1.5 | Z42: 22277 | AB42: 532950 | AC42: 532950_trangbtb | AD42: 0 | AE42: Theo quy định của TCT | AJ42: 668.304 | AK42: đang thanh toán | AM42: 39 Phạm Thị Liên, Phường Kim Long, TP Huế | AN42: 13h30-14h30 | AO42: 1-2 lần/tuần | AP42: 45 | AQ42: Xe máy | AS42: 45858 | BC42: X | BD42: 960400 | BE42: 1095600 | BF42: 339600 | BG42: =SUM(BD42:BF42) -> 2395600 | BH42: Hồ sơ vật lý và hồ sơ điện tử | BI42: Minh - Long | BJ42: 532950 | BK42: An Hoà | BL42: Phường Hương An | BP42: X | BQ42: X | BR42: Bưu điện TT Thuận Hóa - Phú Xuân
A43: 41 | B43: 5310 | C43: Bưu điện TT Thuận Hóa - Phú Xuân | D43: Shop | E43: C001396353 | F43: Nguyễn Ngọc Cầu | G43: Tổ 13 KHu vực 5 An Hòa, TP Huế, P. An Hòa, Quận Phú Xuân, TP. Huế | H43: 0387848315 | I43: Nguyễn Ngọc Cầu | J43: C001396353 | L43: 141/2021/HĐBC/BĐTPH-NNCAU | M43: 44270 | N43: Không xác định | P43: Thanh toán cước KHi chi trả cod | Q43: Thanh toán TM theo yêu cầu KH | S43: Đang hoạt động | T43: PHẠM THỊ THANH UYÊN | U43: CTN001 | V43: GTG021 | W43: CÂY CẢNH | X43: 0.72484615 | Y43: 2.1666667 | Z43: 71305.1 | AB43: 532950 | AC43: 532950_trangbtb | AE43: Thực hiện theo quy định của TCT | AJ43: Đã thanh toán công nợ | AM43: Tổ 13 KHu vực 5 An Hòa, TP Huế, P. An Hòa, Quận Phú Xuân, TP. Huế | AP43: 65 | AS43: 45856 | BB43: X | BD43: 80750 | BE43: 84006 | BF43: 0 | BG43: =SUM(BD43:BF43) -> 164756 | BH43: Hồ sơ vật lý và hồ sơ điện tử | BI43: Minh - Long | BJ43: 532950 | BK43: An Hoà | BL43: Phường Hương An | BP43: X | BQ43: X | BR43: Bưu điện TT Thuận Hóa - Phú Xuân
A44: 42 | B44: 5310 | C44: Bưu điện TT Thuận Hóa - Phú Xuân | D44: Shop | E44: C016958917 | F44: Trần như quỳnh | G44: 448 Lê Duẫn | H44: 0932415390 | I44: Trần Như Quỳnh | J44: C016958917 | L44: HĐ23-2025-HĐBH-BĐTTHPX-SUNDAY | M44: 45709 | N44: Không xác định | P44: Thanh toán khi nhận tiền cod | Q44: CK qua ngân hàng (2,4,6 hằng tuần) | R44: 0932415390 MB Bank | S44: Đang hoạt động | T44: PHẠM THỊ THANH UYÊN | U44: CTN009 | X44: 0.5 | Y44: 0.033333333 | Z44: 684 | AB44: 532950 | AC44: 532950_trangbtb | AE44: Theo quy định TCT | AF44: Không có yêu cầu khác. | AJ44: Đã thanh toán | AM44: 448 Lê Duẫn | AP44: 1 | AR44: Khách hàng tự mang đến bưu cục | AS44: 45812 | BB44: X | BD44: 16400 | BE44: 19000 | BF44: 56145 | BG44: =SUM(BD44:BF44) -> 91545 | BH44: Hồ sơ vật lý và hồ sơ điện tử | BI44: Minh - Long | BJ44: 532950 | BK44: An Hoà | BL44: Phường Hương An | BM44: X | BP44: X | BQ44: X | BR44: Bưu điện TT Thuận Hóa - Phú Xuân
A45: 43 | B45: 5310 | C45: Bưu điện TT Thuận Hóa - Phú Xuân | D45: SME | E45: C007520178 | F45: Trung Tâm Công Tác Xã Hội Và Quỹ Bảo Trợ Trẻ Em Tỉnh Thừa Thiên Huế | G45: 65 Đặng Tất, An Hoà, Thừa Thiên Huế | H45: 0775518598 | J45: C007520178 | K45: 3301723537 | L45: HĐ006.2024-HĐBC-BĐTPH-QBT | M45: 45302 | N45: Không xác định | P45: Thanh toán vào tháng sau | S45: Đang hoạt động | T45: PHẠM THỊ THANH UYÊN | U45: ETN001 | X45: 0.05365 | Y45: 0.66666667 | Z45: 8323.2 | AB45: 532950 | AC45: 532950_trangbtb | AE45: Theo quy định TCT | AF45: Không có yêu cầu khác. | AJ45: Đã thanh toán | AM45: 65 Đặng Tất, An Hoà, Thừa Thiên Huế | AN45: 14h00-15h00 | AO45: 2-3 lần/tuần | AP45: 5 | AQ45: Xe máy | AS45: 45869 | BC45: X | BD45: 138000 | BE45: 300200 | BF45: 96000 | BG45: =SUM(BD45:BF45) -> 534200 | BH45: Hồ sơ vật lý và hồ sơ điện tử | BI45: Minh - Long | BJ45: 532950 | BK45: An Hoà | BL45: Phường Hương An | BP45: X | BQ45: X | BR45: Bưu điện TT Thuận Hóa - Phú Xuân
A46: 44 | B46: 5310 | C46: Bưu điện TT Thuận Hóa - Phú Xuân | D46: Shop | E46: C002139719 | F46: Trần Thanh Hải | G46: 157 Tăng Bạt Hổ, Phú Thuận,TP Huế | H46: 0901172224 | J46: C002139719 | L46: 317/2021/HĐBC/BĐTPH-TTHAI | M46: 44286 | N46: Không xác định | O46: Không có | P46: 01 tuần/lần Chuyển khoản | Q46: 01 tuần/lần Chuyển khoản | R46: 55110000788469 BIDV Trần Thanh Hải | S46: Đang hoạt động | T46: HỒ VĂN KỲ | U46: CTN007, CTN009, ETN011, CTN001 | V46: GTG021 | W46: Đồ gốm xưa, mảnh sành sứ | X46: 1.83 | Y46: 0.37 | Z46: 13549.93 | AB46: 532950 | AC46: 532950_trangbtb | AD46: *BƯU TÁ LIÊN HỆ THEO SĐT TRÊN BƯU GỬI" | AE46: Theo quy định TCT | AF46: Không có yêu cầu khác. | AJ46: Đã thanh toán | AM46: 157 Tăng Bạt Hổ, Phú Thuận,TP Huế | AP46: 11 | AR46: Khách hàng tự mang đến bưu cục | AS46: 45869 | BC46: X | BD46: 721158 | BE46: 465156 | BF46: 67275 | BG46: =SUM(BD46:BF46) -> 1253589 | BH46: Hồ sơ vật lý và hồ sơ điện tử | BI46: Minh - Long | BJ46: 532950 | BK46: An Hoà | BL46: Phường Hương An | BM46: X | BP46: X | BQ46: X | BR46: Bưu điện TT Thuận Hóa - Phú Xuân
A47: 45 | B47: 5310 | C47: Bưu điện TT Thuận Hóa - Phú Xuân | D47: Key Account | E47: T001800991 | F47: Cục Quản Lý Thị Trường Tỉnh Thừa Thiên Huế. | G47: 126 Nguyễn Văn Linh, An Hoà, Tp. Huế. | H47: 0765240817 | J47: T001800991 | K47: 3301037993 | L47: 150/2021/HĐBC/BĐTPH-CUC QLTT | M47: 44270 | N47: Không xác định | O47: Không có | P47: Thanh toán khi nhận tiền cod | S47: Đang hoạt động | T47: HỒ VĂN KỲ | U47: CTN001, ETN001 | W47: bình giữ nhiệt, đồ dùng | X47: 0.37 | Y47: 0.6 | Z47: 10208.07 | AB47: 532950 | AC47: 532950_trangbtb | AE47: Theo quy định TCT | AF47: Không có yêu cầu khác. | AJ47: Đã thanh toán | AM47: 126 Nguyễn Văn Linh, An Hoà, Tp. Huế. | AN47: 14h00-15h00 | AO47: 2-3 lần/tuần | AP47: 18 | AQ47: Xe máy | AS47: 45869 | BC47: X | BD47: 157500 | BE47: 437400 | BF47: 67600 | BG47: =SUM(BD47:BF47) -> 662500 | BH47: Hồ sơ vật lý và hồ sơ điện tử | BI47: Minh - Long | BJ47: 532950 | BK47: An Hoà | BL47: Phường Hương An | BP47: X | BQ47: X | BR47: Bưu điện TT Thuận Hóa - Phú Xuân
A48: 46 | B48: 5310 | C48: Bưu điện TT Thuận Hóa - Phú Xuân | D48: SME | E48: C001911309 | F48: Công Ty CP Vật Tư Nông Nghiệp TT Huế | G48: 22 Tản Đà, Hương Sơ, TP Huế | H48: 023435588330 | I48: Trần Thuyên | J48: C001911309 | K48: 3300101244 | L48: 01/HĐBC/BĐTPH-VTNN | M48: 44197 | N48: Không xác định | O48: Không có | P48: Thanh toán khi nhận tiền cod | S48: Đang hoạt động | T48: PHẠM THỊ THANH UYÊN | U48: CTN001, ETN001, ETN011 | X48: 0.46 | Y48: 0.5 | Z48: 9639.27 | AB48: 532950 | AC48: 532950_trangbtb | AE48: Theo quy định TCT | AF48: Không có yêu cầu khác. | AJ48: Đã thanh toán | AM48: 22 Tản Đà, Hương Sơ, TP Huế | AN48: 14h00-15h00 | AO48: 2-3 lần/tuần | AP48: 15 | AQ48: Xe máy | AS48: 45869 | BC48: X | BD48: 63600 | BE48: 0 | BF48: 11200 | BG48: =SUM(BD48:BF48) -> 74800 | BH48: Hồ sơ vật lý và hồ sơ điện tử | BI48: Minh - Long | BJ48: 532950 | BK48: An Hoà | BL48: Phường Hương An | BP48: X | BQ48: X | BR48: Bưu điện TT Thuận Hóa - Phú Xuân
A49: 47 | B49: 5310 | C49: Bưu điện TT Thuận Hóa - Phú Xuân | D49: SME | E49: T017135421 | F49: Công Ty TNHH Sản Xuất TM Và DV Duy Trí | G49: Số 9, Đường số 1, Cụm công nghiệp An Hòa, P An Hòa, Q Phú Xuân | H49: 0987543284 | I49: Trương Đình Dũng | J49: T017135421 | K49: 3300415138 | L49: HĐ61.2025_HĐBC_BĐTTTHPX_CTDT | M49: 45741 | N49: Không xác định | O49: Không có | P49: Thanh toán vào tháng sau | S49: Đang hoạt động | T49: PHẠM THỊ THANH UYÊN | U49: RTN001 | W49: Tài liệu | X49: 0.24 | Y49: 0.5 | Z49: 7261.93 | AB49: 532950 | AC49: 532950_trangbtb | AE49: Theo quy định TCT | AF49: Không có yêu cầu khác. | AJ49: Đã thanh toán | AM49: Số 9, Đường số 1, Cụm công nghiệp An Hòa, P An Hòa, Q Phú Xuân | AN49: 14h00-15h00 | AO49: 2-3 lần/tuần | AP49: 15 | AQ49: Xe máy | AS49: 45869 | BB49: X | BD49: 177514 | BE49: 214880 | BF49: 76050 | BG49: =SUM(BD49:BF49) -> 468444 | BH49: Hồ sơ vật lý và hồ sơ điện tử | BI49: Minh - Long | BJ49: 532950 | BK49: An Hoà | BL49: Phường Hương An | BP49: X | BQ49: x | BR49: Bưu điện TT Thuận Hóa - Phú Xuân
A50: 48 | B50: 5310 | C50: Bưu điện TT Thuận Hóa - Phú Xuân | D50: Shop | E50: C016285328 | F50: Nguyễn Duy Nam | G50: 19 Mai Khắc Đôn, P. Kim Long TP. Huế Tỉnh Thừa Thiên Huế | H50: 0979852346 | J50: C016285328 | L50: HĐ199.2024_HĐBC_BĐTPH_NDN | M50: 45614 | N50: Không xác định | O50: Không có | P50: Thanh toán tại Bưu điện | R50: 4002205203633 Agribank Nguyễn Duy Nam | S50: Đang hoạt động | T50: PHẠM THỊ THANH UYÊN | U50: CTN009 | V50: GTG021 | W50: Phụ tùng xe đạp | X50: 2.43 | Y50: 0.17 | Z50: 4932 | AB50: 532950 | AC50: 532950_trangbtb | AD50: bta liên hệ sdt trên bưu gửi | AE50: Theo quy định TCT | AF50: Không có yêu cầu khác. | AJ50: Đã thanh toán | AM50: 19 Mai Khắc Đôn, P. Kim Long TP. Huế Tỉnh Thừa Thiên Huế | AP50: 5 | AR50: Khách hàng tự mang đến bưu cục | AS50: 45869 | BC50: X | BD50: 473490 | BE50: 405000 | BF50: 174000 | BG50: =SUM(BD50:BF50) -> 1052490 | BH50: Hồ sơ vật lý và hồ sơ điện tử | BI50: Minh - Long | BJ50: 532950 | BK50: An Hoà | BL50: Phường Hương An | BP50: X | BQ50: x | BR50: Bưu điện TT Thuận Hóa - Phú Xuân
A51: 49 | B51: 5310 | C51: Bưu điện TT Thuận Hóa - Phú Xuân | D51: Shop | E51: C017146248 | F51: Nguyễn Thị Như Lệ | G51: 10/252 lý thái tổ , p an hòa, quận phú xuân, tp huế | H51: 0704563053 | J51: C017146248 | L51: C017146248_HĐ45.2025_HĐBC_BĐTTTHPX_NTNL | M51: 45735 | N51: Không xác định | O51: Không có | P51: Thanh toán khi nhận tiền cod | Q51: Thứ 2.4.6 hàng tuần Chuyển khoản | R51: 5510745334 BIDV Nguyễn Thị Như Lệ | S51: Đang hoạt động | T51: PHẠM THỊ THANH UYÊN | U51: CTN009 | V51: GTG021 | W51: Đồng hồ, hương, cao bôi muỗi | X51: 0.53 | Y51: 0.23 | Z51: 4860 | AB51: 532950 | AC51: 532950_trangbtb | AE51: Theo quy định TCT | AF51: Không có yêu cầu khác. | AJ51: Đã thanh toán | AM51: 10/252 lý thái tổ , p an hòa, quận phú xuân, tp huế | AP51: 7 | AR51: Khách hàng tự mang đến bưu cục | AS51: 45869 | BB51: X | BD51: 526259 | BE51: 396659 | BF51: 126000 | BG51: =SUM(BD51:BF51) -> 1048918 | BH51: Hồ sơ vật lý và hồ sơ điện tử | BI51: Minh - Long | BJ51: 532950 | BK51: An Hoà | BL51: Phường Hương An | BM51: X | BP51: X | BQ51: X | BR51: Bưu điện TT Thuận Hóa - Phú Xuân
A52: 50 | B52: 5310 | C52: Bưu điện TT Thuận Hóa - Phú Xuân | D52: SME | E52: T001800104 | F52: CÔNG TY CỔ PHẦN HAI RÊ | G52: 170 LÊ DUẨN, TP HUẾ | H52: 0234.3529090 | I52: Nguyễn Thị Tuyết Châu | J52: T001800104 | K52: 3300383743 | L52: 149/2021/HĐBC/BĐTPH-CTYCPHAIRE | M52: 44270 | N52: Không xác định | O52: Không có | P52: Thanh toán vào tháng sau | S52: Đang hoạt động | T52: HỒ VĂN KỲ | U52: ETN001 | X52: 0.05 | Y52: 0.23 | Z52: 3816 | AB52: 532950 | AC52: 532950_trangbtb | AD52: BƯU TÁ LH SĐT TRÊN BG | AE52: Theo quy định TCT | AF52: Không có yêu cầu khác. | AJ52: Đã thanh toán | AM52: 170 LÊ DUẨN, TP HUẾ | AN52: 14h00-15h00 | AO52: 2-3 lần/tuần | AP52: 7 | AQ52: Xe máy | AS52: 45869 | BC52: X | BD52: 261598 | BE52: 275425 | BF52: 142800 | BG52: =SUM(BD52:BF52) -> 679823 | BH52: Hồ sơ vật lý và hồ sơ điện tử | BI52: Minh - Long | BJ52: 532950 | BK52: An Hoà | BL52: Phường Hương An | BP52: X | BQ52: X | BR52: Bưu điện TT Thuận Hóa - Phú Xuân
A53: 51 | B53: 5310 | C53: Bưu điện TT Thuận Hóa - Phú Xuân | D53: SME | E53: T001800501 | F53: CÔNG TY TNHH XL-SX ĐIỆN CƠ SDC | G53: SỐ 4 ĐƯỜNG SỐ 3 KCN HƯƠNG SƠ HUẾ | H53: 0905232438 | I53: Đồng Quỳnh Trang | J53: T001800501 | K53: 3300322606 | L53: 145/2021/HĐBC/BĐTPH-CTY ĐIỆNCƠ | M53: 44270 | N53: Không xác định | O53: Không có | P53: Thanh toán vào tháng sau | S53: Đang hoạt động | T53: HỒ VĂN KỲ | U53: ETN001 | X53: 0.03 | Y53: 0.17 | Z53: 2282.4 | AB53: 532950 | AC53: 532950_trangbtb | AD53: BTA LH SĐT TRÊN BG | AE53: Theo quy định TCT | AF53: Không có yêu cầu khác. | AJ53: Đã thanh toán | AM53: SỐ 4 ĐƯỜNG SỐ 3 KCN HƯƠNG SƠ HUẾ | AN53: 14h00-15h00 | AO53: 2-3 lần/tuần | AP53: 5 | AQ53: Xe máy | AS53: 45869 | BC53: X | BD53: 118600 | BE53: 307200 | BF53: 84000 | BG53: =SUM(BD53:BF53) -> 509800 | BH53: Hồ sơ vật lý và hồ sơ điện tử | BI53: Minh - Long | BJ53: 532950 | BK53: An Hoà | BL53: Phường Hương An | BP53: X | BQ53: X | BR53: Bưu điện TT Thuận Hóa - Phú Xuân
A54: 52 | B54: 5310 | C54: Bưu điện TT Thuận Hóa - Phú Xuân | D54: SME | E54: T001399434 | F54: Công Ty Cổ Phần Lục Gia Phát | G54: 674 Lê Duẩn, TP Huế | H54: 0234.3588828 | I54: Phan Thị Lệ | J54: T001399434 | K54: 3301323401 | L54: 101-hdbc-bdtph-lucgiaphat 44Van | M54: 43831 | N54: Không xác định | O54: Không có | P54: Thanh toán vào tháng sau | S54: Đang hoạt động | T54: PHẠM THỊ THANH UYÊN | U54: ETN001 | X54: 0.04 | Y54: 0.07 | Z54: 1123.2 | AB54: 532950 | AC54: 532950_trangbtb | AD54: bta lh sdt trên bưu gửi | AE54: Theo quy định TCT | AF54: Không có yêu cầu khác. | AJ54: Đã thanh toán | AM54: 674 Lê Duẩn, TP Huế | AN54: 14h00-15h00 | AO54: 2-3 lần/tuần | AP54: 2 | AQ54: Xe máy | AS54: 45869 | BC54: X | BD54: 159200 | BE54: 487400 | BF54: 40600 | BG54: =SUM(BD54:BF54) -> 687200 | BH54: Hồ sơ vật lý và hồ sơ điện tử | BI54: Minh - Long | BJ54: 532950 | BK54: An Hoà | BL54: Phường Hương An | BP54: X | BQ54: X | BR54: Bưu điện TT Thuận Hóa - Phú Xuân
A55: 53 | B55: 5310 | C55: Bưu điện TT Thuận Hóa - Phú Xuân | D55: SME | E55: T001571446 | F55: DƯỢC PHẨM MẠNH TÝ | G55: P. Vĩnh Ninh TP. Huế Tỉnh Thừa Thiên Huế | H55: 0234.3936768 | I55: Nguyễn Ngọc | J55: T001571446 | K55: 3300314838 | L55: 101/HĐBC/BCCP-DPMT | M55: 42885 | N55: Không xác định | P55: Thanh toán cước KHi chi trả cod | Q55: 2lần/tuần tại BC | S55: Đang hoạt động | T55: HỒ VĂN KỲ | U55: ETN001 | W55: Thuốc tây | X55: 0.24255725 | Y55: 4 | Z55: 98792 | AB55: 532950 | AC55: 532950_trangbtb | AD55: *BƯU TÁ LIÊN HỆ THEO SĐT TRÊN BƯU GỬI" | AE55: Thực hiện theo quy định của TCT | AJ55: Đã thanh toán công nợ | AM55: P. Vĩnh Ninh TP. Huế Tỉnh Thừa Thiên Huế | AN55: 15h00-17h00 | AO55: 1 lần/ngày | AP55: 131 | AQ55: xe máy | AS55: 45856 | BC55: X | BD55: 1322245 | BE55: 2792100 | BF55: 587400 | BG55: =SUM(BD55:BF55) -> 4701745 | BH55: Hồ sơ vật lý và hồ sơ điện tử | BI55: Minh - Long | BJ55: 532950 | BK55: An Hoà | BL55: Phường Hương An | BM55: X | BP55: X | BQ55: X | BR55: Bưu điện TT Thuận Hóa - Phú Xuân
A56: 54 | B56: 5310 | C56: Bưu điện TT Thuận Hóa - Phú Xuân | D56: Shop | E56: C008038568 | F56: CÔNG TY TNHH SẢN XUÁT TMDV ĐĂNG TUÁN | G56: 4 Đường số 4 Cụm công nghiệp An Hoà, Phường An Hoà, TP Huế | H56: 0962578878 | I56: Nguyễn Đăng Huy | J56: C008038568 | K56: 3300511931 | L56: HĐ65.2024_HĐBC_BĐTPH_ĐT | M56: 21/3/2024 | N56: Không xác định | P56: 1 lần/1 tháng | S56: Đang hoạt động | T56: PHẠM THỊ THANH UYÊN | U56: ETN001 ETN011 ETN031 ETN013 ETN003 CTN001 CTN007 CTN016 RTN001 CTN007 CTN009 | V56: GTG071 | W56: Áo quần | X56: 18.94414 | Y56: 5.2333333 | Z56: 620381 | AB56: 532950 | AC56: 532950_trangbtb | AD56: KHông cho xem hàng | AE56: Thực hiện theo quy định của TCT | AJ56: Đã thanh toán công nợ | AM56: 4 Đường số 4 Cụm công nghiệp An Hoà, Phường Phú Xuân, TP Huế | AN56: 16h00- 17h00 | AO56: 1 lần / ngày | AP56: 157 | AQ56: ô tô | AS56: 45856 | AV56: HẰNG NGÀY | AZ56: X | BD56: 17981680 | BE56: 19073395 | BF56: 6480435 | BG56: =SUM(BD56:BF56) -> 43535510 | BH56: Hồ sơ vật lý và hồ sơ điện tử | BI56: Rà soát để điều chỉnh lại bàn giao trên CMS | BJ56: 532950 | BK56: An Hoà | BL56: Phường Hương An | BM56: X | BP56: X | BQ56: X | BR56: Bưu điện TT Thuận Hóa - Phú Xuân
A57: 55 | B57: 5310 | C57: Bưu điện TT Thuận Hóa - Phú Xuân | D57: Shop | E57: C017698626 | F57: Võ Thị Quỳnh Nhi | G57: 6/17 Trần Quý KHoáng, P. An Hòa TP. Huế Tỉnh Thừa Thiên Huế | H57: 0379758637 | I57: Võ Thị Quỳnh Nhi | J57: C017698626 | L57: HĐ140.2025_HĐBC_BĐTTTHPX_VTQN | M57: 09/6/2025 | N57: 46182 | P57: Thứ 2, 4, 6 | Q57: Chuyển KHoản | R57: 1028658433 VCB CN Huế Võ Thị Quỳnh Nhi | S57: Đang hoạt động | T57: Phan Thị Hoài Phương | U57: CTN009, EQT002 | V57: GTG021 | W57: Áo quần | X57: 6.56 | Y57: 0.033333333 | Z57: 333.33333 | AB57: 532950 | AC57: 532950_trangbtb | AD57: BƯU TÁ LH SỐ ĐT TRÊN BG ĐỂ PHÁT | AE57: Thực hiện theo quy định của TCT | AJ57: Đã thanh toán công nợ | AM57: 6/17 Trần Quý KHoáng, P. Hương An TP. Huế | AN57: 16h00 | AO57: 2-3 lần /tháng | AP57: 2 | AQ57: xe máy | AS57: 45848 | AV57: HẰNG NGÀY | BB57: X | BD57: 9259 | BE57: 18518 | BF57: 0 | BG57: =SUM(BD57:BF57) -> 27777 | BH57: Chưa có thông tin | BI57: Rà soát để điều chỉnh lại bàn giao trên CMS | BJ57: 532950 | BK57: An Hoà | BL57: Phường Hương An | BM57: X | BP57: X | BQ57: X | BR57: Bưu điện TT Thuận Hóa - Phú Xuân
A58: 56 | B58: 5310 | C58: Bưu điện TT Thuận Hóa - Phú Xuân | D58: Shop | E58: C001395931 | F58: Trần Thị Thu | G58: 208 Lê Duẩn, P. Phú Thuận TP. Huế Tỉnh Thừa Thiên Huế | H58: 0706003295 | I58: Trần Thị Thu | J58: C001395931 | L58: 71-hdbc-bdtph-tranthithu 44Van | M58: 43881 | N58: KHông xác định | P58: 1 lần/1 tháng | S58: Đang hoạt động | T58: PHẠM THỊ THANH UYÊN | U58: ETN001 ETN011 ETN031 ETN013 ETN003 CTN001 CTN007 CTN016 RTN001 CTN007 CTN009 | V58: GTG021 | W58: Sách | X58: 2.7347222 | Y58: 1.2 | Z58: 6372 | AB58: 532950 | AC58: 532950_trangbtb | AD58: Cho xem hàng, KHÁCH ĐƯỢC KIỂM TRA HÀNG, NẾU KHÔNG NHẬN THÌ THANH TOÁN PHÍ HỦY ĐƠN HÀNG 30.000 ĐỒNG ( ĐỐI VỚI ĐỊA CHỈ NHẬN NGOÀI TỈNH TT HUẾ); 15.000 ĐỒNG ( ĐỐI VỚI ĐỊA CHỈ NHẬN TRONG TỈNH TT HUẾ). | AE58: Thực hiện theo quy định của TCT | AJ58: Đã thanh toán công nợ | AM58: 208 Lê Duẩn, P. Phú Xuân TP. Huế | AN58: 11h00 -16h00 | AO58: 2-3 lần /tuần | AP58: 42 | AQ58: xe máy | AS58: 45853 | AV58: HẰNG NGÀY | BC58: X | BD58: 646025 | BE58: 185000 | BF58: 176000 | BG58: =SUM(BD58:BF58) -> 1007025 | BH58: Hồ sơ vật lý và hồ sơ điện tử | BI58: Thy - Dũng | BJ58: 532950 | BK58: An Hoà | BL58: Phường Hương An | BP58: X | BQ58: X | BR58: Bưu điện TT Thuận Hóa - Phú Xuân
A59: 57 | B59: 5310 | C59: Bưu điện TT Thuận Hóa - Phú Xuân | D59: Key Account | E59: T001800475 | F59: Trung Tâm Dịch Vụ Đấu Giá Tài Sản | G59: 17 Nguyễn Văn Linh, P. Hương Sơ TP. Huế Tỉnh Thừa Thiên Huế | I59: Phan Tiến Dũng | J59: T001800475 | K59: 3300366723 | L59: 144/2021/HĐBC/BĐTPH-TTĐGTS | M59: 44270 | N59: KHông xác định | P59: 01 tháng/lần Tại địa chỉ bên A | S59: Đang hoạt động | T59: HỒ VĂN KỲ | U59: ETN001 | V59: GTG001 | W59: Tài Liệu | X59: 0.0643125 | Y59: 2.6666667 | Z59: 38070 | AB59: 532950 | AC59: 532950_trangbtb | AD59: BƯU TÁ VUI LÒNG LIÊN HỆ SĐT NGƯỜI NHẬN TRÊN BƯU GỬI ĐỂ PHÁT HÀNG | AE59: Thực hiện theo quy định của TCT | AJ59: Đã thanh toán công nợ | AM59: 17 Nguyễn Văn Linh, P. Hương An TP. Huế | AN59: 11h00 -16h00 | AO59: 2-3 lần /tuần | AP59: 80 | AQ59: xe máy | AS59: 45850 | AV59: HẰNG NGÀY | BC59: X | BD59: 926300 | BE59: 359900 | BF59: 390400 | BG59: =SUM(BD59:BF59) -> 1676600 | BH59: Hồ sơ vật lý và hồ sơ điện tử | BI59: vũ - lan | BJ59: 532950 | BK59: An Hoà | BL59: Phường Hương An | BP59: X | BQ59: X | BR59: Bưu điện TT Thuận Hóa - Phú Xuân
A60: 58 | B60: 5310 | C60: Bưu điện TT Thuận Hóa - Phú Xuân | D60: Shop | E60: C006146255 | F60: Bongo Plastic | G60: 92 Lý Thái Tổ, An Hoà, Thừa Thiên Huế | H60: 0903507408 | I60: Nguyễn Hữu Sy | J60: C006146255 | L60: HĐ034.2023-HĐBC-BĐTPH-BGP | M60: 45017 | N60: Không xác định | P60: thanh toán cước khi chi trả cod | Q60: CK thứ 2,4,6 hằng tuần | R60: 0161000826132_vietcombank _ Nguyen Huu Sy | S60: Đang hoạt động | T60: PHẠM THỊ THANH UYÊN | U60: CTN009 | X60: 7.8867895 | Y60: 0.63333333 | Z60: 24417.333 | AB60: 532950 | AC60: 532950_trangbtb | AE60: Theo quy định TCT | AF60: Không có yêu cầu khác. | AJ60: đã thanh toán | AM60: 92 Lý Thái Tổ, An Hoà, Thừa Thiên Huế | AN60: 17h00-18h00 | AO60: 1 lần/ ngày | AP60: 11 | AQ60: Ô tô | AS60: 45812 | BB60: X | BD60: 40000 | BE60: 0 | BF60: 40000 | BG60: =SUM(BD60:BF60) -> 80000 | BH60: Hồ sơ vật lý và hồ sơ điện tử | BI60: Rà soát để điều chỉnh lại bàn giao trên CMS | BJ60: 532950 | BK60: An Hoà | BL60: Phường Hương An | BM60: X | BP60: X | BQ60: x | BR60: Bưu điện TT Thuận Hóa - Phú Xuân
A61: 59 | B61: 5310 | C61: Bưu điện TT Thuận Hóa - Phú Xuân | D61: Cá Nhân | E61: C018395618 | F61: Nguyễn Công Tý | G61: tdp thanh chữ | H61: 0905214893 | J61: C018395618 | L61: HĐ248.2025.HĐBC-BĐKVTH-PX.PX.LKG | M61: 45929 | S61: Đang thực hiện | T61: NGUYỄN ĐỨC LỘC | AB61: 532950 | AC61: 532950_trangbtb | BD61: 195500 | BE61: 147000 | BF61: 0 | BG61: =SUM(BD61:BF61) -> 342500 | BI61: Minh - Long | BJ61: 532950 | BK61: An Hoà | BL61: Phường Hương An | BP61: X | BQ61: R | BR61: Bưu điện TT Thuận Hóa - Phú Xuân
A62: 60 | B62: 5310 | C62: Bưu điện TT Thuận Hóa - Phú Xuân | D62: Cá Nhân | E62: C018228601 | F62: Lê Đình Huy | G62: 27 Trần Nguyên Đán | H62: 0905477679 | J62: C018228601 | L62: HĐ242.2025.HĐBC-BĐKVTH-PX.PX.LKG | M62: 45901 | S62: Đang thực hiện | T62: NGUYỄN ĐỨC LỘC | AB62: 532950 | AC62: 532950_trangbtb | BD62: 0 | BE62: 31890 | BF62: 76890 | BG62: =SUM(BD62:BF62) -> 108780 | BI62: Rà soát để bàn giao trên CMS | BJ62: 532950 | BK62: An Hoà | BL62: Phường Hương An | BP62: X | BQ62: R | BR62: Bưu điện TT Thuận Hóa - Phú Xuân
A63: 61 | B63: 5310 | C63: Bưu điện TT Thuận Hóa - Phú Xuân | D63: Tổ Chức | E63: T019378284 | F63: Công An Phường Hương An | G63: 07 Nguyễn Văn Linh, phường Hương An, TP Huế | H63: 02343588455 | J63: T019378284 | L63: HĐ 12/2026/ HĐ¬_BC-PHBC/BĐTP- CA PHƯỜNG HƯƠNG AN | M63: 46023 | S63: Đang hoạt động | T63: NGUYỄN ĐỨC LỘC | U63: ETN001 | X63: 35 | Y63: 9 | Z63: 104400 | AB63: 532950 | AC63: 532950_trangbtb | AD63: 0 | BD63: 0 | BE63: 104400 | BF63: 53691 | BG63: =SUM(BD63:BF63) -> 158091 | BI63: Rà soát để bàn giao trên CMS | BJ63: 532950 | BK63: An Hoà | BL63: Phường Hương An | BP63: X | BR63: Bưu điện TT Thuận Hóa - Phú Xuân
A64: 62 | B64: 5310 | C64: Bưu điện TT Thuận Hóa - Phú Xuân | D64: Key Account | E64: T017962895 | F64: Trung Tâm HCC Phường Hương An | G64: 143 Nguyễn Văn Linh, phường Hương AnTP. Huế | I64: Trần Đạo Quang Vũ | J64: T017962895 | L64: 177/2025/HĐ_BC-PHBC/BĐTT-TTPVHCCPHA | M64: 45839 | N64: Không xác định | O64: Không có | P64: 01 tháng/lần Trong 03 - 05 ngày làm việc tiếp theo kể từ ngày nhận được hoá đơn GTGT hợp lệ | S64: Đang hoạt động | T64: ĐẶNG TUẤN VŨ | U64: Dịch vụ HCC, luân chuyển hồ sơ HCC, KT1, EMS, Chuyển phát bưu phẩm trong nước và quốc tế | W64: Tài liệu | X64: 0.28 | Y64: 0.066666667 | Z64: 1883.3333 | AA64: My VNP | AB64: 532950 | AC64: 532950_trangbtb | AE64: Thực hiện theo quy định của TCT | AJ64: 61020 | AK64: Đang làm thanh toán | BB64: X | BD64: 0 | BE64: 113200 | BF64: 9600 | BG64: =SUM(BD64:BF64) -> 122800 | BH64: Hồ sơ vật lý và hồ sơ điện tử | BI64: Minh - Long | BJ64: 532950 | BK64: An Hoà | BL64: Phường Hương An | BP64: X | BQ64: X | BR64: Bưu điện TT Thuận Hóa - Phú Xuân
A65: 63 | B65: 5310 | C65: Bưu điện TT Thuận Hóa - Phú Xuân | D65: Key Account | E65: T017962878 | F65: UBND Phường Hương An | G65: 143 Nguyễn Văn Linh, phường Hương AnTP. Huế | I65: Nguyễn Đình Tuấn | J65: T017962878 | L65: 195/2025/HĐ_BC-PHBC/BĐTT-VPUBHA | M65: 45839 | N65: Không xác định | O65: Không có | P65: 01 tháng/lần Trong 03 - 05 ngày làm việc tiếp theo kể từ ngày nhận được hoá đơn GTGT hợp lệ | S65: Đang hoạt động | T65: ĐẶNG TUẤN VŨ | U65: Dịch vụ HCC, luân chuyển hồ sơ HCC, KT1, EMS, Chuyển phát bưu phẩm trong nước và quốc tế | W65: Tài liệu | X65: 0.038125 | Y65: 0.26666667 | Z65: 3616.3333 | AA65: My VNP | AB65: 532950 | AC65: 532950_trangbtb | AE65: Thực hiện theo quy định của TCT | AJ65: 117170 | AK65: Đang làm thanh toán | BB65: X | BD65: 339245 | BE65: 81200 | BF65: 100800 | BG65: =SUM(BD65:BF65) -> 521245 | BH65: Hồ sơ vật lý và hồ sơ điện tử | BI65: Minh - Long | BJ65: 532950 | BK65: An Hoà | BL65: Phường Hương An | BP65: X | BQ65: X | BR65: Bưu điện TT Thuận Hóa - Phú Xuân
A66: 64 | B66: 5310 | C66: Bưu điện TT Thuận Hóa - Phú Xuân | D66: Shop | E66: C005951881 | F66: Hạnh Trần | G66: Hương Hồ, TP Huế | H66: 0945222286 | I66: Nguyễn Thị Hồng Liên | J66: C005951881 | L66: HĐ10.2023-HĐBC-BĐTPH-STHT | M66: 44973 | N66: Không xác định | P66: Thanh toán cước KHi chi trả cod | Q66: CK qua ngân hàng, 1 TuẦn/lần | R66: 0945222286_Sacombank | S66: Đang hoạt động | T66: PHẠM THỊ THANH UYÊN | U66: CTN009 | V66: GTG021 | W66: Á o Quần | X66: 2.3 | Y66: 0 | Z66: 53345 | AB66: 535530 | AC66: 535530_loanptk | AE66: Thực hiện theo quy định của TCT | AJ66: Đã thanh toán công nợ | AM66: Hương Hồ, TP Huế | AN66: 14h00-16h00 | AO66: 1 lần/ngày | AP66: 100 | AQ66: xe máy | AS66: 45856 | BB66: X | BD66: 3517260 | BE66: 1808940 | BF66: 38000 | BG66: =SUM(BD66:BF66) -> 5364200 | BH66: Hồ sơ vật lý và hồ sơ điện tử | BI66: Rà soát để điều chỉnh lại bàn giao trên CMS | BJ66: 535530 | BK66: Hương An | BL66: Phường Hương An | BM66: X | BP66: X | BQ66: X | BR66: Bưu điện TT Thuận Hóa - Phú Xuân
A67: 65 | B67: 5310 | C67: Bưu điện TT Thuận Hóa - Phú Xuân | D67: Shop | E67: C017277901 | F67: Nguyễn Ngoc | G67: 15 Cao Văn Khánh, Hương An, P. Hương An TX. Hương Trà Tỉnh Thừa Thiên Huế | H67: 0784433533 | J67: C017277901 | L67: HĐ78-2025-HĐBC-BĐTTHPX-NN | M67: 45755 | N67: Không xác định | O67: Không có | P67: Trong 03 - 05 ngày làm việc tiếp theo kể từ ngày nhận được hoá đơn GTGT hợp lệ | S67: Đang hoạt động | T67: PHẠM THỊ THANH UYÊN | U67: CTN007 | V67: GTG021 | W67: Bình sữa, bỉm, sữa chua, xe đồ chơi, vitamin | X67: 1.19 | Y67: 0.47 | Z67: 4666.67 | AB67: 535530 | AC67: 535530_loanptk | AE67: Theo quy định TCT | AF67: Không có yêu cầu khác. | AJ67: Đã thanh toán | AM67: 15 Cao Văn Khánh, Hương An, P. Hương An TX. Hương Trà Tỉnh Thừa Thiên Huế | AN67: 14h00-15h00 | AO67: 1-2 lần / tuần | AP67: 14 | AQ67: Xe máy | AS67: 45869 | BB67: X | BD67: 46777 | BE67: 75036 | BF67: 0 | BG67: =SUM(BD67:BF67) -> 121813 | BH67: Chưa có thông tin | BI67: Rà soát để điều chỉnh lại bàn giao trên CMS | BJ67: 535530 | BK67: Hương An | BL67: Phường Hương An | BM67: X | BP67: X | BQ67: X | BR67: Bưu điện TT Thuận Hóa - Phú Xuân
A68: 66 | B68: 5310 | C68: Bưu điện TT Thuận Hóa - Phú Xuân | D68: Shop | E68: C016182592 | F68: Diệu Trần | G68: 105 Long Hồ _ Hương Hồ _ Hương Trà_ TP Huế | H68: 0375434638 | I68: Trần Thị Mỹ Diệu | J68: C016182592 | L68: 40.2025/HĐBC/BĐTPH-TTMD | M68: 45729 | N68: Không xác định | O68: Không có | P68: Trong 03 - 05 ngày làm việc tiếp theo kể từ ngày nhận được hoá đơn GTGT hợp lệ | Q68: Thứ 2,4,6 hàng tuần Tiền mặt Chuyển khoản | R68: 5511195738 BIDV Trần Thị Mỹ Diệu | S68: Đang hoạt động | T68: PHẠM THỊ THANH UYÊN | U68: CTN009 | V68: GTG021 | W68: Body | X68: 0.6 | Y68: 0.03 | Z68: 684 | AB68: 535530 | AC68: 535530_loanptk | AD68: Không cho xem hàng | AE68: Theo quy định TCT | AF68: Không có yêu cầu khác. | AJ68: Đã thanh toán | AM68: 105 Long Hồ _ Hương Hồ _ Hương Trà_ TP Huế | AN68: 14h00-16h00 | AO68: 1-2 lần / tuần | AP68: 1 | AQ68: Xe máy | AS68: 45842 | BB68: X | BD68: 212725 | BE68: 0 | BF68: 0 | BG68: =SUM(BD68:BF68) -> 212725 | BH68: Hồ sơ vật lý và hồ sơ điện tử | BI68: Rà soát để điều chỉnh lại bàn giao trên CMS | BJ68: 535530 | BK68: Hương An | BL68: Phường Hương An | BP68: X | BQ68: X | BR68: Bưu điện TT Thuận Hóa - Phú Xuân
A69: 67 | B69: 5310 | C69: Bưu điện TT Thuận Hóa - Phú Xuân | D69: Shop | E69: C005134242 | F69: Shop Phan Mai | G69: Long Hồ Hạ 2, Hương Hồ, TP Huế | H69: 0354573660 | I69: Phan Thị Mai | J69: C005134242 | L69: C005134242_HĐ109.2022-HĐBC-BĐTPH-SPM | M69: 01/8/2022 | N69: Không xác định | P69: Thanh toán cước KHi chi trả cod | Q69: Chuyển KHoản qua ngân hàng | R69: 0161001720126 | S69: Đang hoạt động | T69: PHẠM THỊ THANH UYÊN | U69: CTN009 | V69: GTG021 | W69: Cơ KHí | X69: 4.8328723 | Y69: 2 | Z69: 58233 | AB69: 535550 | AC69: 535550_huyennct | AD69: Cho Xem Hàng..Bưu Tá Phát Theo Số Điện Thoại Trên Bưu Gửi | AE69: Thực hiện theo quy định của TCT | AJ69: Đã thanh toán công nợ | AM69: Long Hồ Hạ 2, Hương Hồ, TP Huế | AN69: 14h00-16h00 | AO69: 1 lần/ngày | AP69: 47 | AQ69: xe máy | AS69: 45856 | BB69: X | BD69: 6110000 | BE69: 2934400 | BF69: 283000 | BG69: =SUM(BD69:BF69) -> 9327400 | BH69: Hồ sơ vật lý và hồ sơ điện tử | BI69: Minh - Long | BJ69: 535550 | BK69: Hương Hồ | BL69: Phường Kim Long | BP69: X | BQ69: X | BR69: Bưu điện TT Thuận Hóa - Phú Xuân
A70: 68 | B70: 5310 | C70: Bưu điện TT Thuận Hóa - Phú Xuân | D70: Shop | E70: C002469485 | F70: SƯ MINH GIẢI | G70: CHÙA HUYỀN KHÔNG PHƯỜNG HƯƠNG HỒ TP HUẾ | H70: 0967140053 | J70: C002469485 | L70: HĐ483.2021-HĐBC-BĐTPH-SMG | M70: 44461 | N70: Không xác định | O70: Không có | P70: Ngay khi sử dụng dịch vụ Thanh toán tại địa chỉ bên A | Q70: 01 tuần/lần Thanh toán tại địa chỉ bên A | S70: Đang hoạt động | T70: HỒ VĂN KỲ | U70: CTN001, ETN001, CTN007 | V70: GTG021 | W70: Bánh kẹo, sách | X70: 3.62 | Y70: 0.07 | Z70: 3082.43 | AB70: 535550 | AC70: 535550_huyennct | AD70: BƯU TÁ PHÁT THEO SỐ ĐIỆN THOẠI TRÊN BƯU GỬI | AE70: Theo quy định TCT | AF70: Không có yêu cầu khác. | AJ70: Đã thanh toán | AM70: CHÙA HUYỀN KHÔNG PHƯỜNG HƯƠNG HỒ TP HUẾ | AP70: 4 | AR70: Khách hàng tự mang đến bưu cục | AS70: 45869 | BC70: X | BD70: 117283 | BE70: 48635 | BF70: 0 | BG70: =SUM(BD70:BF70) -> 165918 | BH70: Hồ sơ vật lý và hồ sơ điện tử | BI70: Minh - Long | BJ70: 535550 | BK70: Hương Hồ | BL70: Phường Kim Long | BP70: X | BQ70: X | BR70: Bưu điện TT Thuận Hóa - Phú Xuân
A71: 69 | B71: 5310 | C71: Bưu điện TT Thuận Hóa - Phú Xuân | D71: SME | E71: T001460533 | F71: Công ty CP giống cây trồng vật nuôi | G71: 128 Nguyễn Phúc Nguyên, TP Huế | H71: 01635704977 | I71: Thanh | J71: T001460533 | L71: 161/2021/HĐBC/BĐTP-CTYCPGCTVN | M71: 15/03/2021 | N71: Không xác định | P71: Thanh toán vào giữa tháng sau | T71: PHẠM THỊ THANH UYÊN | U71: ETN001, CTN001 | W71: Tài liệu | X71: 0.2 | Y71: 1.33 | Z71: 24046 | AB71: 532760 | AC71: 532760_duongvt | AD71: *BƯU TÁ LIÊN HỆ THEO SĐT TRÊN BƯU GỬI" | AE71: Theo quy định của TCT | AJ71: 721.394 | AK71: đang làm thanh toán | AM71: 128 Nguyễn Phúc Nguyên, TP Huế | AN71: 13h30-14h30 | AO71: 1 lân / ngày | AP71: 40 | AQ71: Xe máy | AS71: 45862 | BC71: X | BD71: 2351729 | BE71: 790300 | BF71: 158700 | BG71: =SUM(BD71:BF71) -> 3300729 | BH71: Hồ sơ vật lý và hồ sơ điện tử | BI71: Phát - Long | BJ71: 532760 | BK71: Kim Long | BL71: Phường Kim Long | BP71: X | BQ71: X | BR71: Bưu điện TT Thuận Hóa - Phú Xuân
A72: 70 | B72: 5310 | C72: Bưu điện TT Thuận Hóa - Phú Xuân | D72: Shop | E72: C017458373 | F72: Minh Nguyệt | G72: 204 Lý Nam Đế, P. Hương Long TP. Huế Tỉnh Thừa Thiên Huế | H72: 0779337121 | I72: Lê Thị Nguyệt | J72: C017458373 | L72: HĐ108-2025-HĐBC-BĐTTTHPX-MN | M72: 45784 | N72: Không xác định | P72: Thanh toán cước khi nhận tiền COD | Q72: Chuyển khoản, theo yêu cầu KH | R72: 4000205198545 Agribank | S72: Đang hoạt động | T72: PHẠM THỊ THANH UYÊN | U72: ETN001 | V72: GTG021 | W72: Dụng cụ xây dựng, vụn sành sư, bi thủy tinh, mắt thuyền, râu rồng | X72: 5.42 | Y72: 0.5 | Z72: 22496 | AB72: 532760 | AC72: 532760_duongvt | AD72: *BƯU TÁ LIÊN HỆ THEO SĐT TRÊN BƯU GỬI" | AE72: Theo quy định của TCT | AJ72: 674.868 | AK72: đang thanh toán | AM72: 204 Lý Nam Đế, P. Hương Long TP. Huế Tỉnh Thừa Thiên Huế | AP72: 15 | AR72: Khách hàng tự mang đến BC | AS72: 45861 | AV72: Khi phát sinh yêu cầu | BC72: X | BD72: 67200 | BE72: 51000 | BF72: 0 | BG72: =SUM(BD72:BF72) -> 118200 | BH72: Hồ sơ vật lý và hồ sơ điện tử | BI72: Rà soát để điều chỉnh lại bàn giao trên CMS | BJ72: 532760 | BK72: Kim Long | BL72: Phường Kim Long | BP72: X | BQ72: X | BR72: Bưu điện TT Thuận Hóa - Phú Xuân
A73: 71 | B73: 5310 | C73: Bưu điện TT Thuận Hóa - Phú Xuân | D73: Shop | E73: C004228093 | F73: Nguyễn Thị Cẩm Tú | G73: 3/15 Nguyễn Hữu Dật, Kim Long | H73: 0971383073 | I73: Nguyễn Thị Cẩm Tú | J73: C004228093 | L73: HĐ5182021-HĐBC-BĐTPH-NTCT | M73: 01/11/2021 | N73: Không xác định | P73: Thanh toán cước KHi chi trả cod | Q73: CK qua ngân hàng, 1 TuẦn/lần | R73: 0161000882115_Việtcombank | S73: Đang hoạt động | T73: HỒ VĂN KỲ | U73: CTN009 | W73: Áo | X73: 0.38818182 | Y73: 3 | Z73: 48805 | AB73: 532760 | AC73: 532760_duongvt | AD73: Yêu Cầu Liên Hệ Người Gửi KHi KHông Phát Được Hàng. KHông Được Tự Ý Chuyển Hoàn KHi KHông Liên Hệ Lại Người Gửi .Cám Ơn | AE73: Thực hiện theo quy định của TCT | AJ73: Đã thanh toán công nợ | AM73: 3/15 Nguyễn Hữu Dật, Kim Long | AN73: 10h; 14h | AO73: 1 lần/ngày | AP73: 77 | AQ73: xe máy | AS73: 45854 | BB73: X | BD73: 2669000 | BE73: 3184000 | BF73: 844000 | BG73: =SUM(BD73:BF73) -> 6697000 | BH73: Hồ sơ vật lý và hồ sơ điện tử | BI73: Minh - Long | BJ73: 532760 | BK73: Kim Long | BL73: Phường Kim Long | BM73: X | BP73: X | BQ73: X | BR73: Bưu điện TT Thuận Hóa - Phú Xuân
A74: 72 | B74: 5310 | C74: Bưu điện TT Thuận Hóa - Phú Xuân | D74: Shop | E74: C001395313 | F74: Phạm Thị Hồng Phương | G74: 1 Bửu Đình, Phường Kim Long, TP Huế | H74: 0915551419 | I74: Phạm Thị Hồng Phương | J74: C001395313 | L74: HĐ078.2022-HĐBC-BĐTPH-PTHP | M74: 44701 | N74: Không xác định | P74: Thanh toán khi nhận tiền cod | Q74: CK Thứ 3,6 hằng tuần | R74: 0161000884912 Vietcombank CN Huế | S74: Đang hoạt động | T74: PHẠM THỊ THANH UYÊN | U74: CTN007 | V74: GTG021 | W74: Áo quần | X74: 0.99887097 | Y74: 1.0333333 | Z74: 10333.333 | AB74: 532760 | AC74: 532760_duongvt | AE74: Theo quy định TCT | AF74: Không có yêu cầu khác. | AJ74: đã thanh toán | AM74: 1 Bửu Đình, Phường Kim Long, TP Huế | AN74: 13h30- 14h30 | AO74: 2-3 lần/ tuần | AP74: 14 | AQ74: Xe máy | AS74: 45812 | BB74: X | BD74: 223698 | BE74: 120367 | BF74: 0 | BG74: =SUM(BD74:BF74) -> 344065 | BH74: Hồ sơ vật lý và hồ sơ điện tử | BI74: Phát - Long | BJ74: 532760 | BK74: Kim Long | BL74: Phường Kim Long | BM74: X | BP74: X | BQ74: X | BR74: Bưu điện TT Thuận Hóa - Phú Xuân
A75: 73 | B75: 5310 | C75: Bưu điện TT Thuận Hóa - Phú Xuân | D75: Shop | E75: C004290691 | F75: Ngọa Tùng Am | G75: chùa huyền không sơn thượng, P Hương Hồ, Hương Trà, Huế | H75: 0899228727 | I75: Nguyễn Tấn Phẩm | J75: C004290691 | L75: HĐ007.2022-HĐBC-BĐTPH-NTA | M75: 44581 | N75: Không xác định | O75: Không có | P75: Trong 03 - 05 ngày làm việc tiếp theo kể từ ngày nhận được hoá đơn GTGT hợp lệ | Q75: 01 tháng/lần Tiền mặt/Chuyển khoản | R75: 19135719310013 Techcmbank Nguyễn Tấn Phẩm | S75: Đang hoạt động | T75: HỒ VĂN KỲ | U75: ETN013, CTN001 | W75: Hồ sơ, sách | X75: 8.37 | Y75: 0.07 | Z75: 8365.9 | AB75: 532760 | AC75: 532760_duongvt | AE75: Theo quy định TCT | AF75: Không có yêu cầu khác. | AJ75: đã thanh toán | AM75: chùa huyền không sơn thượng, P Hương Hồ, Hương Trà, Huế | AP75: 2 | AR75: Khách hàng tự mang đến bưu cục | AS75: 45869 | BC75: X | BD75: 391235 | BE75: 118170 | BF75: 0 | BG75: =SUM(BD75:BF75) -> 509405 | BH75: Hồ sơ vật lý và hồ sơ điện tử | BI75: Phát - Long | BJ75: 532760 | BK75: Kim Long | BL75: Phường Kim Long | BP75: X | BQ75: X | BR75: Bưu điện TT Thuận Hóa - Phú Xuân
A76: 74 | B76: 5310 | C76: Bưu điện TT Thuận Hóa - Phú Xuân | D76: SME | E76: T001800841 | F76: Công ty TNHH Phương Ty | G76: Đường Sư Vạn Hạnh, Kim Long, TP Huế | H76: 0905337733 | I76: Hạnh | J76: T001800841 | K76: 3300345240 | L76: 158/2021/HĐBC/BĐTP-CTYPTY | M76: 44270 | N76: Không xác định | O76: Không có | P76: 01 tháng/lần Thanh toán tại địa chỉ bên A | T76: HỒ VĂN KỲ | U76: ETN001 | X76: 0.06 | Y76: 0.63 | Z76: 9928.8 | AB76: 532760 | AC76: 532760_duongvt | AD76: *BƯU TÁ LIÊN HỆ THEO SĐT TRÊN BƯU GỬI" | AE76: Theo quy định TCT | AF76: Không có yêu cầu khác. | AJ76: đã thanh toán | AM76: Đường Sư Vạn Hạnh, Kim Long, TP Huế | AP76: 19 | AR76: Khách hàng tự mang đến bưu cục | AS76: 45869 | BC76: X | BD76: 276200 | BE76: 126000 | BF76: 50400 | BG76: =SUM(BD76:BF76) -> 452600 | BH76: Hồ sơ vật lý và hồ sơ điện tử | BI76: Phát - Long | BJ76: 532760 | BK76: Kim Long | BL76: Phường Kim Long | BP76: X | BQ76: X | BR76: Bưu điện TT Thuận Hóa - Phú Xuân
A77: 75 | B77: 5310 | C77: Bưu điện TT Thuận Hóa - Phú Xuân | D77: Shop | E77: C001396248 | F77: Khánh Hòa | G77: Nhà số 160 Hải Triều, phường An Đông, TP Huế, P. An Đông TP. Huế Tỉnh Thừa Thiên Huế | H77: 399176321 | I77: Khánh Hòa | J77: C001396248 | L77: 202/HĐBC/BĐTP/SHOPBONGBONG | M77: 44166 | N77: Không xác định | O77: Không có | P77: 01 tháng/lần Chuyển khoản | Q77: 01 tuần/lần Chuyển khoản | R77: 0161000770953 VCB Lê Thị Lành | S77: Đang hoạt động | T77: PHẠM THỊ THANH UYÊN | U77: CTN007, CTN009 | V77: GTG021 | W77: Ga, thảm, chiếu | X77: 1.96 | Y77: 0.4 | Z77: 6368.27 | AB77: 532760 | AC77: 532760_duongvt | AE77: Theo quy định TCT | AF77: Không có yêu cầu khác. | AJ77: đã thanh toán | AM77: 199 Phan Đình Phùng, Huế | AP77: 12 | AR77: Khách hàng tự mang đến bưu cục | AS77: 45869 | BB77: X | BD77: 147290 | BE77: 63600 | BF77: 0 | BG77: =SUM(BD77:BF77) -> 210890 | BH77: Hồ sơ vật lý và hồ sơ điện tử | BI77: Phát - Long | BJ77: 532760 | BK77: Kim Long | BL77: Phường Kim Long | BM77: X | BP77: X | BQ77: x | BR77: Bưu điện TT Thuận Hóa - Phú Xuân
A78: 76 | B78: 5310 | C78: Bưu điện TT Thuận Hóa - Phú Xuân | D78: Tổ Chức | E78: T001571619 | F78: CN KHAI THÁC ĐƯỜNG SẮT TTHUẾ | G78: 01 Bùi Thị Xuân, Phường Vĩnh Ninh, TP Huế | H78: 0905302357 | J78: T001571619 | L78: 154/2021/HĐBC/BĐTP-CNKTĐS | M78: 44270 | S78: Đang hoạt động | T78: HỒ VĂN KỲ | U78: 0 | W78: TL;1;0;0 | AB78: 532760 | AC78: 532760_duongvt | BD78: 2362900 | BE78: 2300900 | BF78: 587300 | BG78: =SUM(BD78:BF78) -> 5251100 | BH78: Hồ sơ vật lý và hồ sơ điện tử | BI78: Minh - Long | BJ78: 532760 | BK78: Kim Long | BL78: Phường Kim Long | BP78: X | BQ78: R | BR78: Bưu điện TT Thuận Hóa - Phú Xuân
A79: 77 | B79: 5310 | C79: Bưu điện TT Thuận Hóa - Phú Xuân | D79: Cá Nhân | E79: C017328237 | F79: Trần Thị Uyên Như | G79: 4/314 Lý Nam Đế | H79: 0356009208 | J79: C017328237 | L79: HĐ88.2025_HĐBC_BĐTTTHPX_TTUN | M79: 45762 | S79: Đang hoạt động | T79: PHẠM THỊ THANH UYÊN | AB79: 532760 | AC79: 532760_duongvt | BD79: 0 | BE79: 553000 | BF79: 73000 | BG79: =SUM(BD79:BF79) -> 626000 | BH79: Hồ sơ vật lý và hồ sơ điện tử | BI79: Rà soát để điều chỉnh lại bàn giao trên CMS | BJ79: 532760 | BK79: Kim Long | BL79: Phường Kim Long | BP79: X | BQ79: R | BR79: Bưu điện TT Thuận Hóa - Phú Xuân
A80: 78 | B80: 5310 | C80: Bưu điện TT Thuận Hóa - Phú Xuân | D80: Cá Nhân | E80: C005720049 | F80: Nhung Thuỳ | G80: kiệt 2/240 Lý Nam Đế phường Hương Long | H80: 0961502169 | J80: C005720049 | L80: C005720049_HĐ63.2024_HĐBC_BĐTPH_NT | M80: 45371 | S80: Đang hoạt động | T80: PHẠM THỊ THANH UYÊN | U80: CG347369573VN | W80: quần áo^1^0^0 | AB80: 532760 | AC80: 532760_duongvt | BD80: 60581 | BE80: 103608 | BF80: 0 | BG80: =SUM(BD80:BF80) -> 164189 | BH80: Hồ sơ vật lý và hồ sơ điện tử | BI80: Minh - Long | BJ80: 532760 | BK80: Kim Long | BL80: Phường Kim Long | BM80: X | BP80: X | BQ80: R | BR80: Bưu điện TT Thuận Hóa - Phú Xuân
A81: 79 | B81: 5310 | C81: Bưu điện TT Thuận Hóa - Phú Xuân | D81: Tổ Chức | E81: T018405045 | F81: Phòng Kinh Tế, Hạ Tầng Và Đô Thị Phường Kim Long | G81: 69 Nguyễn Hoàng, Phường Kim Long, TP Huế | H81: 0979237555 | J81: T018405045 | L81: 238-2025 HĐBC BĐKVTTTHPX-PKTHT&ĐTPKL | M81: 45909 | S81: Đang thực hiện | T81: DƯƠNG THỊ HÒE | AB81: 532760 | AC81: 532760_duongvt | BD81: 0 | BE81: 19200 | BF81: 0 | BG81: =SUM(BD81:BF81) -> 19200 | BI81: Rà soát để bàn giao trên CMS | BJ81: 532760 | BK81: Kim Long | BL81: Phường Kim Long | BP81: X | BQ81: R | BR81: Bưu điện TT Thuận Hóa - Phú Xuân
A82: 80 | B82: 5310 | C82: Bưu điện TT Thuận Hóa - Phú Xuân | D82: Tổ Chức | E82: T018159985 | F82: Hội Chữ Thập Đỏ Thành Phố Huế | G82: 119 Vạn Xuân, | H82: 0982448133 | J82: T018159985 | T82: HOÀNG VĂN DUY | AB82: 532760 | AC82: 532760_duongvt | BD82: 1248574 | BE82: 2060124 | BF82: 94500 | BG82: =SUM(BD82:BF82) -> 3403198 | BH82: Hồ sơ vật lý và hồ sơ điện tử | BI82: Phát - Long | BJ82: 532760 | BK82: Kim Long | BL82: Phường Kim Long | BP82: X | BQ82: R | BR82: Bưu điện TT Thuận Hóa - Phú Xuân
A83: 81 | B83: 5310 | C83: Bưu điện TT Thuận Hóa - Phú Xuân | D83: Key Account | E83: T017962802 | F83: Trung Tâm HCC Phường Kim Long | G83: 87 Phạm Thị Liên, phường Kim Long, TP. Huế | I83: Lê Văn Thìn | J83: T017962802 | L83: 178/2025/HĐ_BC-PHBC/BĐTT-TTPVHCCPKL | M83: 45839 | N83: Không xác định | O83: Không có | P83: 01 tháng/lần Trong 03 - 05 ngày làm việc tiếp theo kể từ ngày nhận được hoá đơn GTGT hợp lệ | S83: Đang hoạt động | T83: ĐẶNG TUẤN VŨ | U83: Dịch vụ HCC, luân chuyển hồ sơ HCC, KT1, EMS, Chuyển phát bưu phẩm trong nước và quốc tế | W83: Tài liệu | X83: 0.052 | Y83: 0.16666667 | Z83: 5000 | AA83: My VNP | AB83: 532760 | AC83: 532760_duongvt | AE83: Thực hiện theo quy định của TCT | AJ83: 162000 | AK83: Đang làm thanh toán | BB83: X | BD83: 160455 | BE83: 442175 | BF83: 0 | BG83: =SUM(BD83:BF83) -> 602630 | BH83: Hồ sơ vật lý và hồ sơ điện tử | BI83: Phát - Long | BJ83: 532760 | BK83: Kim Long | BL83: Phường Kim Long | BP83: X | BQ83: X | BR83: Bưu điện TT Thuận Hóa - Phú Xuân
A84: 82 | B84: 5310 | C84: Bưu điện TT Thuận Hóa - Phú Xuân | D84: SME | E84: T001799595 | F84: Công ty Yakult | G84: 61 đường số 5 an cựu city Tp Huế | H84: 0234 3861 542 | I84: Nguyễn Trần Công Phi | J84: T001799595 | K84: 3700723994-014 | L84: HĐ376-HĐBC-BĐTPH-CTYK | M84: 44169 | N84: Không xác định | O84: Không có | P84: Thanh toán vào tháng sau | S84: Đang hoạt động | T84: HỒ VĂN KỲ | U84: ETN001, ETN013 | W84: Hồ sơ | X84: 0.4 | Y84: 0.27 | Z84: 14536.8 | AB84: 536801 | AC84: 536801_tienttt | AE84: Theo quy định TCT | AF84: Không có yêu cầu khác. | AJ84: Đã thanh toán | AM84: 61 đường số 5 an cựu city Tp Huế | AN84: 08h00-10h00; 14h00-16h00 | AO84: 1-2 lần/tuần | AP84: 8 | AQ84: Xe máy | AS84: 45869 | BC84: X | BD84: 211800 | BE84: 271200 | BF84: 132000 | BG84: =SUM(BD84:BF84) -> 615000 | BH84: Hồ sơ vật lý và hồ sơ điện tử | BI84: Bảo + Ni | BJ84: 536801 | BK84: Phú Thượng | BL84: Phường Mỹ Thượng | BP84: X | BQ84: X | BR84: Bưu điện TT Thuận Hóa - Phú Xuân
A85: 83 | B85: 5310 | C85: Bưu điện TT Thuận Hóa - Phú Xuân | D85: SME | E85: T001799882 | F85: Công Ty Cổ Phần ICO Chi Nhánh Huế | G85: 42 Nguyễn Khánh Toàn, TP Huế | H85: ‭0905378177‬ | I85: Phạm Văn Diệu | J85: T001799882 | K85: 2400399209-016 | L85: 373/HĐBC/BĐTPH-CTCPYTICO | M85: 44169 | N85: Không xác định | O85: Không có | P85: Thanh toán vào tháng sau | S85: Đang hoạt động | T85: HỒ VĂN KỲ | U85: ETN001 | V85: GTG071 | W85: Hồ sơ | X85: 0.15 | Y85: 0.5 | Z85: 13127.23 | AB85: 536801 | AC85: 536801_tienttt | AE85: Theo quy định TCT | AF85: Không có yêu cầu khác. | AJ85: Đã thanh toán | AM85: 42 Nguyễn Khánh Toàn, TP Huế | AN85: 08h00-10h00; 14h00-16h00 | AO85: 1-2 lần/tuần | AP85: 15 | AQ85: Xe máy | AS85: 45869 | BC85: X | BD85: 1715400 | BE85: 966000 | BF85: 489000 | BG85: =SUM(BD85:BF85) -> 3170400 | BH85: Hồ sơ vật lý và hồ sơ điện tử | BI85: Bảo + Ni | BJ85: 536801 | BK85: Phú Thượng | BL85: Phường Mỹ Thượng | BP85: X | BQ85: x | BR85: Bưu điện TT Thuận Hóa - Phú Xuân
A86: 84 | B86: 5310 | C86: Bưu điện TT Thuận Hóa - Phú Xuân | D86: SME | E86: T001800798 | F86: Du Lịch Đại Bàng | G86: 115 Phạm Văn Đồng, phường Vỹ Dạ, Huế | H86: 0234.3936787 | I86: Lê Thị Hồng Tuyết | J86: T001800798 | K86: 3301494534 | L86: 269/2021/HĐBC/BĐTPH-DLDAIBANG | M86: 44272 | N86: Không xác định | O86: Không có | P86: Thanh toán vào tháng sau | S86: Đang hoạt động | T86: HỒ VĂN KỲ | U86: ETN001 | W86: Hồ sơ | X86: 0.05 | Y86: 0.17 | Z86: 2289.6 | AB86: 536801 | AC86: 536801_tienttt | AE86: Theo quy định TCT | AF86: Không có yêu cầu khác. | AJ86: Đã thanh toán | AM86: 115 Phạm Văn Đồng, phường Vỹ Dạ, Huế | AN86: 08h00-10h00; 14h00-16h00 | AO86: 1-2 lần/tuần | AP86: 5 | AQ86: Xe máy | AS86: 45869 | BC86: X | BD86: 200145 | BE86: 11400 | BF86: 147745 | BG86: =SUM(BD86:BF86) -> 359290 | BH86: Hồ sơ vật lý và hồ sơ điện tử | BI86: Bảo + Ni | BJ86: 536801 | BK86: Phú Thượng | BL86: Phường Mỹ Thượng | BP86: X | BQ86: X | BR86: Bưu điện TT Thuận Hóa - Phú Xuân
A87: 85 | B87: 5310 | C87: Bưu điện TT Thuận Hóa - Phú Xuân | D87: SME | E87: C003707155 | F87: CÔNG TY TNHH HÙNG GIA TRANG | G87: D37 Green,TL10-Phú Mỹ, Phú Vang,T T Huế | H87: 0985323235 | I87: Huỳnh Thị Tuệ Trang | J87: C003707155 | K87: 3301336506 | L87: HĐ466.2021-HĐBC-BĐTPH-HTTT | M87: 44455 | N87: Không xác định | O87: Không có | P87: 02 tuần/lần Thanh toán tại điểm giao dịch bên B | Q87: 01 tuần/lần Chuyển khoản | R87: 109813346789 Vietinbank Huỳnh Thị Tuệ Trang | T87: HỒ VĂN KỲ | U87: ETN001 | V87: GTG047 | W87: Hồ sơ | X87: 0.27 | Y87: 0.67 | Z87: 10238.4 | AB87: 536801 | AC87: 536801_tienttt | AE87: Theo quy định TCT | AF87: Không có yêu cầu khác. | AJ87: Đã thanh toán | AM87: D37 Green,TL10-Phú Mỹ, Phú Vang,T T Huế | AN87: 08h00-10h00; 14h00-16h00 | AO87: 1-2 lần/tuần | AP87: 20 | AQ87: Xe máy | AS87: 45869 | BC87: X | BD87: 168600 | BE87: 216010 | BF87: 17500 | BG87: =SUM(BD87:BF87) -> 402110 | BH87: Hồ sơ vật lý và hồ sơ điện tử | BI87: Rà soát để điều chỉnh lại bàn giao trên CMS | BJ87: 536801 | BK87: Phú Thượng | BL87: Phường Mỹ Thượng | BP87: X | BQ87: X | BR87: Bưu điện TT Thuận Hóa - Phú Xuân
A88: 86 | B88: 5310 | C88: Bưu điện TT Thuận Hóa - Phú Xuân | D88: Shop | E88: C005677266 | F88: Huế Farm | G88: 8 xuân hoà thuỷ vân huế | H88: 02343601111 | I88: Lê Thị Anh Thư | J88: C005677266 | K88: 3301688346 | L88: 162 HĐBC/BĐ-HF | M88: 44886 | N88: Không xác định | O88: Không có | P88: Trong 03 - 05 ngày làm việc tiếp theo kể từ ngày nhận được hoá đơn GTGT hợp lệ | S88: Đang hoạt động | T88: PHẠM THỊ THANH UYÊN | U88: CTN009 | W88: Dầu ăn | X88: 10.2 | Y88: 0.03 | Z88: 2268 | AB88: 536801 | AC88: 536801_tienttt | AE88: Theo quy định TCT | AF88: Không có yêu cầu khác. | AJ88: Đã thanh toán | AP88: 1 | AR88: Khách hàng tự mang đến bưu cục | AS88: 45842 | BB88: X | BD88: 59400 | BE88: 0 | BF88: 0 | BG88: =SUM(BD88:BF88) -> 59400 | BH88: Hồ sơ vật lý và hồ sơ điện tử | BI88: Rà soát để điều chỉnh lại bàn giao trên CMS | BJ88: 536801 | BK88: Phú Thượng | BL88: Phường Mỹ Thượng | BM88: X | BP88: X | BQ88: X | BR88: Bưu điện TT Thuận Hóa - Phú Xuân
A89: 87 | B89: 5310 | C89: Bưu điện TT Thuận Hóa - Phú Xuân | D89: Shop | E89: C004676750 | F89: TRẦN THỊ THU SƯƠNG | G89: Nhà 35 kiệt 2 Tỉnh lộ 10, Phường Phú Thượng, TP Huế | H89: 0934848499 | J89: C004676750 | L89: HĐ15.2022.HĐBC-BĐTPH-TTS | M89: 44615 | N89: Không xác định | O89: Không có | P89: Trong 03 - 05 ngày làm việc tiếp theo kể từ ngày nhận được hoá đơn GTGT hợp lệ | S89: Đang hoạt động | T89: HỒ VĂN KỲ | U89: CTN001 | W89: Bánh | X89: 1.88 | Y89: 0.03 | Z89: 1339.4 | AB89: 536801 | AC89: 536801_tienttt | AD89: BƯU TÁ LIÊN HỆ SĐT TRÊN VẬN ĐƠN | AE89: Theo quy định TCT | AF89: Không có yêu cầu khác. | AJ89: Đã thanh toán | AM89: Nhà 35 kiệt 2 Tỉnh lộ 10, Phường Phú Thượng, TP Huế | AP89: 1 | AR89: Khách hàng tự mang đến bưu cục | AS89: 45869 | BC89: X | BD89: 0 | BE89: 75951 | BF89: 333532 | BG89: =SUM(BD89:BF89) -> 409483 | BH89: Hồ sơ vật lý và hồ sơ điện tử | BI89: Rà soát để điều chỉnh lại bàn giao trên CMS | BJ89: 536801 | BK89: Phú Thượng | BL89: Phường Mỹ Thượng | BP89: X | BQ89: X | BR89: Bưu điện TT Thuận Hóa - Phú Xuân
A90: 88 | B90: 5310 | C90: Bưu điện TT Thuận Hóa - Phú Xuân | D90: Shop | E90: C001395857 | F90: Trần Thị Mai Liên | G90: 35/92 Đặng Huy Trứ, Phường Phước Vĩnh, TP Huế | H90: 0702626909 | I90: Trần Thị Mai Liên | J90: C001395857 | L90: 105/2021/HĐBC/BĐTPH-TTML | M90: 44271 | N90: Không xác định | O90: Không có | P90: Thanh toán cước khi chi trả cod | Q90: Thanh toán bằng CK (t2/t4/t6) | R90: 1913542797600 Techcombank Trần Thị Mai Liên | S90: Đang hoạt động | T90: PHẠM THỊ THANH UYÊN | U90: CTN009 | V90: GTG071;GTG021 | W90: Saffron, mật ong, máy xay, dầu gội phủ bạc, kem chống nắng | X90: 2.39 | Y90: 0.6 | Z90: 17795.1 | AB90: 536801 | AC90: 536801_tienttt | AE90: Theo quy định TCT | AF90: Không có yêu cầu khác. | AJ90: 212112 | AK90: đang làm thanh toán | AM90: 35/92 Đặng Huy Trứ, Phường Phước Vĩnh, TP Huế | AN90: 15h00-16h00 | AO90: 2-3 lần/tuần | AP90: 18 | AQ90: Xe máy | AS90: 45869 | BB90: X | BD90: 192000 | BE90: 872130 | BF90: 581125 | BG90: =SUM(BD90:BF90) -> 1645255 | BH90: Hồ sơ vật lý và hồ sơ điện tử | BI90: Rà soát để điều chỉnh lại bàn giao trên CMS | BJ90: 536801 | BK90: Phú Thượng | BL90: Phường Mỹ Thượng | BP90: X | BQ90: X | BR90: Bưu điện TT Thuận Hóa - Phú Xuân
A91: 89 | B91: 5310 | C91: Bưu điện TT Thuận Hóa - Phú Xuân | D91: SME | E91: T001864878 | F91: CÔNG TY TNHH IN ẤN NGỌC TẤN | G91: X. Phú Thượng H. Phú Vang Tỉnh Thừa Thiên Huế | H91: 0935567636 | J91: T001864878 | K91: 3301605082 | O91: Không có | P91: Thanh toán vào tháng sau | S91: Đang hoạt động | T91: HỒ VĂN KỲ | U91: CTN007 | V91: GTG071;GTG021 | W91: HỘP | X91: 2.64 | Y91: 0.03 | Z91: 1837.63 | AB91: 536801 | AC91: 536801_tienttt | AD91: BƯU TÁ LIÊN HỆ SĐT TRÊN VẬN ĐƠN | AE91: Theo quy định TCT | AF91: Không có yêu cầu khác. | AJ91: Đã thanh toán | AM91: X. Phú Thượng H. Phú Vang Tỉnh Thừa Thiên Huế | AN91: 08h00-10h00; 14h00-16h00 | AO91: 1-2 lần/tuần | AP91: 1 | AQ91: Xe máy | AS91: 45869 | BC91: X | BD91: 384970 | BE91: 57090 | BF91: 58445 | BG91: =SUM(BD91:BF91) -> 500505 | BH91: Hồ sơ vật lý và hồ sơ điện tử | BI91: Bảo + Ni | BJ91: 536801 | BK91: Phú Thượng | BL91: Phường Mỹ Thượng | BP91: X | BQ91: R | BR91: Bưu điện TT Thuận Hóa - Phú Xuân
A92: 90 | B92: 5310 | C92: Bưu điện TT Thuận Hóa - Phú Xuân | D92: Cá Nhân | E92: C008012733 | F92: Đê Car | G92: 01 Hồng Khẳng Vĩ Dạ THừa Thiên Huế | H92: 0796536793 | J92: C008012733 | L92: HĐ049.2024-HĐBC-BĐTPH-ĐC | M92: 45351 | S92: Đang hoạt động | T92: PHẠM THỊ THANH UYÊN | U92: CK344118117VN | W92: mâm ô tô^1^0^0 | AB92: 536801 | AC92: 536801_tienttt | BD92: 1092545 | BE92: 683545 | BF92: 0 | BG92: =SUM(BD92:BF92) -> 1776090 | BH92: Hồ sơ vật lý và hồ sơ điện tử | BI92: Bảo + Ni | BJ92: 536801 | BK92: Phú Thượng | BL92: Phường Mỹ Thượng | BP92: X | BQ92: R | BR92: Bưu điện TT Thuận Hóa - Phú Xuân
A93: 91 | B93: 5310 | C93: Bưu điện TT Thuận Hóa - Phú Xuân | D93: Cá Nhân | E93: C008302404 | F93: Sĩ Sạc Ác Quy | G93: Lô A8- KĐT Phú Mỹ Thượng | H93: 0352177110 | J93: C008302404 | L93: HĐ89.2024_HĐBC_BĐTPH_SSA | M93: 45404 | S93: Đang hoạt động | T93: PHẠM THỊ THANH UYÊN | U93: 0 | W93: ÁC QUY;1;0;0 | AB93: 536801 | AC93: 536801_tienttt | BD93: 108600 | BE93: 21000 | BF93: 0 | BG93: =SUM(BD93:BF93) -> 129600 | BH93: Hồ sơ vật lý và hồ sơ điện tử | BI93: Bảo + Ni | BJ93: 536801 | BK93: Phú Thượng | BL93: Phường Mỹ Thượng | BP93: X | BQ93: R | BR93: Bưu điện TT Thuận Hóa - Phú Xuân
A94: 92 | B94: 5310 | C94: Bưu điện TT Thuận Hóa - Phú Xuân | D94: Tổ Chức | E94: T018726408 | F94: CÔNG TY TNHH NGHIÊN CỨU VÀ PHÁT TRIỂN HUEFARM | G94: Kiệt 8, Xuân Hòa | H94: 0934927575 | J94: T018726408 | L94: HĐ260/BC-PHBC/BĐTP-HUEFARM | M94: 45952 | S94: Đang thực hiện | T94: HOÀNG HỮU QUANG | AB94: 536801 | AC94: 536801_tienttt | BD94: 269800 | BE94: 0 | BF94: 0 | BG94: =SUM(BD94:BF94) -> 269800 | BH94: Hồ sơ vật lý và hồ sơ điện tử | BI94: Bảo + Ni | BJ94: 536801 | BK94: Phú Thượng | BL94: Phường Mỹ Thượng | BP94: X | BQ94: R | BR94: Bưu điện TT Thuận Hóa - Phú Xuân
A95: 93 | B95: 5310 | C95: Bưu điện TT Thuận Hóa - Phú Xuân | D95: Tổ Chức | E95: T019251782 | F95: Công Ty TNHH MTV Sản Xuất Và Thương Mại Ba Hưng | G95: 222 Phạm Văn Đồng, Phường Mỹ Thượng, TP Huế | H95: 02342470004 | J95: T019251782 | L95: HĐ04.2026 | M95: 46035 | S95: Đang hoạt động | T95: Phan Thị Hoài Phương | U95: ETN001 | X95: 40 | Y95: 1 | Z95: 48600 | AB95: 536801 | AC95: 536801_tienttt | AD95: 0 | BD95: 0 | BE95: 48600 | BF95: 132000 | BG95: =SUM(BD95:BF95) -> 180600 | BI95: Rà soát để bàn giao trên CMS | BJ95: 536801 | BK95: Phú Thượng | BL95: Phường Mỹ Thượng | BP95: X | BR95: Bưu điện TT Thuận Hóa - Phú Xuân
A96: 94 | B96: 5310 | C96: Bưu điện TT Thuận Hóa - Phú Xuân | D96: Key Account | E96: T017959635 | F96: Trung Tâm HCC Phường Mỹ Thượng | G96: 449 Phạm Văn Đồng, phường Mỹ Thượng,TP. Huế | I96: Nguyễn Hữu Toàn | J96: T017959635 | L96: 174/2025/HĐ_BC-PHBC/BĐTT-TTPVHCCPMT | M96: 45839 | N96: Không xác định | O96: Không có | P96: 01 tháng/lần Trong 03 - 05 ngày làm việc tiếp theo kể từ ngày nhận được hoá đơn GTGT hợp lệ | S96: Đang hoạt động | T96: ĐẶNG TUẤN VŨ | U96: Dịch vụ HCC, luân chuyển hồ sơ HCC, KT1, EMS, Chuyển phát bưu phẩm trong nước và quốc tế | W96: Tài liệu | X96: 0.0375 | Y96: 0.066666667 | Z96: 2050 | AA96: My VNP | AB96: 536801 | AC96: 536801_tienttt | AE96: Thực hiện theo quy định của TCT | AJ96: 66420 | AK96: Đang làm thanh toán | BB96: X | BD96: 399500 | BE96: 61000 | BF96: 90500 | BG96: =SUM(BD96:BF96) -> 551000 | BH96: Hồ sơ vật lý và hồ sơ điện tử | BI96: Bảo + Ni | BJ96: 536801 | BK96: Phú Thượng | BL96: Phường Mỹ Thượng | BP96: X | BQ96: X | BR96: Bưu điện TT Thuận Hóa - Phú Xuân
A97: 95 | B97: 5310 | C97: Bưu điện TT Thuận Hóa - Phú Xuân | D97: Shop | E97: C005879192 | F97: Đặng Nhật Linh | G97: tỉnh lộ 10 | H97: 0906546112 | I97: Đặng Nhật Linh | J97: C005879192 | L97: HĐ05.2023-HĐBC-BĐTPH-CX | M97: 44963 | N97: Không xác định | P97: Nhận tiền COD thanh toán cước | Q97: Chuyển khoản | R97: 100006662680 Vietinbank Đặng Nhật Linh | S97: Đang hoạt động | T97: PHẠM THỊ THANH UYÊN | U97: CTN007, CTN009 | V97: GTG021 | W97: Đồ gia dụng, mỹ phẩm, đồ ăn, gia vị | X97: 2.59 | Y97: 0.9 | Z97: 20057 | AB97: 536810 | AC97: 536810_laint | AD97: 0 | AE97: Theo quy định của TCT | AJ97: đã thanh toán | AM97: tỉnh lộ 10 | AN97: 08h00-09h00 và 14h00-15hh0 | AO97: 1 lân / ngày | AP97: 27 | AQ97: Xe máy | AS97: 45862 | AV97: Hàng tuần | BB97: X | BD97: 869227 | BE97: 216315 | BF97: 465715 | BG97: =SUM(BD97:BF97) -> 1551257 | BH97: Hồ sơ vật lý và hồ sơ điện tử | BI97: Bảo + Ni | BJ97: 536810 | BK97: Trung Đông | BL97: Phường Mỹ Thượng | BM97: X | BP97: X | BQ97: X | BR97: Bưu điện TT Thuận Hóa - Phú Xuân
A98: 96 | B98: 5310 | C98: Bưu điện TT Thuận Hóa - Phú Xuân | D98: Shop | E98: C017231723 | F98: Lê Văn Bảo | G98: trung đông, X. Phú Thượng H. Phú Vang Tỉnh Thừa Thiên Huế | H98: 0868821121 | I98: Lê Văn Bảo | J98: C017231723 | L98: HĐ97.2025-HĐBC-BĐTPH-DH | M98: 45748 | N98: Không xác định | P98: 1-2 lần/tháng | S98: Đang hoạt động | T98: VÕ KHẮC QUÝ | U98: CTN001 CTN007 | W98: Thuốc men | X98: 0.93 | Y98: 2 | Z98: 121585 | AB98: 536810 | AC98: 536810_laint | AD98: Bưu tá liên hệ phát theo sdt trên đơn hàng, KHông phát được liên hệ ngay người gủi, kb | AE98: Thực hiện theo quy định của TCT | AJ98: Đã thanh toán công nợ | AM98: trung đông, X. Phú Thượng H. Phú Vang Tỉnh Thừa Thiên Huế | AN98: 15h00-17h00 | AO98: 1 lần/ngày | AP98: 68 | AQ98: xe máy | AS98: 45855 | BC98: X | BD98: 1400067 | BE98: 325200 | BF98: 0 | BG98: =SUM(BD98:BF98) -> 1725267 | BH98: Hồ sơ vật lý và hồ sơ điện tử | BI98: Bảo + Ni | BJ98: 536810 | BK98: Trung Đông | BL98: Phường Mỹ Thượng | BP98: X | BQ98: X | BR98: Bưu điện TT Thuận Hóa - Phú Xuân
A99: 97 | B99: 5310 | C99: Bưu điện TT Thuận Hóa - Phú Xuân | D99: Shop | E99: C001411475 | F99: Bùi ngọc tân | G99: Phú Mậu, Phú Vang, TT Huế | H99: 0702644663 | I99: Bùi ngọc tân | J99: C001411475 | L99: HĐ:82/HĐBC/BĐHPV-BNT | M99: 44501 | N99: Không xác định | P99: Thanh toán cước KHi chi trả cod | Q99: Thanh toán TM theo yều cầu KH | S99: Đang hoạt động | T99: HỒ VĂN KỲ | U99: CTN009 | V99: GTG021 | W99: Nhông sên | X99: 14.712424 | Y99: 1.1 | Z99: 90806.667 | AB99: 536810 | AC99: 536810_laint | AE99: Thực hiện theo quy định của TCT | AJ99: Đã thanh toán công nợ | AM99: Phú Mậu, Phú Vang, TT Huế | AN99: 15h00-17h00 | AO99: 1 lần/ngày | AP99: 33 | AQ99: xe máy | AS99: 45853 | BC99: X | BD99: 3619000 | BE99: 4010470 | BF99: 664000 | BG99: =SUM(BD99:BF99) -> 8293470 | BH99: Hồ sơ vật lý và hồ sơ điện tử | BI99: Bảo + Ni | BJ99: 536810 | BK99: Trung Đông | BL99: Phường Mỹ Thượng | BM99: X | BP99: X | BQ99: X | BR99: Bưu điện TT Thuận Hóa - Phú Xuân
A100: 98 | B100: 5310 | C100: Bưu điện TT Thuận Hóa - Phú Xuân | D100: Shop | E100: C007575168 | F100: Dương Thị Diệu Hoà | G100: Xóm 2 Thôn Phò an, X. Phú Dương H. Phú Vang Tỉnh Thừa Thiên Huế | H100: 0388848023 | J100: C007575168 | L100: HĐ005.2024-HĐBC-BĐTPH-DH | M100: 45300 | N100: Không xác định | O100: Không có | P100: Thanh toán cước ngay khi gửi | R100: Chuyển khoản | S100: Đang hoạt động | T100: PHẠM THỊ THANH UYÊN | U100: CTN009 | V100: GTG021 | W100: hoa kẽm nhung | X100: 4.71 | Y100: 0.2 | Z100: 7596 | AB100: 536810 | AC100: 536810_laint | AD100: Bưu tá liên hệ phát theo sdt trên đơn hàng, kb | AE100: Theo quy định TCT | AF100: Không có yêu cầu khác. | AJ100: Đã thanh toán | AM100: Xóm 2 Thôn Phò an, X. Phú Dương H. Phú Vang Tỉnh Thừa Thiên Huế | AP100: 6 | AR100: Khách hàng tự mang đến bưu cục | AS100: 45869 | BB100: X | BD100: 1714000 | BE100: 1250000 | BF100: 103400 | BG100: =SUM(BD100:BF100) -> 3067400 | BH100: Hồ sơ vật lý và hồ sơ điện tử | BI100: Bảo + Ni | BJ100: 536810 | BK100: Trung Đông | BL100: Phường Mỹ Thượng | BP100: X | BQ100: x | BR100: Bưu điện TT Thuận Hóa - Phú Xuân
...

Sheet Sheet1
A1: 1387 | B1: Đơn vị | C1: Tên đơn vị | D1: Loại KHách hàng | E1: Thông tin đơn hàng | V1: Đặc điểm đơn hàng | AK1: Công nợ | AN1: Yêu cầu thu gom | AT1: Lịch sử chăm sóc KHách hàng | AX1: KPI & mục tiêu Đã cam kết | AZ1: Nhóm KHách hàng | BE1: Doanh thu tháng 12/2025 | BF1: Doanh thu tháng 01/2026 | BG1: Doanh thu tháng 02/2026 (01/02-22/02) | BH1: Doanh thu 3 tháng | BI1: THÔNG TIN CHI TIẾT | BJ1: GHI CHÚ | BK1: Mã BC | BL1: Tên BC/VHX | BM1: BĐP/X | BN1: Cước đặc thù | BO1: Người rà soát bàn giao TTKD | BP1: Người rà soát bàn giao TTVH | BQ1: Đơn vị đã gắn HĐ trên CMS | BR1: Đã gửi HĐ vật lý lên TTKD | BS1: Tên đơn vị
A2: TT | E2: Mã CRM/CMS | G2: Tên KHách hàng | H2: Địa chỉ | I2: Điện thoại | J2: Người liên hệ | K2: Mã CRM/CMS | L2: Mã số thuế | M2: Số hợp đồng | N2: Thời hạn hợp đồng | O2: Thời hạn kết thúc | P2: Phụ lục, thoả thuận bổ sung Hợp đồng | Q2: Thời gian, quy định việc thanh toán cước BCCP ghi nợ | R2: Hình thức, thời gian thanh toán tiền thu hộ COD | S2: Số tài KHoản nhận tiền thu hộ COD, phí ship | T2: Trạng thái hoạt động | U2: Người quản lý KHách hàng (Họ tên, số điện thoại, email) | V2: Dịch vụ sử dụng | W2: Dịch vụ GTGT KHác | X2: Nội dung hàng hóa gửi | Y2: KHối lượng dự kiến/bưu gửi | Z2: Sản lượng bình quân/ngày | AA2: Doanh thu bình quân/ngày | AB2: Hình thức phát hành: KH dùng My VNP/exel/thủ công…. | AC2: Bưu cục ghi nhận doanh thu (số hiệu bưu cục, tên bưu cục) | AD2: Tài KHoản trên Portal KHL ghi nhận doanh thu | AE2: Chú dẫn yêu cầu chuyển phát | AF2: Chỉ tiêu thời gian toàn trình dịch vụ | AG2: Yêu cầu KHác: - Gia công, đóng gói - Thuê KHo,... (nếu có) - KHác biệt về thời gian cutoff (nếu có) - ......(nếu có) | AH2: KHiếu nại, chốt phạt bồi thường (KHác biệt nếu có) | AI2: [ ] KHách hàng có cấu hình hệ thống đặc biệt cần duy trì? | AJ2: [ ] Có dịch vụ tuỳ chỉnh hay tích hợp đặc thù? | AK2: [ ] KHách hàng còn công nợ chưa thanh toán? | AL2: [ ] Có lịch trình thu hồi hoặc xử lý công nợ? | AM2: Hình thức phạt đối với chậm trả nợ | AN2: Địa chỉ thu gom (chi tiết đến phường/xã, quận/huyện,..) | AO2: Thời gian thu gom | AP2: Tần suất thu gom | AQ2: Sản lượng thu gom | AR2: Phương tiện thu gom | AS2: KHác biệt thu gom (nếu có) | AT2: [ ] Tương tác gần nhất với KHách hàng | AU2: [ ] Ghi chú yêu cầu đặc biệt hoặc sự cố đang xử lý | AV2: [ ] Cam kết dịch vụ Đã thực hiện | AW2: [ ] Kế hoạch chăm sóc định kỳ | AX2: [ ] Cam kết chất lượng hoặc KPI giữa KHách hàng và Trung tâm Kinh doanh | AY2: [ ] Theo dõi mức độ hoàn thành và kế hoạch tiếp tục | AZ2: KHách hàng sàn TMĐT | BA2: KH tạo đơn bằng phần mềm bán hàng | BB2: KH tạo đơn và gửi thông tin qua API cho BĐVN | BC2: Tạo đơn trên PM MyVNP | BD2: Tạo đơn trên phần mềm Portal KHL | BI2: THÔNG TIN CHI TIẾT
A3: 1 | B3: 5310 | C3: Bưu điện TT Thuận Hóa - Phú Xuân | D3: SME | E3: T004890545 | F3: SME | G3: Công Ty Cổ Phần Toyota Huế | H3: Lô C, KĐT Phú Mỹ An, Đường Tố Hữu, An Đông, TP Huế | I3: 02436299696 | J3: Lê Thế Vỹ | K3: T004890545 | L3: 3301635376 | M3: HĐ54-2022_HĐBC_BĐTPH-MTL | N3: 01/5/2022 | O3: Không xác định | Q3: 1-2 lần/tháng | T3: Đang hoạt động | U3: HỒ VĂN KỲ | V3: ETN001 | X3: Thư | Y3: 17.14 | Z3: 2 | AA3: 51292 | AC3: 533810 | AD3: 533810_dungntt | AF3: Thực hiện theo quy định của TCT | AK3: 3181837 | AL3: Đang liên hệ thanh toán | AN3: Lô C, KĐT Phú Mỹ An, Đường Tố Hữu, An Đông, TP Huế | AO3: 14h00-17h00 | AP3: 1 lần/ngày | AQ3: 66 | AR3: xe máy | AT3: 45855 | BC3: X | BE3: 1862866 | BF3: 2425140 | BG3: 813058 | BH3: 5101064 | BI3: Hồ sơ vật lý và hồ sơ điện tử | BJ3: Phát - Long | BK3: 533810 | BL3: Thuỷ An | BM3: Phường An Cựu | BQ3: X | BR3: X | BS3: Bưu điện TT Thuận Hóa - Phú Xuân
A4: 2 | B4: 5310 | C4: Bưu điện TT Thuận Hóa - Phú Xuân | D4: Shop | E4: C001395675 | F4: Shop | G4: VÕ HOÀNG MINH | H4: Đường số 7, An Cựu City, P An Đông, TP Huế | I4: 0932436536 | J4: VÕ HOÀNG MINH | K4: C001395675 | M4: 151/HĐBC-BĐTP/VHM | N4: 43685 | O4: Không xác định | Q4: Thanh toán ngay khi gửi | T4: Đang hoạt động | U4: PHẠM THỊ THANH UYÊN | V4: ETN011 | X4: TRANH VE | Y4: 3.5743333 | Z4: 0.1 | AA4: 6994.4 | AC4: 533810 | AD4: 533810_dungntt | AF4: Theo quy định TCT | AG4: Không có yêu cầu khác. | AK4: đã thanh toán | AN4: Đường số 7, An Cựu City, P An Đông, TP Huế | AO4: 09h00-11h00; 15h00-17h00 | AP4: 1-2 lần/tuần | AQ4: 3 | AR4: Xe máy | AT4: 45782 | BC4: X | BE4: 232290 | BF4: 175356 | BG4: 0 | BH4: 407646 | BI4: Hồ sơ vật lý và hồ sơ điện tử | BJ4: Phát - Long | BK4: 533810 | BL4: Thuỷ An | BM4: Phường An Cựu | BQ4: X | BR4: X | BS4: Bưu điện TT Thuận Hóa - Phú Xuân
A5: 3 | B5: 5310 | C5: Bưu điện TT Thuận Hóa - Phú Xuân | D5: SME | E5: T001799661 | F5: SME | G5: CÔNG TY TNHH TM QUỐC HÙNG | H5: 86 HÙNG VƯƠNG, TP HUẾ | I5: 0989020237 | J5: Nguyễn Trần Như Ý | K5: T001799661 | L5: 3300338476 | M5: 384/HĐBC/BĐTPH-CTQUOCHUNG | N5: 44169 | O5: Không xác định | P5: Không có | Q5: 01 tháng/lần Thanh toán tại địa chỉ bên A | T5: Đang hoạt động | U5: HỒ VĂN KỲ | V5: ETN011, ETN011 | X5: Phụ tùng xe máy | Y5: 0.41 | Z5: 0.33 | AA5: 13125.6 | AC5: 533810 | AE5: SỐ ĐT NTO GHI TRÊN ĐƠN HÀNG.TSK | AF5: Theo quy định TCT | AG5: Không có yêu cầu khác. | AK5: 759.888 | AL5: đang thanh toán | AN5: 86 HÙNG VƯƠNG, TP HUẾ | AO5: 09h00-11h00; 15h00-17h00 | AP5: 1-2 lần/tuần | AQ5: 10 | AR5: Xe máy | AT5: 45869 | BD5: X | BE5: 0 | BF5: 0 | BG5: 18000 | BH5: 18000 | BI5: Hồ sơ vật lý và hồ sơ điện tử | BJ5: Phát - Long | BK5: 533810 | BL5: Thuỷ An | BM5: Phường An Cựu | BQ5: X | BR5: X | BS5: Bưu điện TT Thuận Hóa - Phú Xuân
A6: 4 | B6: 5310 | C6: Bưu điện TT Thuận Hóa - Phú Xuân | D6: SME | E6: T001456556 | F6: SME | G6: Công ty luật TNHH Nhật Nam và cộng sự | H6: 52 Hoàng Văn Thụ, P An Đông, TP Huế | I6: 0234.3936155 | J6: Trần Nhật Nam | K6: T001456556 | L6: 3301516202 | M6: 149/HĐBC-BĐTP/TNN | N6: 43685 | O6: Không xác định | P6: Không có | Q6: Thanh toán vào tháng sau | T6: Đang hoạt động | U6: PHẠM THỊ THANH UYÊN | V6: ETN001 | Y6: 0.07 | Z6: 0.87 | AA6: 12283.2 | AC6: 533810 | AD6: 533810_dungntt | AE6: SỐ ĐT NTO GHI TRÊN ĐƠN HÀNG.TKS | AF6: Theo quy định TCT | AG6: Không có yêu cầu khác. | AK6: 2,605,824 | AL6: khách hàng chậm trả | AN6: 52 Hoàng Văn Thụ, P An Đông, TP Huế | AO6: 09h00-11h00; 15h00-17h00 | AP6: 1-2 lần/tuần | AQ6: 26 | AR6: Xe máy | AT6: 45869 | BD6: X | BE6: 459600 | BF6: 223200 | BG6: 138400 | BH6: 821200 | BI6: Hồ sơ vật lý và hồ sơ điện tử | BJ6: Phát - Long | BK6: 533810 | BL6: Thuỷ An | BM6: Phường An Cựu | BQ6: X | BR6: X | BS6: Bưu điện TT Thuận Hóa - Phú Xuân
A7: 5 | B7: 5310 | C7: Bưu điện TT Thuận Hóa - Phú Xuân | D7: SME | E7: T001799967 | F7: SME | G7: CÔNG TY TNHH MTV PHÁT LÊ | H7: 108 TRƯỜNG CHINH, P. An Đông TP. Huế Tỉnh Thừa Thiên Huế | I7: 0234.3934999 | J7: Trần Thị Thúy Nhi | K7: T001799967 | L7: 3301335118 | M7: 391/HĐBC/BĐTPH-PL | N7: 44168 | O7: Không xác định | P7: Không có | Q7: Thanh toán vào tháng sau | R7: Ngay khi sử dụng dịch vụ Thanh toán tại địa chỉ bên A | T7: Đang hoạt động | U7: HỒ VĂN KỲ | V7: ETN001, CTN001 | X7: Tài liệu | Y7: 1.12 | Z7: 0.27 | AA7: 7325.63 | AC7: 533810 | AD7: 533810_dungntt | AE7: SỐ ĐT NTO GHI TRÊN ĐƠN HÀNG.TKS | AF7: Theo quy định TCT | AG7: Không có yêu cầu khác. | AK7: đã thanh toán | AN7: 108 TRƯỜNG CHINH, P. An Đông TP. Huế Tỉnh Thừa Thiên Huế | AO7: 09h00-11h00; 15h00-17h00 | AP7: 1-2 lần/tuần | AQ7: 8 | AR7: Xe máy | AT7: 45869 | BD7: X | BE7: 334254 | BF7: 226908 | BG7: 179175 | BH7: 740337 | BI7: Hồ sơ vật lý và hồ sơ điện tử | BJ7: Phát - Long | BK7: 533810 | BL7: Thuỷ An | BM7: Phường An Cựu | BQ7: X | BR7: X | BS7: Bưu điện TT Thuận Hóa - Phú Xuân
A8: 6 | B8: 5310 | C8: Bưu điện TT Thuận Hóa - Phú Xuân | D8: SME | E8: C001929335 | F8: SME | G8: Công Ty Tnhh Tm Tân Quốc Hùng | H8: 128 hùng vương, P. Phú Hội TP. Huế Tỉnh Thừa Thiên Huế | I8: 02343811015 | J8: Võ Văn Hùng | K8: C001929335 | L8: 3300556058 | M8: 389/HĐBC | N8: 44228 | O8: Không xác định | P8: Không có | Q8: Thanh toán vào tháng sau | T8: Đang hoạt động | U8: PHẠM THỊ THANH UYÊN | V8: ETN001 | Y8: 0.05 | Z8: 0.17 | AA8: 2376 | AC8: 533810 | AD8: 533810_dungntt | AE8: SỐ ĐT NTO GHI TRÊN ĐƠN HÀNG.TKS | AF8: Theo quy định TCT | AG8: Không có yêu cầu khác. | AK8: đã thanh toán | AN8: 128 hùng vương, P. Phú Hội TP. Huế Tỉnh Thừa Thiên Huế | AO8: 09h00-11h00; 15h00-17h00 | AP8: 1-2 lần/tuần | AQ8: 5 | AR8: Xe máy | AT8: 45869 | BD8: X | BE8: 82200 | BF8: 100200 | BG8: 0 | BH8: 182400 | BI8: Hồ sơ vật lý và hồ sơ điện tử | BJ8: Phát - Long | BK8: 533810 | BL8: Thuỷ An | BM8: Phường An Cựu | BQ8: X | BR8: x | BS8: Bưu điện TT Thuận Hóa - Phú Xuân
A9: 7 | B9: 5310 | C9: Bưu điện TT Thuận Hóa - Phú Xuân | D9: SME | E9: T002490015 | F9: SME | G9: Công Ty Cổ Phần Tập Đoàn IUC | H9: Tầng 3, Tòa nhà Vinaconex 7, số 64 Đường Nguyễn Văn Giáp , phường Cầu Diễn, Quận Nam Từ Liêm, Hà Nội | I9: 0908576568 | J9: Nguyễn Thành Công | K9: T002490015 | L9: 0104230537 | M9: 383.2021/HĐBC-BĐTPH-IUC | N9: 44389 | O9: Không xác định | P9: Không có | Q9: Thanh toán vào tháng sau | T9: Đang hoạt động | U9: HỒ VĂN KỲ | V9: ETN001 | Y9: 0.07 | Z9: 0.1 | AA9: 2008.8 | AC9: 533810 | AD9: 533810_dungntt | AE9: SỐ ĐT NTO GHI TRÊN ĐƠN HÀNG.TKS | AF9: Theo quy định TCT | AG9: Không có yêu cầu khác. | AK9: đã thanh toán | AN9: Tầng 3, Tòa nhà Vinaconex 7, số 64 Đường Nguyễn Văn Giáp , phường Cầu Diễn, Quận Nam Từ Liêm, Hà Nội | AO9: 09h00-11h00; 15h00-17h00 | AP9: 1-2 lần/tuần | AQ9: 3 | AR9: Xe máy | AT9: 45869 | BD9: X | BE9: 96600 | BF9: 84600 | BG9: 245158 | BH9: 426358 | BI9: Hồ sơ vật lý và hồ sơ điện tử | BJ9: Phát - Long | BK9: 533810 | BL9: Thuỷ An | BM9: Phường An Cựu | BQ9: X | BR9: X | BS9: Bưu điện TT Thuận Hóa - Phú Xuân
A10: 8 | B10: 5310 | C10: Bưu điện TT Thuận Hóa - Phú Xuân | D10: Shop | E10: C005695891 | F10: Shop | G10: Lê Thị Mỹ Hiền | H10: 04 Hoàng Văn Thụ, P. Xuân Phú TP. Huế Tỉnh Thừa Thiên Huế | I10: 0775555986 | K10: C005695891 | M10: HĐ170-HĐBC-BĐTP-LTMH | N10: 44890 | O10: Không xác định | P10: Không có | Q10: 01 tháng/lần Thanh toán tại địa chỉ bên A | T10: Đang hoạt động | U10: PHẠM THỊ THANH UYÊN | V10: ETN037 | W10: GTG021 | X10: thư | Y10: 0.05 | Z10: 0.07 | AA10: 1188 | AC10: 533810 | AD10: 533810_dungntt | AF10: Theo quy định TCT | AG10: Không có yêu cầu khác. | AK10: đã thanh toán | AN10: 04 Hoàng Văn Thụ, P. Xuân Phú TP. Huế Tỉnh Thừa Thiên Huế | AQ10: 2 | AS10: Khách hàng tự mang đến bưu cục | AT10: 45869 | BC10: X | BE10: 51200 | BF10: 1182500 | BG10: 986000 | BH10: 2219700 | BI10: Hồ sơ vật lý và hồ sơ điện tử | BJ10: Phát - Long | BK10: 533810 | BL10: Thuỷ An | BM10: Phường An Cựu | BQ10: X | BR10: X | BS10: Bưu điện TT Thuận Hóa - Phú Xuân
A11: 9 | B11: 5310 | C11: Bưu điện TT Thuận Hóa - Phú Xuân | D11: SME | E11: T001799573 | F11: SME | G11: CTY CP BĐS MINH ĐIỀN VITAL | H11: Khu đô thị The Manor Crown, Xuân Phú, TP huế | I11: 0907024029 | J11: Đặng Mạnh Cường | K11: T001799573 | L11: 3301350500 | M11: HĐ394-HĐBC-BĐTPH-VITAL | N11: 44169 | O11: Không xác định | P11: Không có | Q11: Thanh toán vào tháng sau | T11: Đang hoạt động | U11: HỒ VĂN KỲ | V11: ETN001 | Y11: 0.06 | Z11: 0.07 | AA11: 820.8 | AC11: 533810 | AD11: 533810_dungntt | AE11: SỐ ĐT NTO GHI TRÊN ĐƠN HÀNG.TKS | AF11: Theo quy định TCT | AG11: Không có yêu cầu khác. | AK11: 157.464 | AL11: đang làm thanh toán | AN11: Khu đô thị The Manor Crown, Xuân Phú, TP huế | AO11: 09h00-11h00; 15h00-17h00 | AP11: 1-2 lần/tuần | AQ11: 2 | AR11: Xe máy | AT11: 45869 | BD11: X | BE11: 357000 | BF11: 365200 | BG11: 208800 | BH11: 931000 | BI11: Hồ sơ vật lý và hồ sơ điện tử | BJ11: Phát - Long | BK11: 533810 | BL11: Thuỷ An | BM11: Phường An Cựu | BQ11: X | BR11: X | BS11: Bưu điện TT Thuận Hóa - Phú Xuân
A12: 10 | B12: 5310 | C12: Bưu điện TT Thuận Hóa - Phú Xuân | D12: SME | E12: T001399385 | F12: SME | G12: CÔNG TY CỔ PHẦN VẬN TẢI VÀ DỊCH VỤ PETROLIMEX THỪA THIÊN HUẾ | I12: 02343812117 | J12: Chị Trang | K12: T001399385 | M12: 100/HĐBC-BĐTP/CTY PERTOLIMEX | N12: 06/06/2017 | O12: Không xác định | Q12: 1 lần/ tháng | T12: Đang hoạt động | U12: PHẠM THỊ THANH UYÊN | V12: ETN013 | X12: TÀI LIỆU | Y12: 0.14375 | Z12: 32 | AA12: 32150 | AC12: 533810 | AD12: 533810_dungntt | AE12: BƯU TÁ VUI LÒNG LH SĐT NGƯỜI NHẬN TRÊN BG ĐỂ PHÁT HÀNH | AF12: Theo quy định của TCT | AK12: 1,983,636 | AL12: đang thanh toán | AN12: 13 Trần Thanh Mại, phường An Cựu | AO12: 14h00-16h00 | AP12: 1 lân / ngày | AQ12: 35 | AR12: Xe máy | AT12: 45862 | AW12: Khi có yêu cầu | BD12: X | BE12: 4097925 | BF12: 1407542 | BG12: 222700 | BH12: 5728167 | BI12: Hồ sơ vật lý và hồ sơ điện tử | BJ12: vũ - lan | BK12: 533810 | BL12: Thuỷ An | BM12: Phường An Cựu | BQ12: X | BR12: X | BS12: Bưu điện TT Thuận Hóa - Phú Xuân
A13: 11 | B13: 5310 | C13: Bưu điện TT Thuận Hóa - Phú Xuân | D13: SME | E13: T001799834 | F13: SME | G13: CÔNG TY CỔ PHẦN XÂY DỰNG VÀ ĐẦU TƯ XUÂN PHÚ | H13: NHÀ 17 ĐƯỜNG SỐ 4 AN CỰU CITY, P. An Cựu TP. Huế Tỉnh Thừa Thiên Huế | I13: 0705358292 | J13: Lê Thanh Hà | K13: T001799834 | L13: 3301545034 | M13: HĐ377-HĐBC-BĐTPH-CTCPVXDĐTXP | N13: 44169 | O13: Không xác định | P13: Không có | Q13: Thanh toán trong tháng sau | T13: Đang hoạt động | U13: HỒ VĂN KỲ | V13: ETN001 | Y13: 0.58 | Z13: 0.1 | AA13: 5335.2 | AC13: 533810 | AD13: 533810_dungntt | AE13: BƯU TÁ LIÊN HỆ SĐT TRÊN BG ĐỂ PHÁT HÀNG | AF13: Theo quy định TCT | AG13: Không có yêu cầu khác. | AK13: đã thanh toán | AN13: NHÀ 17 ĐƯỜNG SỐ 4 AN CỰU CITY, P. An Cựu TP. Huế Tỉnh Thừa Thiên Huế | AO13: 14h00-17h00 | AP13: 1-2 lần/tháng | AQ13: 3 | AR13: Xe máy | AT13: 45869 | BD13: X | BE13: 0 | BF13: 9600 | BG13: 37200 | BH13: 46800 | BI13: Hồ sơ vật lý và hồ sơ điện tử | BJ13: Bảo + Hương | BK13: 533810 | BL13: Thuỷ An | BM13: Phường An Cựu | BQ13: X | BR13: x | BS13: Bưu điện TT Thuận Hóa - Phú Xuân
A14: 12 | B14: 5310 | C14: Bưu điện TT Thuận Hóa - Phú Xuân | D14: SME | E14: T001800268 | F14: SME | G14: TRƯỜNG CAO ĐẲNG Y TẾ | H14: 1 NGUYỄN TRƯỜNG TỘ, TP HUẾ | I14: 0234.3822414 | J14: Văn Thư | K14: T001800268 | L14: 3300369717 | M14: 253/2021/HĐBC/BĐTP-CĐYTE | N14: 44272 | O14: Không xác định | Q14: 1 lần/ tháng | T14: Đang hoạt động | U14: HỒ VĂN KỲ | V14: ETN001, ETN013 | X14: Tài liệu | Y14: 0.04 | Z14: 0.97 | AA14: 18101 | AC14: 533810 | AD14: 533810_dungntt | AE14: BƯU TÁ VUI LÒNG LIÊN HỆ SĐT NGƯỜI NHẬN TRÊN BƯU GỬI ĐỂ PHÁT HÀNG | AF14: Theo quy định của TCT | AK14: đã thanh toán | AN14: 1 NGUYỄN TRƯỜNG TỘ, TP HUẾ | AO14: 14h-15h | AP14: 1 lần/ ngày | AQ14: 29 | AR14: xe máy | AT14: hằng ngày | AU14: BƯU TÁ VUI LÒNG LIÊN HỆ SĐT NGƯỜI NHẬN TRÊN BƯU GỬI ĐỂ PHÁT HÀNG | AV14: KHÔNG ĐƯỢC CẬP NHẬT KHỐNG TT PHÁT , NHẬP ĐẦY ĐỦ TT NGƯỜI NHẬN , NGƯỜI NHẬN THAY | BD14: X | BE14: 26000 | BF14: 0 | BG14: 0 | BH14: 26000 | BI14: Hồ sơ vật lý và hồ sơ điện tử | BJ14: Rà soát để điều chỉnh lại bàn giao trên CMS | BK14: 533810 | BL14: Thuỷ An | BM14: Phường An Cựu | BQ14: X | BR14: X | BS14: Bưu điện TT Thuận Hóa - Phú Xuân
A15: 13 | B15: 5310 | C15: Bưu điện TT Thuận Hóa - Phú Xuân | D15: Shop | E15: C016607629 | F15: Shop | G15: Cánh Buồm | H15: Lô A34 Đường số 2 KĐT An Cựu City, P. An Đông TP. Huế Tỉnh Thừa Thiên Huế | J15: Cánh Buồm | K15: C016607629 | Q15: 1 lần/1 tháng | T15: Đang hoạt động | U15: PHẠM THỊ THANH UYÊN | V15: ETN011 | W15: GTG021 | X15: Tài liệu | Y15: 0.077638889 | Z15: 2.4 | AA15: 65123.5 | AC15: 533810 | AD15: 533810_dungntt | AF15: Thực hiện theo quy định của TCT | AK15: Đã thanh toán công nợ | AN15: Lô A34 Đường số 2 KĐT An Cựu City, P. An Đông TP. Huế Tỉnh Thừa Thiên Huế | AO15: 15h00-17h00 | AP15: 1 lần/ngày | AQ15: 72 | AR15: xe máy | AT15: 45856 | BD15: X | BE15: 741025 | BF15: 481435 | BG15: 0 | BH15: 1222460 | BI15: Hồ sơ vật lý và hồ sơ điện tử | BJ15: Phát - Long | BK15: 533810 | BL15: Thuỷ An | BM15: Phường An Cựu | BQ15: X | BR15: R | BS15: Bưu điện TT Thuận Hóa - Phú Xuân
A16: 14 | B16: 5310 | C16: Bưu điện TT Thuận Hóa - Phú Xuân | D16: SME | E16: T005217327 | F16: SME | G16: Công Ty Cổ Phần BWB-chi Nhánh Huế | H16: Tầng 6 tháp The Manor Crown | J16: Tuyết | K16: T005217327 | L16: 0107763981-002 | Q16: Thanh toán vào tháng sau | T16: Đang hoạt động | U16: PHẠM THỊ THANH UYÊN | V16: ETN001 | Y16: 0.065 | Z16: 0.066666667 | AA16: 1231.2 | AC16: 533810 | AD16: 533810_dungntt | AF16: Theo quy định TCT | AG16: Không có yêu cầu khác. | AK16: 31.752 | AL16: đang làm thanh toán | AN16: Tầng 6 tháp The Manor Crown | AO16: 09h00-11h00; 15h00-17h00 | AP16: 1-2 lần/tuần | AQ16: 2 | AR16: Xe máy | AT16: 45869 | BD16: X | BE16: 0 | BF16: 18000 | BG16: 0 | BH16: 18000 | BI16: Hồ sơ vật lý và hồ sơ điện tử | BJ16: Phát - Long | BK16: 533810 | BL16: Thuỷ An | BM16: Phường An Cựu | BQ16: X | BR16: R | BS16: Bưu điện TT Thuận Hóa - Phú Xuân
A17: 15 | B17: 5310 | C17: Bưu điện TT Thuận Hóa - Phú Xuân | D17: Cá Nhân | E17: C018726221 | F17: Cá Nhân | G17: Nguyễn Huyền Tôn Nữ Ái Vân | H17: 08 Tố Hữu, P. Xuân Phú , Quận Thuận Hóa, TP. Huế | I17: 0899489952 | K17: C018726221 | M17: 259.202TH5/HĐBC/BĐKVTHPX-NHTNAV | N17: 45952 | T17: Đang hoạt động | U17: NGUYỄN BÁ TRÀ MI | AC17: 533810 | AD17: 533810_dungntt | BE17: 204518 | BF17: 117295 | BG17: 79036 | BH17: 400849 | BJ17: Rà soát để bàn giao trên CMS | BK17: 533810 | BL17: Thuỷ An | BM17: Phường An Cựu | BN17: X | BQ17: X | BR17: R | BS17: Bưu điện TT Thuận Hóa - Phú Xuân
A18: 16 | B18: 5310 | C18: Bưu điện TT Thuận Hóa - Phú Xuân | D18: Cá Nhân | E18: C018656707 | F18: Cá Nhân | G18: Nguyễn Ngọc Phú | H18: 189 Bà Triệu - Thuận Hóa - Thành Phố Huế | I18: 0898254999 | K18: C018656707 | T18: Đang hoạt động | U18: NGUYỄN BÁ TRÀ MI | AC18: 533810 | AD18: 533810_dungntt | BE18: 59000 | BF18: 0 | BG18: 0 | BH18: 59000 | BJ18: Lan - Thắm | BK18: 533810 | BL18: Thuỷ An | BM18: Phường An Cựu | BQ18: X | BR18: R | BS18: Bưu điện TT Thuận Hóa - Phú Xuân
A19: 17 | B19: 5310 | C19: Bưu điện TT Thuận Hóa - Phú Xuân | D19: Cá Nhân | E19: C018477419 | F19: Cá Nhân | G19: Nhà May Duy Tuấn | H19: 134 Trường Chinh - Phường An Cựu - Thành Phố Huế | I19: 0908680906 | K19: C018477419 | U19: NGUYỄN BÁ TRÀ MI | AC19: 533810 | AD19: 533810_dungntt | BE19: 143523 | BF19: 145703 | BG19: 144945 | BH19: 434171 | BJ19: Lan - Thắm/Phát - Long | BK19: 533810 | BL19: Thuỷ An | BM19: Phường An Cựu | BQ19: X | BR19: R | BS19: Bưu điện TT Thuận Hóa - Phú Xuân
A20: 18 | B20: 5310 | C20: Bưu điện TT Thuận Hóa - Phú Xuân | D20: Tổ Chức | E20: T018318911 | F20: Tổ Chức | G20: CÔNG AN PHƯỜNG AN CỰU | H20: 18 Hoàng Quốc Việt | I20: 02343817234 | K20: T018318911 | M20: HĐ230.2025-HĐBC-PHBC-BĐTP-CAPHUONGANCUU | N20: 45887 | T20: Đang thực hiện | U20: NGUYỄN BÁ TRÀ MI | AC20: 533810 | AD20: 533810_dungntt | BE20: 135200 | BF20: 502345 | BG20: 249172 | BH20: 886717 | BJ20: Phát - Long | BK20: 533810 | BL20: Thuỷ An | BM20: Phường An Cựu | BQ20: X | BR20: R | BS20: Bưu điện TT Thuận Hóa - Phú Xuân
A21: 19 | B21: 5310 | C21: Bưu điện TT Thuận Hóa - Phú Xuân | D21: Cá Nhân | E21: C018568551 | F21: Cá Nhân | G21: CÔNG TY CỔ PHẦN TẬP ĐOÀN BẢO HIỂM DBV - CN HUẾ | H21: Tầng 2 tòa nhà 189 Phạm Văn Đồng, Phường Vỹ Dạ, Thành Phố Huế | I21: 097258523 | K21: C018568551 | M21: 249.202TH5/HĐBC/BĐKVTHPX-DBV | N21: 45931 | T21: Đang thực hiện | U21: NGUYỄN BÁ TRÀ MI | AC21: 533810 | AD21: 533810_dungntt | BE21: 493600 | BF21: 574300 | BG21: 215000 | BH21: 1282900 | BJ21: Rà soát để bàn giao trên CMS | BK21: 533810 | BL21: Thuỷ An | BM21: Phường An Cựu | BQ21: X | BR21: R | BS21: Bưu điện TT Thuận Hóa - Phú Xuân
A22: 20 | B22: 5310 | C22: Bưu điện TT Thuận Hóa - Phú Xuân | D22: Cá Nhân | E22: C018388055 | F22: Cá Nhân | G22: Shin shop | H22: phong chương phong điền | I22: 0764768555 | K22: C018388055 | M22: HĐ235.2025_HĐBC-BĐH_HTN | N22: 45908 | T22: Đang thực hiện | U22: NGUYỄN BÁ TRÀ MI | AC22: 533810 | AD22: 533810_dungntt | BE22: 94495 | BF22: 16400 | BG22: 28259 | BH22: 139154 | BJ22: Rà soát để bàn giao trên CMS | BK22: 533810 | BL22: Thuỷ An | BM22: Phường An Cựu | BN22: X | BQ22: X | BR22: R | BS22: Bưu điện TT Thuận Hóa - Phú Xuân
A23: 21 | B23: 5310 | C23: Bưu điện TT Thuận Hóa - Phú Xuân | D23: Cá Nhân | E23: C018272260 | F23: Cá Nhân | G23: đinh thị phượng | H23: bến xe phía nam phường an cựu | I23: 0814767134 | K23: C018272260 | M23: HĐ232.2025_HĐBC_BĐH_ĐTP | N23: 45887 | T23: Đang thực hiện | U23: NGUYỄN BÁ TRÀ MI | AC23: 533810 | AD23: 533810_dungntt | BE23: 0 | BF23: 601000 | BG23: 0 | BH23: 601000 | BJ23: Rà soát để bàn giao trên CMS | BK23: 533810 | BL23: Thuỷ An | BM23: Phường An Cựu | BQ23: X | BR23: R | BS23: Bưu điện TT Thuận Hóa - Phú Xuân
A24: 22 | B24: 5310 | C24: Bưu điện TT Thuận Hóa - Phú Xuân | D24: Tổ Chức | E24: T018411531 | F24: Tổ Chức | G24: Phú Xuân Travel | H24: 51 Bà Triệu, Vỹ Dạ, Thành Phố Huế | I24: 0902882168 | K24: T018411531 | M24: 239.2025/HĐBC/BĐKVTHPX-PXT | N24: 45909 | T24: Đang thực hiện | U24: NGUYỄN BÁ TRÀ MI | AC24: 533810 | AD24: 533810_dungntt | BE24: 45100 | BF24: 0 | BG24: 0 | BH24: 45100 | BJ24: Lan - Thắm | BK24: 533810 | BL24: Thuỷ An | BM24: Phường An Cựu | BQ24: X | BR24: R | BS24: Bưu điện TT Thuận Hóa - Phú Xuân
A25: 23 | B25: 5310 | C25: Bưu điện TT Thuận Hóa - Phú Xuân | D25: Cá Nhân | E25: C018894162 | F25: Cá Nhân | G25: ÁO DÀI ĐAN PHƯƠNG | H25: 08 Đường Bà Triệu, P. Phú Hội, Quận Phú Xuân | I25: 0914478999 | K25: C018894162 | M25: 264.2025/HĐBC/BĐKVTHPX-ADĐP | N25: 45976 | T25: Đang hoạt động | V25: ETN011 | W25: GTG071 | Y25: 4373 | Z25: 2 | AA25: 208290 | AC25: 533810 | AD25: 533810_dungntt | AE25: hỗ trợ phát ngay khi đến, cám ơn. | BE25: 801395 | BF25: 694351 | BG25: 448215 | BH25: 1943961 | BI25: Chưa có thông tin | BJ25: Rà soát để điều chỉnh lại bàn giao trên CMS | BK25: 533810 | BL25: Thuỷ An | BM25: Phường An Cựu | BQ25: X | BR25: R | BS25: Bưu điện TT Thuận Hóa - Phú Xuân
A26: 24 | B26: 5310 | C26: Bưu điện TT Thuận Hóa - Phú Xuân | D26: Tổ Chức | E26: T018894468 | F26: Tổ Chức | G26: Văn Phòng HĐND Và UBND Phường An Cựu | H26: 67A Đường Hoàng Quốc Việt, P. An Cựu, Quận Phú Xuân | K26: T018894468 | M26: 262.2025/HĐBC/BĐKVTHPX-HĐN-UBNDPAC | N26: 45976 | T26: Đang hoạt động | V26: ETN001 | W26: 0 | Y26: 120 | Z26: 3 | AA26: 32500 | AC26: 533810 | AD26: 533810_dungntt | AE26: 0 | BE26: 168600 | BF26: 498745 | BG26: 89200 | BH26: 756545 | BJ26: Rà soát để bàn giao trên CMS | BK26: 533810 | BL26: Thuỷ An | BM26: Phường An Cựu | BQ26: X | BR26: R | BS26: Bưu điện TT Thuận Hóa - Phú Xuân
A27: 25 | B27: 5310 | C27: Bưu điện TT Thuận Hóa - Phú Xuân | D27: Cá Nhân | E27: C019136875 | F27: Cá Nhân | G27: May store | H27: số nhà 18 kiệt 154 bà triệu, Phường Thuận Hóa, TP Huế | I27: 0365156019 | K27: C019136875 | M27: 285/2025/HĐ_BC-PHBC/BĐTP-MAYSTORE | N27: 46023 | T27: Đang hoạt động | U27: NGUYỄN BÁ TRÀ MI | V27: CTN009; CTN007 | W27: GTG021; GTG047;GTG021 | Y27: 774.02914 | Z27: 398 | AA27: 8262457 | AC27: 533810 | AD27: 533810_dungntt | AE27: Không cho xem hàng, gọi cho người gửi trước khi chuyển hoàn | BE27: 0 | BF27: 8262457 | BG27: 4628564 | BH27: 12891021 | BJ27: Rà soát để bàn giao trên CMS | BK27: 533810 | BL27: Thuỷ An | BM27: Phường An Cựu | BN27: X | BQ27: X | BS27: Bưu điện TT Thuận Hóa - Phú Xuân
A28: 26 | B28: 5310 | C28: Bưu điện TT Thuận Hóa - Phú Xuân | D28: Cá Nhân | E28: C001395300 | F28: Cá Nhân | G28: Cô Lộc | H28: 4/4/4 Kiệt 33 An Dương Vương An Cựu TP Huế | I28: 0918581215 | K28: C001395300 | M28: 49/HĐBC/BĐTPH-CL | N28: 44256 | T28: Đang hoạt động | U28: PHẠM THỊ THANH UYÊN | V28: CTN001; CTN007 | W28: GTG021; GTG071 | Y28: 861.35211 | Z28: 41 | AA28: 1974993 | AC28: 533810 | AD28: 533810_dungntt | AE28: gọi sđt trên đơn hàng | BE28: 0 | BF28: 1974993 | BG28: 848485 | BH28: 2823478 | BJ28: Phát - Long | BK28: 533810 | BL28: Thuỷ An | BM28: Phường An Cựu | BQ28: X | BS28: Bưu điện TT Thuận Hóa - Phú Xuân
A29: 27 | B29: 5310 | C29: Bưu điện TT Thuận Hóa - Phú Xuân | D29: Cá Nhân | E29: C019370201 | F29: Cá Nhân | G29: Võ Nhật Bình | H29: Thôn Bằng Lãng, Thuỷ Bằng, Phường Thủy Xuân, TP Huế | I29: 0867676257 | K29: C019370201 | M29: 01/2026-HĐ/BCCP/BDTPHUE-BDAC-DNB | N29: 46050 | T29: Đang hoạt động | U29: NGUYỄN BÁ TRÀ MI | V29: CTN009 | W29: GTG021 | Y29: 1300 | Z29: 5 | AA29: 166668 | AC29: 533810 | AD29: 533810_dungntt | AE29: Hàng dễ vỡ, vui lòng nhẹ tay; Cho xem hàng không cho đụng vào hàng | BE29: 0 | BF29: 166668 | BG29: 277780 | BH29: 444448 | BJ29: Rà soát để bàn giao trên CMS | BK29: 533810 | BL29: Thuỷ An | BM29: Phường An Cựu | BN29: X | BQ29: X | BS29: Bưu điện TT Thuận Hóa - Phú Xuân
A30: 28 | B30: 5310 | C30: Bưu điện TT Thuận Hóa - Phú Xuân | D30: Key Account | E30: T017963860 | F30: Key Account | G30: Trung Tâm HCC Phường An Cựu | H30: 67A Hoàng Quốc Việt, Phường An Cựu, TP Huế | J30: Phan Đăng Phú Khánh | K30: T017963860 | M30: 175/2025/HĐ_BC-PHBC/BĐTT-TTPVHCCPAC | N30: 45839 | O30: Không xác định | P30: Không có | Q30: 01 tháng/lần Trong 03 - 05 ngày làm việc tiếp theo kể từ ngày nhận được hoá đơn GTGT hợp lệ | T30: Đang hoạt động | U30: ĐẶNG TUẤN VŨ | V30: Dịch vụ HCC, luân chuyển hồ sơ HCC, KT1, EMS, Chuyển phát bưu phẩm trong nước và quốc tế | X30: Tài liệu | Y30: 0.05125 | Z30: 0.4 | AA30: 11000 | AB30: My VNP | AC30: 533810 | AD30: 533810_dungntt | AF30: Thực hiện theo quy định của TCT | AK30: 356400 | AL30: Đang làm thanh toán | BC30: X | BE30: 1091340 | BF30: 1058397 | BG30: 399441 | BH30: 2549178 | BI30: Hồ sơ vật lý và hồ sơ điện tử | BJ30: Lan - Thắm | BK30: 533810 | BL30: Thuỷ An | BM30: Phường An Cựu | BN30: X | BQ30: X | BR30: X | BS30: Bưu điện TT Thuận Hóa - Phú Xuân
A31: 29 | B31: 5310 | C31: Bưu điện TT Thuận Hóa - Phú Xuân | D31: Tổ Chức | E31: T019531120 | F31: Tổ Chức | G31: CÔNG TY TNHH DỊCH VỤ SẢN XUẤT PDM VIỆT NAM | H31: 314 Văn Thánh, phường Kim Long, Thành Phố Huế, Việt Nam | K31: T019531120 | M31: 18 /2026/ HĐ¬BC-PHBC/BĐTPHUE-PDM | N31: 46079 | T31: Đang hoạt động | U31: NGUYỄN BÁ TRÀ MI | AC31: 533810 | BE31: 0 | BF31: 0 | BG31: 0 | BH31: 0 | BJ31: Rà soát để bàn giao trên CMS | BK31: 533810 | BL31: Thuỷ An | BM31: Phường An Cựu | BS31: Bưu điện TT Thuận Hóa - Phú Xuân
A32: 30 | B32: 5310 | C32: Bưu điện TT Thuận Hóa - Phú Xuân | D32: Shop | E32: C017177801 | F32: Shop | G32: Duyên Trần | H32: xóm 11, X. Phú Mậu H. Phú Vang Tỉnh Thừa Thiên Huế | I32: 0775875875 | J32: Trần Thị Ái Duyên | K32: C017177801 | M32: HĐ56.2025.HĐBC-BĐTTTHPX-DT | N32: 45740 | O32: Không xác định | P32: Không có | Q32: Thanh toán vào tháng sau | R32: Thứ 2,4,6 hàng tuần Chuyển khoản | S32: 0825898192 MBBank Trần Thị Ái Duyên | T32: Đang hoạt động | U32: PHẠM THỊ THANH UYÊN | V32: CTN007, CTN009 | W32: GTG021 | X32: Mỹ phẩm | Y32: 0.46 | Z32: 0.57 | AA32: 8420 | AC32: 536790 | AD32: 536790_menpt | AF32: Theo quy định TCT | AG32: Không có yêu cầu khác. | AK32: Đã thanh toán | AN32: xóm 11, X. Phú Mậu H. Phú Vang Tỉnh Thừa Thiên Huế | AQ32: 17 | AS32: Khách hàng tự mang đến bưu cục | AT32: 45869 | BC32: X | BE32: 19000 | BF32: 82834 | BG32: 0 | BH32: 101834 | BI32: Chưa có thông tin | BJ32: Bảo + Ni | BK32: 536790 | BL32: Phú Mậu | BM32: Phường Dương Nỗ | BN32: X | BQ32: X | BR32: X | BS32: Bưu điện TT Thuận Hóa - Phú Xuân
A33: 31 | B33: 5310 | C33: Bưu điện TT Thuận Hóa - Phú Xuân | D33: Shop | E33: C016429937 | F33: Shop | G33: Nguyễn Thị Phương Thảo | H33: xóm 11, làng Thanh Tiên, xã Phú Mậu, TP Huế | I33: 0898194881 | K33: C016429937 | M33: HĐ221-HĐBC-BĐTP-NTPT | N33: 45637 | O33: Không xác định | P33: Không có | Q33: Trong 03 - 05 ngày làm việc tiếp theo kể từ ngày nhận được hoá đơn GTGT hợp lệ | T33: Đang hoạt động | U33: PHẠM THỊ THANH UYÊN | V33: CTN001, CTN007 | W33: GTG021 | X33: hoa giấy, chông | Y33: 1.27 | Z33: 0.2 | AA33: 8039.87 | AC33: 536790 | AD33: 536790_menpt | AF33: Theo quy định TCT | AG33: Không có yêu cầu khác. | AK33: Đã thanh toán | AN33: xóm 11, làng Thanh Tiên, xã Phú Mậu, TP Huế | AQ33: 6 | AS33: Khách hàng tự mang đến bưu cục | AT33: 45869 | BC33: X | BE33: 9237000 | BF33: 5179300 | BG33: 2331600 | BH33: 16747900 | BI33: Hồ sơ vật lý và hồ sơ điện tử | BJ33: Bảo + Ni | BK33: 536790 | BL33: Phú Mậu | BM33: Phường Dương Nỗ | BQ33: X | BR33: X | BS33: Bưu điện TT Thuận Hóa - Phú Xuân
A34: 32 | B34: 5310 | C34: Bưu điện TT Thuận Hóa - Phú Xuân | D34: Shop | E34: C016227458 | F34: Shop | G34: Võ Thị Mỹ Phố | H34: kiệt 5 nguyễn hữu cảnh | I34: 0346429532 | J34: Võ Thị Mỹ Phố | K34: C016227458 | M34: HĐ190.2024_HĐBC_BĐTPH-VTMP | N34: 45607 | O34: Không xác định | Q34: Thanh toán cước khi chi trả cod | R34: CK qua ngân hàng (2,4,6 hằng tuần) | S34: 88184868 MB Bank | T34: Đang hoạt động | U34: PHẠM THỊ THANH UYÊN | V34: CTN007 | W34: GTG021 | X34: Ti Giả Avent | Y34: 1.5175 | Z34: 0.066666667 | AA34: 1089.3333 | AC34: 536790 | AD34: 536790_menpt | AF34: Theo quy định TCT | AG34: Không có yêu cầu khác. | AK34: 139512 | AL34: đang làm thanh toán | AN34: kiệt 5 nguyễn hữu cảnh | AO34: 15h00-16h00 | AP34: 2-3 lần/tuần | AQ34: 2 | AR34: Xe máy | AT34: 45869 | BC34: X | BE34: 161807 | BF34: 0 | BG34: 0 | BH34: 161807 | BI34: Hồ sơ vật lý và hồ sơ điện tử | BJ34: Rà soát để điều chỉnh lại bàn giao trên CMS | BK34: 536790 | BL34: Phú Mậu | BM34: Phường Dương Nỗ | BN34: X | BQ34: X | BR34: X | BS34: Bưu điện TT Thuận Hóa - Phú Xuân
A35: 33 | B35: 5310 | C35: Bưu điện TT Thuận Hóa - Phú Xuân | D35: Cá Nhân | E35: C018988315 | F35: Cá Nhân | G35: Hoài Trinh | H35: Đối diện xóm 6, Mậu Tài, P. Dương Nỗ, Quận Thuận Hóa | I35: 0774507105 | K35: C018988315 | T35: Đang hoạt động | V35: CTN007 | W35: GTG021 | Y35: 162300 | Z35: 76 | AA35: 3073500 | AC35: 536790 | AD35: 536790_menpt | AE35: 0 | BE35: 4095235 | BF35: 3533867 | BG35: 665366 | BH35: 8294468 | BJ35: Rà soát để bàn giao trên CMS | BK35: 536790 | BL35: Phú Mậu | BM35: Phường Dương Nỗ | BS35: Bưu điện TT Thuận Hóa - Phú Xuân
A36: 34 | B36: 5310 | C36: Bưu điện TT Thuận Hóa - Phú Xuân | D36: Cá Nhân | E36: C019314788 | F36: Cá Nhân | G36: Nguyễn Hiếu | H36: Thanh Vinh, phường Dương Nỗ, TP Huế | I36: 0343318436 | K36: C019314788 | M36: HĐ08-2026-HĐBC-BĐKVTHPX- NH | N36: 46042 | T36: Đang hoạt động | U36: HOÀNG VĂN DUY | V36: CTN007; ETN031 | W36: GTG021 | Y36: 1606.25 | Z36: 8 | AA36: 4279200 | AC36: 536790 | AD36: 536790_menpt | AE36: 0 | BE36: 0 | BF36: 4279200 | BG36: 371000 | BH36: 4650200 | BJ36: Rà soát để bàn giao trên CMS | BK36: 536790 | BL36: Phú Mậu | BM36: Phường Dương Nỗ | BQ36: X | BS36: Bưu điện TT Thuận Hóa - Phú Xuân
A37: 35 | B37: 5310 | C37: Bưu điện TT Thuận Hóa - Phú Xuân | D37: Cá Nhân | E37: C019416597 | F37: Cá Nhân | G37: nguyễn hữu thảo | H37: kiệt 19, trung đông, phú thượng, tp huế | I37: 0777550775 | K37: C019416597 | M37: C019416597 | N37: 46056 | T37: Đang hoạt động | U37: HOÀNG VĂN DUY | Y37: 900 | Z37: 1 | AA37: 36000 | AC37: 536790 | BE37: 0 | BF37: 0 | BG37: 36000 | BH37: 36000 | BJ37: Rà soát để bàn giao trên CMS | BK37: 536790 | BL37: Phú Mậu | BM37: Phường Dương Nỗ | BQ37: X | BS37: Bưu điện TT Thuận Hóa - Phú Xuân
A38: 36 | B38: 5310 | C38: Bưu điện TT Thuận Hóa - Phú Xuân | D38: Key Account | E38: T017963459 | F38: Key Account | G38: Trung Tâm HCC Phường Dương Nỗ | H38: Tổ dân phố Mậu Tài, phường Dương Nỗ, TP. Huế | I38: 0234676722 | J38: Trần Quang Dũng | K38: T017963459 | M38: 172/2025/HĐ_BC-PHBC/BĐTT-TTPVHCCPDN | N38: 45839 | O38: Không xác định | P38: Không có | Q38: 01 tháng/lần Trong 03 - 05 ngày làm việc tiếp theo kể từ ngày nhận được hoá đơn GTGT hợp lệ | T38: Đang hoạt động | U38: ĐẶNG TUẤN VŨ | V38: Dịch vụ HCC, luân chuyển hồ sơ HCC, KT1, EMS, Chuyển phát bưu phẩm trong nước và quốc tế | X38: Tài liệu | Y38: 0.067714286 | Z38: 0.46666667 | AA38: 12133.333 | AB38: My VNP | AC38: 536790 | AD38: 536790_menpt | AF38: Thực hiện theo quy định của TCT | AK38: 393120 | AL38: Đang làm thanh toán | BC38: X | BE38: 952200 | BF38: 768500 | BG38: 271500 | BH38: 1992200 | BI38: Hồ sơ vật lý và hồ sơ điện tử | BJ38: Bảo + Ni | BK38: 536790 | BL38: Phú Mậu | BM38: Phường Dương Nỗ | BQ38: X | BR38: X | BS38: Bưu điện TT Thuận Hóa - Phú Xuân
A39: 37 | B39: 5310 | C39: Bưu điện TT Thuận Hóa - Phú Xuân | D39: Tổ Chức | E39: T018859231 | F39: Tổ Chức | G39: Công An Phường Hoá Châu | H39: TDP Vân Quật Thượng, X. Hương Phong, TX. Hương Trà | I39: 0986244166 | K39: T018859231 | T39: Đang hoạt động | V39: KT1007 | W39: 0 | Y39: 210 | Z39: 10 | AA39: 274763 | AC39: 535350 | AD39: 535350_lannh | AE39: 0 | BE39: 557275 | BF39: 572124 | BG39: 185990 | BH39: 1315389 | BI39: Hồ sơ vật lý | BJ39: Rà soát để điều chỉnh lại bàn giao trên CMS | BK39: 535350 | BL39: Hương Vinh | BM39: Phường Hóa Châu | BN39: X | BS39: Bưu điện TT Thuận Hóa - Phú Xuân
A40: 38 | B40: 5310 | C40: Bưu điện TT Thuận Hóa - Phú Xuân | D40: Key Account | E40: T017963122 | F40: Key Account | G40: UBND Phường Hóa Châu | H40: đường Thanh Hà, TDP Tây Thành, phường Hóa Châu, TP. Huế | J40: Võ Việt Đức | K40: T017963122 | M40: 191/2025/HĐ_BC-PHBC/BĐTT-VPUBHC | N40: 45839 | O40: Không xác định | P40: Không có | Q40: 01 tháng/lần Trong 03 - 05 ngày làm việc tiếp theo kể từ ngày nhận được hoá đơn GTGT hợp lệ | T40: Đang hoạt động | U40: ĐẶNG TUẤN VŨ | V40: Dịch vụ HCC, luân chuyển hồ sơ HCC, KT1, EMS, Chuyển phát bưu phẩm trong nước và quốc tế | X40: Tài liệu | Y40: 0 | Z40: 0.033333333 | AA40: 0 | AB40: My VNP | AC40: 535350 | AD40: 535350_lannh | AF40: Thực hiện theo quy định của TCT | AK40: Không có | AL40: Đang làm thanh toán | BC40: X | BE40: 195745 | BF40: 0 | BG40: 0 | BH40: 195745 | BI40: Hồ sơ vật lý và hồ sơ điện tử | BJ40: Bảo + Ni | BK40: 535350 | BL40: Hương Vinh | BM40: Phường Hóa Châu | BQ40: X | BR40: X | BS40: Bưu điện TT Thuận Hóa - Phú Xuân
A41: 39 | B41: 5310 | C41: Bưu điện TT Thuận Hóa - Phú Xuân | D41: Key Account | E41: T017963286 | F41: Key Account | G41: Trung Tâm HCC Phường Hóa Châu | H41: đường Thanh Hà, TDP Tây Thành, phường Hóa Châu, TP. Huế | J41: Võ Việt Đức | K41: T017963286 | M41: 170/2025/HĐ_BC-PHBC/BĐTT-TTPVHCCPHC | N41: 45839 | O41: Không xác định | P41: Không có | Q41: 01 tháng/lần Trong 03 - 05 ngày làm việc tiếp theo kể từ ngày nhận được hoá đơn GTGT hợp lệ | T41: Đang hoạt động | U41: ĐẶNG TUẤN VŨ | V41: Dịch vụ HCC, luân chuyển hồ sơ HCC, KT1, EMS, Chuyển phát bưu phẩm trong nước và quốc tế | X41: Tài liệu | Y41: 0 | Z41: 1.8333333 | AA41: 0 | AB41: My VNP | AC41: 530000 | AD41: 530000_miennt | AF41: Thực hiện theo quy định của TCT | AK41: Không có | AL41: Đang làm thanh toán | BC41: X | BE41: 470045 | BF41: 31000 | BG41: 0 | BH41: 501045 | BI41: Hồ sơ vật lý và hồ sơ điện tử | BJ41: Bảo + Ni | BK41: 535350 | BL41: Hương Vinh | BM41: Phường Hóa Châu | BQ41: X | BR41: X | BS41: Bưu điện TT Thuận Hóa - Phú Xuân
A42: 40 | B42: 5310 | C42: Bưu điện TT Thuận Hóa - Phú Xuân | D42: Key Account | E42: T001800047 | F42: Key Account | G42: Trung Tâm Pháp Y Tâm Thần Khu Vực Miền Trung | H42: 39 Phạm Thị Liên, Phường Kim Long, TP Huế | I42: 0935772389 | K42: T001800047 | M42: 160/2021/HĐBC/BĐTP-TTPHAPY | N42: 15/03/2021 | O42: Không xác định | Q42: Thanh toán vào tháng sau | U42: HỒ VĂN KỲ | V42: ETN001 | X42: Tài liệu | Y42: 0.04 | Z42: 1.5 | AA42: 22277 | AC42: 532950 | AD42: 532950_trangbtb | AE42: 0 | AF42: Theo quy định của TCT | AK42: 668.304 | AL42: đang thanh toán | AN42: 39 Phạm Thị Liên, Phường Kim Long, TP Huế | AO42: 13h30-14h30 | AP42: 1-2 lần/tuần | AQ42: 45 | AR42: Xe máy | AT42: 45858 | BD42: X | BE42: 960400 | BF42: 1095600 | BG42: 339600 | BH42: 2395600 | BI42: Hồ sơ vật lý và hồ sơ điện tử | BJ42: Minh - Long | BK42: 532950 | BL42: An Hoà | BM42: Phường Hương An | BQ42: X | BR42: X | BS42: Bưu điện TT Thuận Hóa - Phú Xuân
A43: 41 | B43: 5310 | C43: Bưu điện TT Thuận Hóa - Phú Xuân | D43: Shop | E43: C001396353 | F43: Shop | G43: Nguyễn Ngọc Cầu | H43: Tổ 13 KHu vực 5 An Hòa, TP Huế, P. An Hòa, Quận Phú Xuân, TP. Huế | I43: 0387848315 | J43: Nguyễn Ngọc Cầu | K43: C001396353 | M43: 141/2021/HĐBC/BĐTPH-NNCAU | N43: 44270 | O43: Không xác định | Q43: Thanh toán cước KHi chi trả cod | R43: Thanh toán TM theo yêu cầu KH | T43: Đang hoạt động | U43: PHẠM THỊ THANH UYÊN | V43: CTN001 | W43: GTG021 | X43: CÂY CẢNH | Y43: 0.72484615 | Z43: 2.1666667 | AA43: 71305.1 | AC43: 532950 | AD43: 532950_trangbtb | AF43: Thực hiện theo quy định của TCT | AK43: Đã thanh toán công nợ | AN43: Tổ 13 KHu vực 5 An Hòa, TP Huế, P. An Hòa, Quận Phú Xuân, TP. Huế | AQ43: 65 | AT43: 45856 | BC43: X | BE43: 80750 | BF43: 84006 | BG43: 0 | BH43: 164756 | BI43: Hồ sơ vật lý và hồ sơ điện tử | BJ43: Minh - Long | BK43: 532950 | BL43: An Hoà | BM43: Phường Hương An | BQ43: X | BR43: X | BS43: Bưu điện TT Thuận Hóa - Phú Xuân
A44: 42 | B44: 5310 | C44: Bưu điện TT Thuận Hóa - Phú Xuân | D44: Shop | E44: C016958917 | F44: Shop | G44: Trần như quỳnh | H44: 448 Lê Duẫn | I44: 0932415390 | J44: Trần Như Quỳnh | K44: C016958917 | M44: HĐ23-2025-HĐBH-BĐTTHPX-SUNDAY | N44: 45709 | O44: Không xác định | Q44: Thanh toán khi nhận tiền cod | R44: CK qua ngân hàng (2,4,6 hằng tuần) | S44: 0932415390 MB Bank | T44: Đang hoạt động | U44: PHẠM THỊ THANH UYÊN | V44: CTN009 | Y44: 0.5 | Z44: 0.033333333 | AA44: 684 | AC44: 532950 | AD44: 532950_trangbtb | AF44: Theo quy định TCT | AG44: Không có yêu cầu khác. | AK44: Đã thanh toán | AN44: 448 Lê Duẫn | AQ44: 1 | AS44: Khách hàng tự mang đến bưu cục | AT44: 45812 | BC44: X | BE44: 16400 | BF44: 19000 | BG44: 56145 | BH44: 91545 | BI44: Hồ sơ vật lý và hồ sơ điện tử | BJ44: Minh - Long | BK44: 532950 | BL44: An Hoà | BM44: Phường Hương An | BN44: X | BQ44: X | BR44: X | BS44: Bưu điện TT Thuận Hóa - Phú Xuân
A45: 43 | B45: 5310 | C45: Bưu điện TT Thuận Hóa - Phú Xuân | D45: SME | E45: C007520178 | F45: SME | G45: Trung Tâm Công Tác Xã Hội Và Quỹ Bảo Trợ Trẻ Em Tỉnh Thừa Thiên Huế | H45: 65 Đặng Tất, An Hoà, Thừa Thiên Huế | I45: 0775518598 | K45: C007520178 | L45: 3301723537 | M45: HĐ006.2024-HĐBC-BĐTPH-QBT | N45: 45302 | O45: Không xác định | Q45: Thanh toán vào tháng sau | T45: Đang hoạt động | U45: PHẠM THỊ THANH UYÊN | V45: ETN001 | Y45: 0.05365 | Z45: 0.66666667 | AA45: 8323.2 | AC45: 532950 | AD45: 532950_trangbtb | AF45: Theo quy định TCT | AG45: Không có yêu cầu khác. | AK45: Đã thanh toán | AN45: 65 Đặng Tất, An Hoà, Thừa Thiên Huế | AO45: 14h00-15h00 | AP45: 2-3 lần/tuần | AQ45: 5 | AR45: Xe máy | AT45: 45869 | BD45: X | BE45: 138000 | BF45: 300200 | BG45: 96000 | BH45: 534200 | BI45: Hồ sơ vật lý và hồ sơ điện tử | BJ45: Minh - Long | BK45: 532950 | BL45: An Hoà | BM45: Phường Hương An | BQ45: X | BR45: X | BS45: Bưu điện TT Thuận Hóa - Phú Xuân
A46: 44 | B46: 5310 | C46: Bưu điện TT Thuận Hóa - Phú Xuân | D46: Shop | E46: C002139719 | F46: Shop | G46: Trần Thanh Hải | H46: 157 Tăng Bạt Hổ, Phú Thuận,TP Huế | I46: 0901172224 | K46: C002139719 | M46: 317/2021/HĐBC/BĐTPH-TTHAI | N46: 44286 | O46: Không xác định | P46: Không có | Q46: 01 tuần/lần Chuyển khoản | R46: 01 tuần/lần Chuyển khoản | S46: 55110000788469 BIDV Trần Thanh Hải | T46: Đang hoạt động | U46: HỒ VĂN KỲ | V46: CTN007, CTN009, ETN011, CTN001 | W46: GTG021 | X46: Đồ gốm xưa, mảnh sành sứ | Y46: 1.83 | Z46: 0.37 | AA46: 13549.93 | AC46: 532950 | AD46: 532950_trangbtb | AE46: *BƯU TÁ LIÊN HỆ THEO SĐT TRÊN BƯU GỬI" | AF46: Theo quy định TCT | AG46: Không có yêu cầu khác. | AK46: Đã thanh toán | AN46: 157 Tăng Bạt Hổ, Phú Thuận,TP Huế | AQ46: 11 | AS46: Khách hàng tự mang đến bưu cục | AT46: 45869 | BD46: X | BE46: 721158 | BF46: 465156 | BG46: 67275 | BH46: 1253589 | BI46: Hồ sơ vật lý và hồ sơ điện tử | BJ46: Minh - Long | BK46: 532950 | BL46: An Hoà | BM46: Phường Hương An | BN46: X | BQ46: X | BR46: X | BS46: Bưu điện TT Thuận Hóa - Phú Xuân
A47: 45 | B47: 5310 | C47: Bưu điện TT Thuận Hóa - Phú Xuân | D47: Key Account | E47: T001800991 | F47: Key Account | G47: Cục Quản Lý Thị Trường Tỉnh Thừa Thiên Huế. | H47: 126 Nguyễn Văn Linh, An Hoà, Tp. Huế. | I47: 0765240817 | K47: T001800991 | L47: 3301037993 | M47: 150/2021/HĐBC/BĐTPH-CUC QLTT | N47: 44270 | O47: Không xác định | P47: Không có | Q47: Thanh toán khi nhận tiền cod | T47: Đang hoạt động | U47: HỒ VĂN KỲ | V47: CTN001, ETN001 | X47: bình giữ nhiệt, đồ dùng | Y47: 0.37 | Z47: 0.6 | AA47: 10208.07 | AC47: 532950 | AD47: 532950_trangbtb | AF47: Theo quy định TCT | AG47: Không có yêu cầu khác. | AK47: Đã thanh toán | AN47: 126 Nguyễn Văn Linh, An Hoà, Tp. Huế. | AO47: 14h00-15h00 | AP47: 2-3 lần/tuần | AQ47: 18 | AR47: Xe máy | AT47: 45869 | BD47: X | BE47: 157500 | BF47: 437400 | BG47: 67600 | BH47: 662500 | BI47: Hồ sơ vật lý và hồ sơ điện tử | BJ47: Minh - Long | BK47: 532950 | BL47: An Hoà | BM47: Phường Hương An | BQ47: X | BR47: X | BS47: Bưu điện TT Thuận Hóa - Phú Xuân
A48: 46 | B48: 5310 | C48: Bưu điện TT Thuận Hóa - Phú Xuân | D48: SME | E48: C001911309 | F48: SME | G48: Công Ty CP Vật Tư Nông Nghiệp TT Huế | H48: 22 Tản Đà, Hương Sơ, TP Huế | I48: 023435588330 | J48: Trần Thuyên | K48: C001911309 | L48: 3300101244 | M48: 01/HĐBC/BĐTPH-VTNN | N48: 44197 | O48: Không xác định | P48: Không có | Q48: Thanh toán khi nhận tiền cod | T48: Đang hoạt động | U48: PHẠM THỊ THANH UYÊN | V48: CTN001, ETN001, ETN011 | Y48: 0.46 | Z48: 0.5 | AA48: 9639.27 | AC48: 532950 | AD48: 532950_trangbtb | AF48: Theo quy định TCT | AG48: Không có yêu cầu khác. | AK48: Đã thanh toán | AN48: 22 Tản Đà, Hương Sơ, TP Huế | AO48: 14h00-15h00 | AP48: 2-3 lần/tuần | AQ48: 15 | AR48: Xe máy | AT48: 45869 | BD48: X | BE48: 63600 | BF48: 0 | BG48: 11200 | BH48: 74800 | BI48: Hồ sơ vật lý và hồ sơ điện tử | BJ48: Minh - Long | BK48: 532950 | BL48: An Hoà | BM48: Phường Hương An | BQ48: X | BR48: X | BS48: Bưu điện TT Thuận Hóa - Phú Xuân
A49: 47 | B49: 5310 | C49: Bưu điện TT Thuận Hóa - Phú Xuân | D49: SME | E49: T017135421 | F49: SME | G49: Công Ty TNHH Sản Xuất TM Và DV Duy Trí | H49: Số 9, Đường số 1, Cụm công nghiệp An Hòa, P An Hòa, Q Phú Xuân | I49: 0987543284 | J49: Trương Đình Dũng | K49: T017135421 | L49: 3300415138 | M49: HĐ61.2025_HĐBC_BĐTTTHPX_CTDT | N49: 45741 | O49: Không xác định | P49: Không có | Q49: Thanh toán vào tháng sau | T49: Đang hoạt động | U49: PHẠM THỊ THANH UYÊN | V49: RTN001 | X49: Tài liệu | Y49: 0.24 | Z49: 0.5 | AA49: 7261.93 | AC49: 532950 | AD49: 532950_trangbtb | AF49: Theo quy định TCT | AG49: Không có yêu cầu khác. | AK49: Đã thanh toán | AN49: Số 9, Đường số 1, Cụm công nghiệp An Hòa, P An Hòa, Q Phú Xuân | AO49: 14h00-15h00 | AP49: 2-3 lần/tuần | AQ49: 15 | AR49: Xe máy | AT49: 45869 | BC49: X | BE49: 177514 | BF49: 214880 | BG49: 76050 | BH49: 468444 | BI49: Hồ sơ vật lý và hồ sơ điện tử | BJ49: Minh - Long | BK49: 532950 | BL49: An Hoà | BM49: Phường Hương An | BQ49: X | BR49: x | BS49: Bưu điện TT Thuận Hóa - Phú Xuân
A50: 48 | B50: 5310 | C50: Bưu điện TT Thuận Hóa - Phú Xuân | D50: Shop | E50: C016285328 | F50: Shop | G50: Nguyễn Duy Nam | H50: 19 Mai Khắc Đôn, P. Kim Long TP. Huế Tỉnh Thừa Thiên Huế | I50: 0979852346 | K50: C016285328 | M50: HĐ199.2024_HĐBC_BĐTPH_NDN | N50: 45614 | O50: Không xác định | P50: Không có | Q50: Thanh toán tại Bưu điện | S50: 4002205203633 Agribank Nguyễn Duy Nam | T50: Đang hoạt động | U50: PHẠM THỊ THANH UYÊN | V50: CTN009 | W50: GTG021 | X50: Phụ tùng xe đạp | Y50: 2.43 | Z50: 0.17 | AA50: 4932 | AC50: 532950 | AD50: 532950_trangbtb | AE50: bta liên hệ sdt trên bưu gửi | AF50: Theo quy định TCT | AG50: Không có yêu cầu khác. | AK50: Đã thanh toán | AN50: 19 Mai Khắc Đôn, P. Kim Long TP. Huế Tỉnh Thừa Thiên Huế | AQ50: 5 | AS50: Khách hàng tự mang đến bưu cục | AT50: 45869 | BD50: X | BE50: 473490 | BF50: 405000 | BG50: 174000 | BH50: 1052490 | BI50: Hồ sơ vật lý và hồ sơ điện tử | BJ50: Minh - Long | BK50: 532950 | BL50: An Hoà | BM50: Phường Hương An | BQ50: X | BR50: x | BS50: Bưu điện TT Thuận Hóa - Phú Xuân
A51: 49 | B51: 5310 | C51: Bưu điện TT Thuận Hóa - Phú Xuân | D51: Shop | E51: C017146248 | F51: Shop | G51: Nguyễn Thị Như Lệ | H51: 10/252 lý thái tổ , p an hòa, quận phú xuân, tp huế | I51: 0704563053 | K51: C017146248 | M51: C017146248_HĐ45.2025_HĐBC_BĐTTTHPX_NTNL | N51: 45735 | O51: Không xác định | P51: Không có | Q51: Thanh toán khi nhận tiền cod | R51: Thứ 2.4.6 hàng tuần Chuyển khoản | S51: 5510745334 BIDV Nguyễn Thị Như Lệ | T51: Đang hoạt động | U51: PHẠM THỊ THANH UYÊN | V51: CTN009 | W51: GTG021 | X51: Đồng hồ, hương, cao bôi muỗi | Y51: 0.53 | Z51: 0.23 | AA51: 4860 | AC51: 532950 | AD51: 532950_trangbtb | AF51: Theo quy định TCT | AG51: Không có yêu cầu khác. | AK51: Đã thanh toán | AN51: 10/252 lý thái tổ , p an hòa, quận phú xuân, tp huế | AQ51: 7 | AS51: Khách hàng tự mang đến bưu cục | AT51: 45869 | BC51: X | BE51: 526259 | BF51: 396659 | BG51: 126000 | BH51: 1048918 | BI51: Hồ sơ vật lý và hồ sơ điện tử | BJ51: Minh - Long | BK51: 532950 | BL51: An Hoà | BM51: Phường Hương An | BN51: X | BQ51: X | BR51: X | BS51: Bưu điện TT Thuận Hóa - Phú Xuân
A52: 50 | B52: 5310 | C52: Bưu điện TT Thuận Hóa - Phú Xuân | D52: SME | E52: T001800104 | F52: SME | G52: CÔNG TY CỔ PHẦN HAI RÊ | H52: 170 LÊ DUẨN, TP HUẾ | I52: 0234.3529090 | J52: Nguyễn Thị Tuyết Châu | K52: T001800104 | L52: 3300383743 | M52: 149/2021/HĐBC/BĐTPH-CTYCPHAIRE | N52: 44270 | O52: Không xác định | P52: Không có | Q52: Thanh toán vào tháng sau | T52: Đang hoạt động | U52: HỒ VĂN KỲ | V52: ETN001 | Y52: 0.05 | Z52: 0.23 | AA52: 3816 | AC52: 532950 | AD52: 532950_trangbtb | AE52: BƯU TÁ LH SĐT TRÊN BG | AF52: Theo quy định TCT | AG52: Không có yêu cầu khác. | AK52: Đã thanh toán | AN52: 170 LÊ DUẨN, TP HUẾ | AO52: 14h00-15h00 | AP52: 2-3 lần/tuần | AQ52: 7 | AR52: Xe máy | AT52: 45869 | BD52: X | BE52: 261598 | BF52: 275425 | BG52: 142800 | BH52: 679823 | BI52: Hồ sơ vật lý và hồ sơ điện tử | BJ52: Minh - Long | BK52: 532950 | BL52: An Hoà | BM52: Phường Hương An | BQ52: X | BR52: X | BS52: Bưu điện TT Thuận Hóa - Phú Xuân
A53: 51 | B53: 5310 | C53: Bưu điện TT Thuận Hóa - Phú Xuân | D53: SME | E53: T001800501 | F53: SME | G53: CÔNG TY TNHH XL-SX ĐIỆN CƠ SDC | H53: SỐ 4 ĐƯỜNG SỐ 3 KCN HƯƠNG SƠ HUẾ | I53: 0905232438 | J53: Đồng Quỳnh Trang | K53: T001800501 | L53: 3300322606 | M53: 145/2021/HĐBC/BĐTPH-CTY ĐIỆNCƠ | N53: 44270 | O53: Không xác định | P53: Không có | Q53: Thanh toán vào tháng sau | T53: Đang hoạt động | U53: HỒ VĂN KỲ | V53: ETN001 | Y53: 0.03 | Z53: 0.17 | AA53: 2282.4 | AC53: 532950 | AD53: 532950_trangbtb | AE53: BTA LH SĐT TRÊN BG | AF53: Theo quy định TCT | AG53: Không có yêu cầu khác. | AK53: Đã thanh toán | AN53: SỐ 4 ĐƯỜNG SỐ 3 KCN HƯƠNG SƠ HUẾ | AO53: 14h00-15h00 | AP53: 2-3 lần/tuần | AQ53: 5 | AR53: Xe máy | AT53: 45869 | BD53: X | BE53: 118600 | BF53: 307200 | BG53: 84000 | BH53: 509800 | BI53: Hồ sơ vật lý và hồ sơ điện tử | BJ53: Minh - Long | BK53: 532950 | BL53: An Hoà | BM53: Phường Hương An | BQ53: X | BR53: X | BS53: Bưu điện TT Thuận Hóa - Phú Xuân
A54: 52 | B54: 5310 | C54: Bưu điện TT Thuận Hóa - Phú Xuân | D54: SME | E54: T001399434 | F54: SME | G54: Công Ty Cổ Phần Lục Gia Phát | H54: 674 Lê Duẩn, TP Huế | I54: 0234.3588828 | J54: Phan Thị Lệ | K54: T001399434 | L54: 3301323401 | M54: 101-hdbc-bdtph-lucgiaphat 44Van | N54: 43831 | O54: Không xác định | P54: Không có | Q54: Thanh toán vào tháng sau | T54: Đang hoạt động | U54: PHẠM THỊ THANH UYÊN | V54: ETN001 | Y54: 0.04 | Z54: 0.07 | AA54: 1123.2 | AC54: 532950 | AD54: 532950_trangbtb | AE54: bta lh sdt trên bưu gửi | AF54: Theo quy định TCT | AG54: Không có yêu cầu khác. | AK54: Đã thanh toán | AN54: 674 Lê Duẩn, TP Huế | AO54: 14h00-15h00 | AP54: 2-3 lần/tuần | AQ54: 2 | AR54: Xe máy | AT54: 45869 | BD54: X | BE54: 159200 | BF54: 487400 | BG54: 40600 | BH54: 687200 | BI54: Hồ sơ vật lý và hồ sơ điện tử | BJ54: Minh - Long | BK54: 532950 | BL54: An Hoà | BM54: Phường Hương An | BQ54: X | BR54: X | BS54: Bưu điện TT Thuận Hóa - Phú Xuân
A55: 53 | B55: 5310 | C55: Bưu điện TT Thuận Hóa - Phú Xuân | D55: SME | E55: T001571446 | F55: SME | G55: DƯỢC PHẨM MẠNH TÝ | H55: P. Vĩnh Ninh TP. Huế Tỉnh Thừa Thiên Huế | I55: 0234.3936768 | J55: Nguyễn Ngọc | K55: T001571446 | L55: 3300314838 | M55: 101/HĐBC/BCCP-DPMT | N55: 42885 | O55: Không xác định | Q55: Thanh toán cước KHi chi trả cod | R55: 2lần/tuần tại BC | T55: Đang hoạt động | U55: HỒ VĂN KỲ | V55: ETN001 | X55: Thuốc tây | Y55: 0.24255725 | Z55: 4 | AA55: 98792 | AC55: 532950 | AD55: 532950_trangbtb | AE55: *BƯU TÁ LIÊN HỆ THEO SĐT TRÊN BƯU GỬI" | AF55: Thực hiện theo quy định của TCT | AK55: Đã thanh toán công nợ | AN55: P. Vĩnh Ninh TP. Huế Tỉnh Thừa Thiên Huế | AO55: 15h00-17h00 | AP55: 1 lần/ngày | AQ55: 131 | AR55: xe máy | AT55: 45856 | BD55: X | BE55: 1322245 | BF55: 2792100 | BG55: 587400 | BH55: 4701745 | BI55: Hồ sơ vật lý và hồ sơ điện tử | BJ55: Minh - Long | BK55: 532950 | BL55: An Hoà | BM55: Phường Hương An | BN55: X | BQ55: X | BR55: X | BS55: Bưu điện TT Thuận Hóa - Phú Xuân
A56: 54 | B56: 5310 | C56: Bưu điện TT Thuận Hóa - Phú Xuân | D56: Shop | E56: C008038568 | F56: Shop | G56: CÔNG TY TNHH SẢN XUÁT TMDV ĐĂNG TUÁN | H56: 4 Đường số 4 Cụm công nghiệp An Hoà, Phường An Hoà, TP Huế | I56: 0962578878 | J56: Nguyễn Đăng Huy | K56: C008038568 | L56: 3300511931 | M56: HĐ65.2024_HĐBC_BĐTPH_ĐT | N56: 21/3/2024 | O56: Không xác định | Q56: 1 lần/1 tháng | T56: Đang hoạt động | U56: PHẠM THỊ THANH UYÊN | V56: ETN001 ETN011 ETN031 ETN013 ETN003 CTN001 CTN007 CTN016 RTN001 CTN007 CTN009 | W56: GTG071 | X56: Áo quần | Y56: 18.94414 | Z56: 5.2333333 | AA56: 620381 | AC56: 532950 | AD56: 532950_trangbtb | AE56: KHông cho xem hàng | AF56: Thực hiện theo quy định của TCT | AK56: Đã thanh toán công nợ | AN56: 4 Đường số 4 Cụm công nghiệp An Hoà, Phường Phú Xuân, TP Huế | AO56: 16h00- 17h00 | AP56: 1 lần / ngày | AQ56: 157 | AR56: ô tô | AT56: 45856 | AW56: HẰNG NGÀY | BA56: X | BE56: 17981680 | BF56: 19073395 | BG56: 6480435 | BH56: 43535510 | BI56: Hồ sơ vật lý và hồ sơ điện tử | BJ56: Rà soát để điều chỉnh lại bàn giao trên CMS | BK56: 532950 | BL56: An Hoà | BM56: Phường Hương An | BN56: X | BQ56: X | BR56: X | BS56: Bưu điện TT Thuận Hóa - Phú Xuân
A57: 55 | B57: 5310 | C57: Bưu điện TT Thuận Hóa - Phú Xuân | D57: Shop | E57: C017698626 | F57: Shop | G57: Võ Thị Quỳnh Nhi | H57: 6/17 Trần Quý KHoáng, P. An Hòa TP. Huế Tỉnh Thừa Thiên Huế | I57: 0379758637 | J57: Võ Thị Quỳnh Nhi | K57: C017698626 | M57: HĐ140.2025_HĐBC_BĐTTTHPX_VTQN | N57: 09/6/2025 | O57: 46182 | Q57: Thứ 2, 4, 6 | R57: Chuyển KHoản | S57: 1028658433 VCB CN Huế Võ Thị Quỳnh Nhi | T57: Đang hoạt động | U57: Phan Thị Hoài Phương | V57: CTN009, EQT002 | W57: GTG021 | X57: Áo quần | Y57: 6.56 | Z57: 0.033333333 | AA57: 333.33333 | AC57: 532950 | AD57: 532950_trangbtb | AE57: BƯU TÁ LH SỐ ĐT TRÊN BG ĐỂ PHÁT | AF57: Thực hiện theo quy định của TCT | AK57: Đã thanh toán công nợ | AN57: 6/17 Trần Quý KHoáng, P. Hương An TP. Huế | AO57: 16h00 | AP57: 2-3 lần /tháng | AQ57: 2 | AR57: xe máy | AT57: 45848 | AW57: HẰNG NGÀY | BC57: X | BE57: 9259 | BF57: 18518 | BG57: 0 | BH57: 27777 | BI57: Chưa có thông tin | BJ57: Rà soát để điều chỉnh lại bàn giao trên CMS | BK57: 532950 | BL57: An Hoà | BM57: Phường Hương An | BN57: X | BQ57: X | BR57: X | BS57: Bưu điện TT Thuận Hóa - Phú Xuân
A58: 56 | B58: 5310 | C58: Bưu điện TT Thuận Hóa - Phú Xuân | D58: Shop | E58: C001395931 | F58: Shop | G58: Trần Thị Thu | H58: 208 Lê Duẩn, P. Phú Thuận TP. Huế Tỉnh Thừa Thiên Huế | I58: 0706003295 | J58: Trần Thị Thu | K58: C001395931 | M58: 71-hdbc-bdtph-tranthithu 44Van | N58: 43881 | O58: KHông xác định | Q58: 1 lần/1 tháng | T58: Đang hoạt động | U58: PHẠM THỊ THANH UYÊN | V58: ETN001 ETN011 ETN031 ETN013 ETN003 CTN001 CTN007 CTN016 RTN001 CTN007 CTN009 | W58: GTG021 | X58: Sách | Y58: 2.7347222 | Z58: 1.2 | AA58: 6372 | AC58: 532950 | AD58: 532950_trangbtb | AE58: Cho xem hàng, KHÁCH ĐƯỢC KIỂM TRA HÀNG, NẾU KHÔNG NHẬN THÌ THANH TOÁN PHÍ HỦY ĐƠN HÀNG 30.000 ĐỒNG ( ĐỐI VỚI ĐỊA CHỈ NHẬN NGOÀI TỈNH TT HUẾ); 15.000 ĐỒNG ( ĐỐI VỚI ĐỊA CHỈ NHẬN TRONG TỈNH TT HUẾ). | AF58: Thực hiện theo quy định của TCT | AK58: Đã thanh toán công nợ | AN58: 208 Lê Duẩn, P. Phú Xuân TP. Huế | AO58: 11h00 -16h00 | AP58: 2-3 lần /tuần | AQ58: 42 | AR58: xe máy | AT58: 45853 | AW58: HẰNG NGÀY | BD58: X | BE58: 646025 | BF58: 185000 | BG58: 176000 | BH58: 1007025 | BI58: Hồ sơ vật lý và hồ sơ điện tử | BJ58: Thy - Dũng | BK58: 532950 | BL58: An Hoà | BM58: Phường Hương An | BQ58: X | BR58: X | BS58: Bưu điện TT Thuận Hóa - Phú Xuân
A59: 57 | B59: 5310 | C59: Bưu điện TT Thuận Hóa - Phú Xuân | D59: Key Account | E59: T001800475 | F59: Key Account | G59: Trung Tâm Dịch Vụ Đấu Giá Tài Sản | H59: 17 Nguyễn Văn Linh, P. Hương Sơ TP. Huế Tỉnh Thừa Thiên Huế | J59: Phan Tiến Dũng | K59: T001800475 | L59: 3300366723 | M59: 144/2021/HĐBC/BĐTPH-TTĐGTS | N59: 44270 | O59: KHông xác định | Q59: 01 tháng/lần Tại địa chỉ bên A | T59: Đang hoạt động | U59: HỒ VĂN KỲ | V59: ETN001 | W59: GTG001 | X59: Tài Liệu | Y59: 0.0643125 | Z59: 2.6666667 | AA59: 38070 | AC59: 532950 | AD59: 532950_trangbtb | AE59: BƯU TÁ VUI LÒNG LIÊN HỆ SĐT NGƯỜI NHẬN TRÊN BƯU GỬI ĐỂ PHÁT HÀNG | AF59: Thực hiện theo quy định của TCT | AK59: Đã thanh toán công nợ | AN59: 17 Nguyễn Văn Linh, P. Hương An TP. Huế | AO59: 11h00 -16h00 | AP59: 2-3 lần /tuần | AQ59: 80 | AR59: xe máy | AT59: 45850 | AW59: HẰNG NGÀY | BD59: X | BE59: 926300 | BF59: 359900 | BG59: 390400 | BH59: 1676600 | BI59: Hồ sơ vật lý và hồ sơ điện tử | BJ59: vũ - lan | BK59: 532950 | BL59: An Hoà | BM59: Phường Hương An | BQ59: X | BR59: X | BS59: Bưu điện TT Thuận Hóa - Phú Xuân
A60: 58 | B60: 5310 | C60: Bưu điện TT Thuận Hóa - Phú Xuân | D60: Shop | E60: C006146255 | F60: Shop | G60: Bongo Plastic | H60: 92 Lý Thái Tổ, An Hoà, Thừa Thiên Huế | I60: 0903507408 | J60: Nguyễn Hữu Sy | K60: C006146255 | M60: HĐ034.2023-HĐBC-BĐTPH-BGP | N60: 45017 | O60: Không xác định | Q60: thanh toán cước khi chi trả cod | R60: CK thứ 2,4,6 hằng tuần | S60: 0161000826132_vietcombank _ Nguyen Huu Sy | T60: Đang hoạt động | U60: PHẠM THỊ THANH UYÊN | V60: CTN009 | Y60: 7.8867895 | Z60: 0.63333333 | AA60: 24417.333 | AC60: 532950 | AD60: 532950_trangbtb | AF60: Theo quy định TCT | AG60: Không có yêu cầu khác. | AK60: đã thanh toán | AN60: 92 Lý Thái Tổ, An Hoà, Thừa Thiên Huế | AO60: 17h00-18h00 | AP60: 1 lần/ ngày | AQ60: 11 | AR60: Ô tô | AT60: 45812 | BC60: X | BE60: 40000 | BF60: 0 | BG60: 40000 | BH60: 80000 | BI60: Hồ sơ vật lý và hồ sơ điện tử | BJ60: Rà soát để điều chỉnh lại bàn giao trên CMS | BK60: 532950 | BL60: An Hoà | BM60: Phường Hương An | BN60: X | BQ60: X | BR60: x | BS60: Bưu điện TT Thuận Hóa - Phú Xuân
A61: 59 | B61: 5310 | C61: Bưu điện TT Thuận Hóa - Phú Xuân | D61: Cá Nhân | E61: C018395618 | F61: Cá Nhân | G61: Nguyễn Công Tý | H61: tdp thanh chữ | I61: 0905214893 | K61: C018395618 | M61: HĐ248.2025.HĐBC-BĐKVTH-PX.PX.LKG | N61: 45929 | T61: Đang thực hiện | U61: NGUYỄN ĐỨC LỘC | AC61: 532950 | AD61: 532950_trangbtb | BE61: 195500 | BF61: 147000 | BG61: 0 | BH61: 342500 | BJ61: Minh - Long | BK61: 532950 | BL61: An Hoà | BM61: Phường Hương An | BQ61: X | BR61: R | BS61: Bưu điện TT Thuận Hóa - Phú Xuân
A62: 60 | B62: 5310 | C62: Bưu điện TT Thuận Hóa - Phú Xuân | D62: Cá Nhân | E62: C018228601 | F62: Cá Nhân | G62: Lê Đình Huy | H62: 27 Trần Nguyên Đán | I62: 0905477679 | K62: C018228601 | M62: HĐ242.2025.HĐBC-BĐKVTH-PX.PX.LKG | N62: 45901 | T62: Đang thực hiện | U62: NGUYỄN ĐỨC LỘC | AC62: 532950 | AD62: 532950_trangbtb | BE62: 0 | BF62: 31890 | BG62: 76890 | BH62: 108780 | BJ62: Rà soát để bàn giao trên CMS | BK62: 532950 | BL62: An Hoà | BM62: Phường Hương An | BQ62: X | BR62: R | BS62: Bưu điện TT Thuận Hóa - Phú Xuân
A63: 61 | B63: 5310 | C63: Bưu điện TT Thuận Hóa - Phú Xuân | D63: Tổ Chức | E63: T019378284 | F63: Tổ Chức | G63: Công An Phường Hương An | H63: 07 Nguyễn Văn Linh, phường Hương An, TP Huế | I63: 02343588455 | K63: T019378284 | M63: HĐ 12/2026/ HĐ¬_BC-PHBC/BĐTP- CA PHƯỜNG HƯƠNG AN | N63: 46023 | T63: Đang hoạt động | U63: NGUYỄN ĐỨC LỘC | V63: ETN001 | Y63: 35 | Z63: 9 | AA63: 104400 | AC63: 532950 | AD63: 532950_trangbtb | AE63: 0 | BE63: 0 | BF63: 104400 | BG63: 53691 | BH63: 158091 | BJ63: Rà soát để bàn giao trên CMS | BK63: 532950 | BL63: An Hoà | BM63: Phường Hương An | BQ63: X | BS63: Bưu điện TT Thuận Hóa - Phú Xuân
A64: 62 | B64: 5310 | C64: Bưu điện TT Thuận Hóa - Phú Xuân | D64: Key Account | E64: T017962895 | F64: Key Account | G64: Trung Tâm HCC Phường Hương An | H64: 143 Nguyễn Văn Linh, phường Hương AnTP. Huế | J64: Trần Đạo Quang Vũ | K64: T017962895 | M64: 177/2025/HĐ_BC-PHBC/BĐTT-TTPVHCCPHA | N64: 45839 | O64: Không xác định | P64: Không có | Q64: 01 tháng/lần Trong 03 - 05 ngày làm việc tiếp theo kể từ ngày nhận được hoá đơn GTGT hợp lệ | T64: Đang hoạt động | U64: ĐẶNG TUẤN VŨ | V64: Dịch vụ HCC, luân chuyển hồ sơ HCC, KT1, EMS, Chuyển phát bưu phẩm trong nước và quốc tế | X64: Tài liệu | Y64: 0.28 | Z64: 0.066666667 | AA64: 1883.3333 | AB64: My VNP | AC64: 532950 | AD64: 532950_trangbtb | AF64: Thực hiện theo quy định của TCT | AK64: 61020 | AL64: Đang làm thanh toán | BC64: X | BE64: 0 | BF64: 113200 | BG64: 9600 | BH64: 122800 | BI64: Hồ sơ vật lý và hồ sơ điện tử | BJ64: Minh - Long | BK64: 532950 | BL64: An Hoà | BM64: Phường Hương An | BQ64: X | BR64: X | BS64: Bưu điện TT Thuận Hóa - Phú Xuân
A65: 63 | B65: 5310 | C65: Bưu điện TT Thuận Hóa - Phú Xuân | D65: Key Account | E65: T017962878 | F65: Key Account | G65: UBND Phường Hương An | H65: 143 Nguyễn Văn Linh, phường Hương AnTP. Huế | J65: Nguyễn Đình Tuấn | K65: T017962878 | M65: 195/2025/HĐ_BC-PHBC/BĐTT-VPUBHA | N65: 45839 | O65: Không xác định | P65: Không có | Q65: 01 tháng/lần Trong 03 - 05 ngày làm việc tiếp theo kể từ ngày nhận được hoá đơn GTGT hợp lệ | T65: Đang hoạt động | U65: ĐẶNG TUẤN VŨ | V65: Dịch vụ HCC, luân chuyển hồ sơ HCC, KT1, EMS, Chuyển phát bưu phẩm trong nước và quốc tế | X65: Tài liệu | Y65: 0.038125 | Z65: 0.26666667 | AA65: 3616.3333 | AB65: My VNP | AC65: 532950 | AD65: 532950_trangbtb | AF65: Thực hiện theo quy định của TCT | AK65: 117170 | AL65: Đang làm thanh toán | BC65: X | BE65: 339245 | BF65: 81200 | BG65: 100800 | BH65: 521245 | BI65: Hồ sơ vật lý và hồ sơ điện tử | BJ65: Minh - Long | BK65: 532950 | BL65: An Hoà | BM65: Phường Hương An | BQ65: X | BR65: X | BS65: Bưu điện TT Thuận Hóa - Phú Xuân
A66: 64 | B66: 5310 | C66: Bưu điện TT Thuận Hóa - Phú Xuân | D66: Shop | E66: C005951881 | F66: Shop | G66: Hạnh Trần | H66: Hương Hồ, TP Huế | I66: 0945222286 | J66: Nguyễn Thị Hồng Liên | K66: C005951881 | M66: HĐ10.2023-HĐBC-BĐTPH-STHT | N66: 44973 | O66: Không xác định | Q66: Thanh toán cước KHi chi trả cod | R66: CK qua ngân hàng, 1 TuẦn/lần | S66: 0945222286_Sacombank | T66: Đang hoạt động | U66: PHẠM THỊ THANH UYÊN | V66: CTN009 | W66: GTG021 | X66: Á o Quần | Y66: 2.3 | Z66: 0 | AA66: 53345 | AC66: 535530 | AD66: 535530_loanptk | AF66: Thực hiện theo quy định của TCT | AK66: Đã thanh toán công nợ | AN66: Hương Hồ, TP Huế | AO66: 14h00-16h00 | AP66: 1 lần/ngày | AQ66: 100 | AR66: xe máy | AT66: 45856 | BC66: X | BE66: 3517260 | BF66: 1808940 | BG66: 38000 | BH66: 5364200 | BI66: Hồ sơ vật lý và hồ sơ điện tử | BJ66: Rà soát để điều chỉnh lại bàn giao trên CMS | BK66: 535530 | BL66: Hương An | BM66: Phường Hương An | BN66: X | BQ66: X | BR66: X | BS66: Bưu điện TT Thuận Hóa - Phú Xuân
A67: 65 | B67: 5310 | C67: Bưu điện TT Thuận Hóa - Phú Xuân | D67: Shop | E67: C017277901 | F67: Shop | G67: Nguyễn Ngoc | H67: 15 Cao Văn Khánh, Hương An, P. Hương An TX. Hương Trà Tỉnh Thừa Thiên Huế | I67: 0784433533 | K67: C017277901 | M67: HĐ78-2025-HĐBC-BĐTTHPX-NN | N67: 45755 | O67: Không xác định | P67: Không có | Q67: Trong 03 - 05 ngày làm việc tiếp theo kể từ ngày nhận được hoá đơn GTGT hợp lệ | T67: Đang hoạt động | U67: PHẠM THỊ THANH UYÊN | V67: CTN007 | W67: GTG021 | X67: Bình sữa, bỉm, sữa chua, xe đồ chơi, vitamin | Y67: 1.19 | Z67: 0.47 | AA67: 4666.67 | AC67: 535530 | AD67: 535530_loanptk | AF67: Theo quy định TCT | AG67: Không có yêu cầu khác. | AK67: Đã thanh toán | AN67: 15 Cao Văn Khánh, Hương An, P. Hương An TX. Hương Trà Tỉnh Thừa Thiên Huế | AO67: 14h00-15h00 | AP67: 1-2 lần / tuần | AQ67: 14 | AR67: Xe máy | AT67: 45869 | BC67: X | BE67: 46777 | BF67: 75036 | BG67: 0 | BH67: 121813 | BI67: Chưa có thông tin | BJ67: Rà soát để điều chỉnh lại bàn giao trên CMS | BK67: 535530 | BL67: Hương An | BM67: Phường Hương An | BN67: X | BQ67: X | BR67: X | BS67: Bưu điện TT Thuận Hóa - Phú Xuân
A68: 66 | B68: 5310 | C68: Bưu điện TT Thuận Hóa - Phú Xuân | D68: Shop | E68: C016182592 | F68: Shop | G68: Diệu Trần | H68: 105 Long Hồ _ Hương Hồ _ Hương Trà_ TP Huế | I68: 0375434638 | J68: Trần Thị Mỹ Diệu | K68: C016182592 | M68: 40.2025/HĐBC/BĐTPH-TTMD | N68: 45729 | O68: Không xác định | P68: Không có | Q68: Trong 03 - 05 ngày làm việc tiếp theo kể từ ngày nhận được hoá đơn GTGT hợp lệ | R68: Thứ 2,4,6 hàng tuần Tiền mặt Chuyển khoản | S68: 5511195738 BIDV Trần Thị Mỹ Diệu | T68: Đang hoạt động | U68: PHẠM THỊ THANH UYÊN | V68: CTN009 | W68: GTG021 | X68: Body | Y68: 0.6 | Z68: 0.03 | AA68: 684 | AC68: 535530 | AD68: 535530_loanptk | AE68: Không cho xem hàng | AF68: Theo quy định TCT | AG68: Không có yêu cầu khác. | AK68: Đã thanh toán | AN68: 105 Long Hồ _ Hương Hồ _ Hương Trà_ TP Huế | AO68: 14h00-16h00 | AP68: 1-2 lần / tuần | AQ68: 1 | AR68: Xe máy | AT68: 45842 | BC68: X | BE68: 212725 | BF68: 0 | BG68: 0 | BH68: 212725 | BI68: Hồ sơ vật lý và hồ sơ điện tử | BJ68: Rà soát để điều chỉnh lại bàn giao trên CMS | BK68: 535530 | BL68: Hương An | BM68: Phường Hương An | BQ68: X | BR68: X | BS68: Bưu điện TT Thuận Hóa - Phú Xuân
A69: 67 | B69: 5310 | C69: Bưu điện TT Thuận Hóa - Phú Xuân | D69: Shop | E69: C005134242 | F69: Shop | G69: Shop Phan Mai | H69: Long Hồ Hạ 2, Hương Hồ, TP Huế | I69: 0354573660 | J69: Phan Thị Mai | K69: C005134242 | M69: C005134242_HĐ109.2022-HĐBC-BĐTPH-SPM | N69: 01/8/2022 | O69: Không xác định | Q69: Thanh toán cước KHi chi trả cod | R69: Chuyển KHoản qua ngân hàng | S69: 0161001720126 | T69: Đang hoạt động | U69: PHẠM THỊ THANH UYÊN | V69: CTN009 | W69: GTG021 | X69: Cơ KHí | Y69: 4.8328723 | Z69: 2 | AA69: 58233 | AC69: 535550 | AD69: 535550_huyennct | AE69: Cho Xem Hàng..Bưu Tá Phát Theo Số Điện Thoại Trên Bưu Gửi | AF69: Thực hiện theo quy định của TCT | AK69: Đã thanh toán công nợ | AN69: Long Hồ Hạ 2, Hương Hồ, TP Huế | AO69: 14h00-16h00 | AP69: 1 lần/ngày | AQ69: 47 | AR69: xe máy | AT69: 45856 | BC69: X | BE69: 6110000 | BF69: 2934400 | BG69: 283000 | BH69: 9327400 | BI69: Hồ sơ vật lý và hồ sơ điện tử | BJ69: Minh - Long | BK69: 535550 | BL69: Hương Hồ | BM69: Phường Kim Long | BQ69: X | BR69: X | BS69: Bưu điện TT Thuận Hóa - Phú Xuân
A70: 68 | B70: 5310 | C70: Bưu điện TT Thuận Hóa - Phú Xuân | D70: Shop | E70: C002469485 | F70: Shop | G70: SƯ MINH GIẢI | H70: CHÙA HUYỀN KHÔNG PHƯỜNG HƯƠNG HỒ TP HUẾ | I70: 0967140053 | K70: C002469485 | M70: HĐ483.2021-HĐBC-BĐTPH-SMG | N70: 44461 | O70: Không xác định | P70: Không có | Q70: Ngay khi sử dụng dịch vụ Thanh toán tại địa chỉ bên A | R70: 01 tuần/lần Thanh toán tại địa chỉ bên A | T70: Đang hoạt động | U70: HỒ VĂN KỲ | V70: CTN001, ETN001, CTN007 | W70: GTG021 | X70: Bánh kẹo, sách | Y70: 3.62 | Z70: 0.07 | AA70: 3082.43 | AC70: 535550 | AD70: 535550_huyennct | AE70: BƯU TÁ PHÁT THEO SỐ ĐIỆN THOẠI TRÊN BƯU GỬI | AF70: Theo quy định TCT | AG70: Không có yêu cầu khác. | AK70: Đã thanh toán | AN70: CHÙA HUYỀN KHÔNG PHƯỜNG HƯƠNG HỒ TP HUẾ | AQ70: 4 | AS70: Khách hàng tự mang đến bưu cục | AT70: 45869 | BD70: X | BE70: 117283 | BF70: 48635 | BG70: 0 | BH70: 165918 | BI70: Hồ sơ vật lý và hồ sơ điện tử | BJ70: Minh - Long | BK70: 535550 | BL70: Hương Hồ | BM70: Phường Kim Long | BQ70: X | BR70: X | BS70: Bưu điện TT Thuận Hóa - Phú Xuân
A71: 69 | B71: 5310 | C71: Bưu điện TT Thuận Hóa - Phú Xuân | D71: SME | E71: T001460533 | F71: SME | G71: Công ty CP giống cây trồng vật nuôi | H71: 128 Nguyễn Phúc Nguyên, TP Huế | I71: 01635704977 | J71: Thanh | K71: T001460533 | M71: 161/2021/HĐBC/BĐTP-CTYCPGCTVN | N71: 15/03/2021 | O71: Không xác định | Q71: Thanh toán vào giữa tháng sau | U71: PHẠM THỊ THANH UYÊN | V71: ETN001, CTN001 | X71: Tài liệu | Y71: 0.2 | Z71: 1.33 | AA71: 24046 | AC71: 532760 | AD71: 532760_duongvt | AE71: *BƯU TÁ LIÊN HỆ THEO SĐT TRÊN BƯU GỬI" | AF71: Theo quy định của TCT | AK71: 721.394 | AL71: đang làm thanh toán | AN71: 128 Nguyễn Phúc Nguyên, TP Huế | AO71: 13h30-14h30 | AP71: 1 lân / ngày | AQ71: 40 | AR71: Xe máy | AT71: 45862 | BD71: X | BE71: 2351729 | BF71: 790300 | BG71: 158700 | BH71: 3300729 | BI71: Hồ sơ vật lý và hồ sơ điện tử | BJ71: Phát - Long | BK71: 532760 | BL71: Kim Long | BM71: Phường Kim Long | BQ71: X | BR71: X | BS71: Bưu điện TT Thuận Hóa - Phú Xuân
A72: 70 | B72: 5310 | C72: Bưu điện TT Thuận Hóa - Phú Xuân | D72: Shop | E72: C017458373 | F72: Shop | G72: Minh Nguyệt | H72: 204 Lý Nam Đế, P. Hương Long TP. Huế Tỉnh Thừa Thiên Huế | I72: 0779337121 | J72: Lê Thị Nguyệt | K72: C017458373 | M72: HĐ108-2025-HĐBC-BĐTTTHPX-MN | N72: 45784 | O72: Không xác định | Q72: Thanh toán cước khi nhận tiền COD | R72: Chuyển khoản, theo yêu cầu KH | S72: 4000205198545 Agribank | T72: Đang hoạt động | U72: PHẠM THỊ THANH UYÊN | V72: ETN001 | W72: GTG021 | X72: Dụng cụ xây dựng, vụn sành sư, bi thủy tinh, mắt thuyền, râu rồng | Y72: 5.42 | Z72: 0.5 | AA72: 22496 | AC72: 532760 | AD72: 532760_duongvt | AE72: *BƯU TÁ LIÊN HỆ THEO SĐT TRÊN BƯU GỬI" | AF72: Theo quy định của TCT | AK72: 674.868 | AL72: đang thanh toán | AN72: 204 Lý Nam Đế, P. Hương Long TP. Huế Tỉnh Thừa Thiên Huế | AQ72: 15 | AS72: Khách hàng tự mang đến BC | AT72: 45861 | AW72: Khi phát sinh yêu cầu | BD72: X | BE72: 67200 | BF72: 51000 | BG72: 0 | BH72: 118200 | BI72: Hồ sơ vật lý và hồ sơ điện tử | BJ72: Rà soát để điều chỉnh lại bàn giao trên CMS | BK72: 532760 | BL72: Kim Long | BM72: Phường Kim Long | BQ72: X | BR72: X | BS72: Bưu điện TT Thuận Hóa - Phú Xuân
A73: 71 | B73: 5310 | C73: Bưu điện TT Thuận Hóa - Phú Xuân | D73: Shop | E73: C004228093 | F73: Shop | G73: Nguyễn Thị Cẩm Tú | H73: 3/15 Nguyễn Hữu Dật, Kim Long | I73: 0971383073 | J73: Nguyễn Thị Cẩm Tú | K73: C004228093 | M73: HĐ5182021-HĐBC-BĐTPH-NTCT | N73: 01/11/2021 | O73: Không xác định | Q73: Thanh toán cước KHi chi trả cod | R73: CK qua ngân hàng, 1 TuẦn/lần | S73: 0161000882115_Việtcombank | T73: Đang hoạt động | U73: HỒ VĂN KỲ | V73: CTN009 | X73: Áo | Y73: 0.38818182 | Z73: 3 | AA73: 48805 | AC73: 532760 | AD73: 532760_duongvt | AE73: Yêu Cầu Liên Hệ Người Gửi KHi KHông Phát Được Hàng. KHông Được Tự Ý Chuyển Hoàn KHi KHông Liên Hệ Lại Người Gửi .Cám Ơn | AF73: Thực hiện theo quy định của TCT | AK73: Đã thanh toán công nợ | AN73: 3/15 Nguyễn Hữu Dật, Kim Long | AO73: 10h; 14h | AP73: 1 lần/ngày | AQ73: 77 | AR73: xe máy | AT73: 45854 | BC73: X | BE73: 2669000 | BF73: 3184000 | BG73: 844000 | BH73: 6697000 | BI73: Hồ sơ vật lý và hồ sơ điện tử | BJ73: Minh - Long | BK73: 532760 | BL73: Kim Long | BM73: Phường Kim Long | BN73: X | BQ73: X | BR73: X | BS73: Bưu điện TT Thuận Hóa - Phú Xuân
A74: 72 | B74: 5310 | C74: Bưu điện TT Thuận Hóa - Phú Xuân | D74: Shop | E74: C001395313 | F74: Shop | G74: Phạm Thị Hồng Phương | H74: 1 Bửu Đình, Phường Kim Long, TP Huế | I74: 0915551419 | J74: Phạm Thị Hồng Phương | K74: C001395313 | M74: HĐ078.2022-HĐBC-BĐTPH-PTHP | N74: 44701 | O74: Không xác định | Q74: Thanh toán khi nhận tiền cod | R74: CK Thứ 3,6 hằng tuần | S74: 0161000884912 Vietcombank CN Huế | T74: Đang hoạt động | U74: PHẠM THỊ THANH UYÊN | V74: CTN007 | W74: GTG021 | X74: Áo quần | Y74: 0.99887097 | Z74: 1.0333333 | AA74: 10333.333 | AC74: 532760 | AD74: 532760_duongvt | AF74: Theo quy định TCT | AG74: Không có yêu cầu khác. | AK74: đã thanh toán | AN74: 1 Bửu Đình, Phường Kim Long, TP Huế | AO74: 13h30- 14h30 | AP74: 2-3 lần/ tuần | AQ74: 14 | AR74: Xe máy | AT74: 45812 | BC74: X | BE74: 223698 | BF74: 120367 | BG74: 0 | BH74: 344065 | BI74: Hồ sơ vật lý và hồ sơ điện tử | BJ74: Phát - Long | BK74: 532760 | BL74: Kim Long | BM74: Phường Kim Long | BN74: X | BQ74: X | BR74: X | BS74: Bưu điện TT Thuận Hóa - Phú Xuân
A75: 73 | B75: 5310 | C75: Bưu điện TT Thuận Hóa - Phú Xuân | D75: Shop | E75: C004290691 | F75: Shop | G75: Ngọa Tùng Am | H75: chùa huyền không sơn thượng, P Hương Hồ, Hương Trà, Huế | I75: 0899228727 | J75: Nguyễn Tấn Phẩm | K75: C004290691 | M75: HĐ007.2022-HĐBC-BĐTPH-NTA | N75: 44581 | O75: Không xác định | P75: Không có | Q75: Trong 03 - 05 ngày làm việc tiếp theo kể từ ngày nhận được hoá đơn GTGT hợp lệ | R75: 01 tháng/lần Tiền mặt/Chuyển khoản | S75: 19135719310013 Techcmbank Nguyễn Tấn Phẩm | T75: Đang hoạt động | U75: HỒ VĂN KỲ | V75: ETN013, CTN001 | X75: Hồ sơ, sách | Y75: 8.37 | Z75: 0.07 | AA75: 8365.9 | AC75: 532760 | AD75: 532760_duongvt | AF75: Theo quy định TCT | AG75: Không có yêu cầu khác. | AK75: đã thanh toán | AN75: chùa huyền không sơn thượng, P Hương Hồ, Hương Trà, Huế | AQ75: 2 | AS75: Khách hàng tự mang đến bưu cục | AT75: 45869 | BD75: X | BE75: 391235 | BF75: 118170 | BG75: 0 | BH75: 509405 | BI75: Hồ sơ vật lý và hồ sơ điện tử | BJ75: Phát - Long | BK75: 532760 | BL75: Kim Long | BM75: Phường Kim Long | BQ75: X | BR75: X | BS75: Bưu điện TT Thuận Hóa - Phú Xuân
A76: 74 | B76: 5310 | C76: Bưu điện TT Thuận Hóa - Phú Xuân | D76: SME | E76: T001800841 | F76: SME | G76: Công ty TNHH Phương Ty | H76: Đường Sư Vạn Hạnh, Kim Long, TP Huế | I76: 0905337733 | J76: Hạnh | K76: T001800841 | L76: 3300345240 | M76: 158/2021/HĐBC/BĐTP-CTYPTY | N76: 44270 | O76: Không xác định | P76: Không có | Q76: 01 tháng/lần Thanh toán tại địa chỉ bên A | U76: HỒ VĂN KỲ | V76: ETN001 | Y76: 0.06 | Z76: 0.63 | AA76: 9928.8 | AC76: 532760 | AD76: 532760_duongvt | AE76: *BƯU TÁ LIÊN HỆ THEO SĐT TRÊN BƯU GỬI" | AF76: Theo quy định TCT | AG76: Không có yêu cầu khác. | AK76: đã thanh toán | AN76: Đường Sư Vạn Hạnh, Kim Long, TP Huế | AQ76: 19 | AS76: Khách hàng tự mang đến bưu cục | AT76: 45869 | BD76: X | BE76: 276200 | BF76: 126000 | BG76: 50400 | BH76: 452600 | BI76: Hồ sơ vật lý và hồ sơ điện tử | BJ76: Phát - Long | BK76: 532760 | BL76: Kim Long | BM76: Phường Kim Long | BQ76: X | BR76: X | BS76: Bưu điện TT Thuận Hóa - Phú Xuân
A77: 75 | B77: 5310 | C77: Bưu điện TT Thuận Hóa - Phú Xuân | D77: Shop | E77: C001396248 | F77: Shop | G77: Khánh Hòa | H77: Nhà số 160 Hải Triều, phường An Đông, TP Huế, P. An Đông TP. Huế Tỉnh Thừa Thiên Huế | I77: 399176321 | J77: Khánh Hòa | K77: C001396248 | M77: 202/HĐBC/BĐTP/SHOPBONGBONG | N77: 44166 | O77: Không xác định | P77: Không có | Q77: 01 tháng/lần Chuyển khoản | R77: 01 tuần/lần Chuyển khoản | S77: 0161000770953 VCB Lê Thị Lành | T77: Đang hoạt động | U77: PHẠM THỊ THANH UYÊN | V77: CTN007, CTN009 | W77: GTG021 | X77: Ga, thảm, chiếu | Y77: 1.96 | Z77: 0.4 | AA77: 6368.27 | AC77: 532760 | AD77: 532760_duongvt | AF77: Theo quy định TCT | AG77: Không có yêu cầu khác. | AK77: đã thanh toán | AN77: 199 Phan Đình Phùng, Huế | AQ77: 12 | AS77: Khách hàng tự mang đến bưu cục | AT77: 45869 | BC77: X | BE77: 147290 | BF77: 63600 | BG77: 0 | BH77: 210890 | BI77: Hồ sơ vật lý và hồ sơ điện tử | BJ77: Phát - Long | BK77: 532760 | BL77: Kim Long | BM77: Phường Kim Long | BN77: X | BQ77: X | BR77: x | BS77: Bưu điện TT Thuận Hóa - Phú Xuân
A78: 76 | B78: 5310 | C78: Bưu điện TT Thuận Hóa - Phú Xuân | D78: Tổ Chức | E78: T001571619 | F78: Tổ Chức | G78: CN KHAI THÁC ĐƯỜNG SẮT TTHUẾ | H78: 01 Bùi Thị Xuân, Phường Vĩnh Ninh, TP Huế | I78: 0905302357 | K78: T001571619 | M78: 154/2021/HĐBC/BĐTP-CNKTĐS | N78: 44270 | T78: Đang hoạt động | U78: HỒ VĂN KỲ | V78: 0 | X78: TL;1;0;0 | AC78: 532760 | AD78: 532760_duongvt | BE78: 2362900 | BF78: 2300900 | BG78: 587300 | BH78: 5251100 | BI78: Hồ sơ vật lý và hồ sơ điện tử | BJ78: Minh - Long | BK78: 532760 | BL78: Kim Long | BM78: Phường Kim Long | BQ78: X | BR78: R | BS78: Bưu điện TT Thuận Hóa - Phú Xuân
A79: 77 | B79: 5310 | C79: Bưu điện TT Thuận Hóa - Phú Xuân | D79: Cá Nhân | E79: C017328237 | F79: Cá Nhân | G79: Trần Thị Uyên Như | H79: 4/314 Lý Nam Đế | I79: 0356009208 | K79: C017328237 | M79: HĐ88.2025_HĐBC_BĐTTTHPX_TTUN | N79: 45762 | T79: Đang hoạt động | U79: PHẠM THỊ THANH UYÊN | AC79: 532760 | AD79: 532760_duongvt | BE79: 0 | BF79: 553000 | BG79: 73000 | BH79: 626000 | BI79: Hồ sơ vật lý và hồ sơ điện tử | BJ79: Rà soát để điều chỉnh lại bàn giao trên CMS | BK79: 532760 | BL79: Kim Long | BM79: Phường Kim Long | BQ79: X | BR79: R | BS79: Bưu điện TT Thuận Hóa - Phú Xuân
A80: 78 | B80: 5310 | C80: Bưu điện TT Thuận Hóa - Phú Xuân | D80: Cá Nhân | E80: C005720049 | F80: Cá Nhân | G80: Nhung Thuỳ | H80: kiệt 2/240 Lý Nam Đế phường Hương Long | I80: 0961502169 | K80: C005720049 | M80: C005720049_HĐ63.2024_HĐBC_BĐTPH_NT | N80: 45371 | T80: Đang hoạt động | U80: PHẠM THỊ THANH UYÊN | V80: CG347369573VN | X80: quần áo^1^0^0 | AC80: 532760 | AD80: 532760_duongvt | BE80: 60581 | BF80: 103608 | BG80: 0 | BH80: 164189 | BI80: Hồ sơ vật lý và hồ sơ điện tử | BJ80: Minh - Long | BK80: 532760 | BL80: Kim Long | BM80: Phường Kim Long | BN80: X | BQ80: X | BR80: R | BS80: Bưu điện TT Thuận Hóa - Phú Xuân
A81: 79 | B81: 5310 | C81: Bưu điện TT Thuận Hóa - Phú Xuân | D81: Tổ Chức | E81: T018405045 | F81: Tổ Chức | G81: Phòng Kinh Tế, Hạ Tầng Và Đô Thị Phường Kim Long | H81: 69 Nguyễn Hoàng, Phường Kim Long, TP Huế | I81: 0979237555 | K81: T018405045 | M81: 238-2025 HĐBC BĐKVTTTHPX-PKTHT&ĐTPKL | N81: 45909 | T81: Đang thực hiện | U81: DƯƠNG THỊ HÒE | AC81: 532760 | AD81: 532760_duongvt | BE81: 0 | BF81: 19200 | BG81: 0 | BH81: 19200 | BJ81: Rà soát để bàn giao trên CMS | BK81: 532760 | BL81: Kim Long | BM81: Phường Kim Long | BQ81: X | BR81: R | BS81: Bưu điện TT Thuận Hóa - Phú Xuân
A82: 80 | B82: 5310 | C82: Bưu điện TT Thuận Hóa - Phú Xuân | D82: Tổ Chức | E82: T018159985 | F82: Tổ Chức | G82: Hội Chữ Thập Đỏ Thành Phố Huế | H82: 119 Vạn Xuân, | I82: 0982448133 | K82: T018159985 | U82: HOÀNG VĂN DUY | AC82: 532760 | AD82: 532760_duongvt | BE82: 1248574 | BF82: 2060124 | BG82: 94500 | BH82: 3403198 | BI82: Hồ sơ vật lý và hồ sơ điện tử | BJ82: Phát - Long | BK82: 532760 | BL82: Kim Long | BM82: Phường Kim Long | BQ82: X | BR82: R | BS82: Bưu điện TT Thuận Hóa - Phú Xuân
A83: 81 | B83: 5310 | C83: Bưu điện TT Thuận Hóa - Phú Xuân | D83: Key Account | E83: T017962802 | F83: Key Account | G83: Trung Tâm HCC Phường Kim Long | H83: 87 Phạm Thị Liên, phường Kim Long, TP. Huế | J83: Lê Văn Thìn | K83: T017962802 | M83: 178/2025/HĐ_BC-PHBC/BĐTT-TTPVHCCPKL | N83: 45839 | O83: Không xác định | P83: Không có | Q83: 01 tháng/lần Trong 03 - 05 ngày làm việc tiếp theo kể từ ngày nhận được hoá đơn GTGT hợp lệ | T83: Đang hoạt động | U83: ĐẶNG TUẤN VŨ | V83: Dịch vụ HCC, luân chuyển hồ sơ HCC, KT1, EMS, Chuyển phát bưu phẩm trong nước và quốc tế | X83: Tài liệu | Y83: 0.052 | Z83: 0.16666667 | AA83: 5000 | AB83: My VNP | AC83: 532760 | AD83: 532760_duongvt | AF83: Thực hiện theo quy định của TCT | AK83: 162000 | AL83: Đang làm thanh toán | BC83: X | BE83: 160455 | BF83: 442175 | BG83: 0 | BH83: 602630 | BI83: Hồ sơ vật lý và hồ sơ điện tử | BJ83: Phát - Long | BK83: 532760 | BL83: Kim Long | BM83: Phường Kim Long | BQ83: X | BR83: X | BS83: Bưu điện TT Thuận Hóa - Phú Xuân
A84: 82 | B84: 5310 | C84: Bưu điện TT Thuận Hóa - Phú Xuân | D84: SME | E84: T001799595 | F84: SME | G84: Công ty Yakult | H84: 61 đường số 5 an cựu city Tp Huế | I84: 0234 3861 542 | J84: Nguyễn Trần Công Phi | K84: T001799595 | L84: 3700723994-014 | M84: HĐ376-HĐBC-BĐTPH-CTYK | N84: 44169 | O84: Không xác định | P84: Không có | Q84: Thanh toán vào tháng sau | T84: Đang hoạt động | U84: HỒ VĂN KỲ | V84: ETN001, ETN013 | X84: Hồ sơ | Y84: 0.4 | Z84: 0.27 | AA84: 14536.8 | AC84: 536801 | AD84: 536801_tienttt | AF84: Theo quy định TCT | AG84: Không có yêu cầu khác. | AK84: Đã thanh toán | AN84: 61 đường số 5 an cựu city Tp Huế | AO84: 08h00-10h00; 14h00-16h00 | AP84: 1-2 lần/tuần | AQ84: 8 | AR84: Xe máy | AT84: 45869 | BD84: X | BE84: 211800 | BF84: 271200 | BG84: 132000 | BH84: 615000 | BI84: Hồ sơ vật lý và hồ sơ điện tử | BJ84: Bảo + Ni | BK84: 536801 | BL84: Phú Thượng | BM84: Phường Mỹ Thượng | BQ84: X | BR84: X | BS84: Bưu điện TT Thuận Hóa - Phú Xuân
A85: 83 | B85: 5310 | C85: Bưu điện TT Thuận Hóa - Phú Xuân | D85: SME | E85: T001799882 | F85: SME | G85: Công Ty Cổ Phần ICO Chi Nhánh Huế | H85: 42 Nguyễn Khánh Toàn, TP Huế | I85: ‭0905378177‬ | J85: Phạm Văn Diệu | K85: T001799882 | L85: 2400399209-016 | M85: 373/HĐBC/BĐTPH-CTCPYTICO | N85: 44169 | O85: Không xác định | P85: Không có | Q85: Thanh toán vào tháng sau | T85: Đang hoạt động | U85: HỒ VĂN KỲ | V85: ETN001 | W85: GTG071 | X85: Hồ sơ | Y85: 0.15 | Z85: 0.5 | AA85: 13127.23 | AC85: 536801 | AD85: 536801_tienttt | AF85: Theo quy định TCT | AG85: Không có yêu cầu khác. | AK85: Đã thanh toán | AN85: 42 Nguyễn Khánh Toàn, TP Huế | AO85: 08h00-10h00; 14h00-16h00 | AP85: 1-2 lần/tuần | AQ85: 15 | AR85: Xe máy | AT85: 45869 | BD85: X | BE85: 1715400 | BF85: 966000 | BG85: 489000 | BH85: 3170400 | BI85: Hồ sơ vật lý và hồ sơ điện tử | BJ85: Bảo + Ni | BK85: 536801 | BL85: Phú Thượng | BM85: Phường Mỹ Thượng | BQ85: X | BR85: x | BS85: Bưu điện TT Thuận Hóa - Phú Xuân
A86: 84 | B86: 5310 | C86: Bưu điện TT Thuận Hóa - Phú Xuân | D86: SME | E86: T001800798 | F86: SME | G86: Du Lịch Đại Bàng | H86: 115 Phạm Văn Đồng, phường Vỹ Dạ, Huế | I86: 0234.3936787 | J86: Lê Thị Hồng Tuyết | K86: T001800798 | L86: 3301494534 | M86: 269/2021/HĐBC/BĐTPH-DLDAIBANG | N86: 44272 | O86: Không xác định | P86: Không có | Q86: Thanh toán vào tháng sau | T86: Đang hoạt động | U86: HỒ VĂN KỲ | V86: ETN001 | X86: Hồ sơ | Y86: 0.05 | Z86: 0.17 | AA86: 2289.6 | AC86: 536801 | AD86: 536801_tienttt | AF86: Theo quy định TCT | AG86: Không có yêu cầu khác. | AK86: Đã thanh toán | AN86: 115 Phạm Văn Đồng, phường Vỹ Dạ, Huế | AO86: 08h00-10h00; 14h00-16h00 | AP86: 1-2 lần/tuần | AQ86: 5 | AR86: Xe máy | AT86: 45869 | BD86: X | BE86: 200145 | BF86: 11400 | BG86: 147745 | BH86: 359290 | BI86: Hồ sơ vật lý và hồ sơ điện tử | BJ86: Bảo + Ni | BK86: 536801 | BL86: Phú Thượng | BM86: Phường Mỹ Thượng | BQ86: X | BR86: X | BS86: Bưu điện TT Thuận Hóa - Phú Xuân
A87: 85 | B87: 5310 | C87: Bưu điện TT Thuận Hóa - Phú Xuân | D87: SME | E87: C003707155 | F87: SME | G87: CÔNG TY TNHH HÙNG GIA TRANG | H87: D37 Green,TL10-Phú Mỹ, Phú Vang,T T Huế | I87: 0985323235 | J87: Huỳnh Thị Tuệ Trang | K87: C003707155 | L87: 3301336506 | M87: HĐ466.2021-HĐBC-BĐTPH-HTTT | N87: 44455 | O87: Không xác định | P87: Không có | Q87: 02 tuần/lần Thanh toán tại điểm giao dịch bên B | R87: 01 tuần/lần Chuyển khoản | S87: 109813346789 Vietinbank Huỳnh Thị Tuệ Trang | U87: HỒ VĂN KỲ | V87: ETN001 | W87: GTG047 | X87: Hồ sơ | Y87: 0.27 | Z87: 0.67 | AA87: 10238.4 | AC87: 536801 | AD87: 536801_tienttt | AF87: Theo quy định TCT | AG87: Không có yêu cầu khác. | AK87: Đã thanh toán | AN87: D37 Green,TL10-Phú Mỹ, Phú Vang,T T Huế | AO87: 08h00-10h00; 14h00-16h00 | AP87: 1-2 lần/tuần | AQ87: 20 | AR87: Xe máy | AT87: 45869 | BD87: X | BE87: 168600 | BF87: 216010 | BG87: 17500 | BH87: 402110 | BI87: Hồ sơ vật lý và hồ sơ điện tử | BJ87: Rà soát để điều chỉnh lại bàn giao trên CMS | BK87: 536801 | BL87: Phú Thượng | BM87: Phường Mỹ Thượng | BQ87: X | BR87: X | BS87: Bưu điện TT Thuận Hóa - Phú Xuân
A88: 86 | B88: 5310 | C88: Bưu điện TT Thuận Hóa - Phú Xuân | D88: Shop | E88: C005677266 | F88: Shop | G88: Huế Farm | H88: 8 xuân hoà thuỷ vân huế | I88: 02343601111 | J88: Lê Thị Anh Thư | K88: C005677266 | L88: 3301688346 | M88: 162 HĐBC/BĐ-HF | N88: 44886 | O88: Không xác định | P88: Không có | Q88: Trong 03 - 05 ngày làm việc tiếp theo kể từ ngày nhận được hoá đơn GTGT hợp lệ | T88: Đang hoạt động | U88: PHẠM THỊ THANH UYÊN | V88: CTN009 | X88: Dầu ăn | Y88: 10.2 | Z88: 0.03 | AA88: 2268 | AC88: 536801 | AD88: 536801_tienttt | AF88: Theo quy định TCT | AG88: Không có yêu cầu khác. | AK88: Đã thanh toán | AQ88: 1 | AS88: Khách hàng tự mang đến bưu cục | AT88: 45842 | BC88: X | BE88: 59400 | BF88: 0 | BG88: 0 | BH88: 59400 | BI88: Hồ sơ vật lý và hồ sơ điện tử | BJ88: Rà soát để điều chỉnh lại bàn giao trên CMS | BK88: 536801 | BL88: Phú Thượng | BM88: Phường Mỹ Thượng | BN88: X | BQ88: X | BR88: X | BS88: Bưu điện TT Thuận Hóa - Phú Xuân
A89: 87 | B89: 5310 | C89: Bưu điện TT Thuận Hóa - Phú Xuân | D89: Shop | E89: C004676750 | F89: Shop | G89: TRẦN THỊ THU SƯƠNG | H89: Nhà 35 kiệt 2 Tỉnh lộ 10, Phường Phú Thượng, TP Huế | I89: 0934848499 | K89: C004676750 | M89: HĐ15.2022.HĐBC-BĐTPH-TTS | N89: 44615 | O89: Không xác định | P89: Không có | Q89: Trong 03 - 05 ngày làm việc tiếp theo kể từ ngày nhận được hoá đơn GTGT hợp lệ | T89: Đang hoạt động | U89: HỒ VĂN KỲ | V89: CTN001 | X89: Bánh | Y89: 1.88 | Z89: 0.03 | AA89: 1339.4 | AC89: 536801 | AD89: 536801_tienttt | AE89: BƯU TÁ LIÊN HỆ SĐT TRÊN VẬN ĐƠN | AF89: Theo quy định TCT | AG89: Không có yêu cầu khác. | AK89: Đã thanh toán | AN89: Nhà 35 kiệt 2 Tỉnh lộ 10, Phường Phú Thượng, TP Huế | AQ89: 1 | AS89: Khách hàng tự mang đến bưu cục | AT89: 45869 | BD89: X | BE89: 0 | BF89: 75951 | BG89: 333532 | BH89: 409483 | BI89: Hồ sơ vật lý và hồ sơ điện tử | BJ89: Rà soát để điều chỉnh lại bàn giao trên CMS | BK89: 536801 | BL89: Phú Thượng | BM89: Phường Mỹ Thượng | BQ89: X | BR89: X | BS89: Bưu điện TT Thuận Hóa - Phú Xuân
A90: 88 | B90: 5310 | C90: Bưu điện TT Thuận Hóa - Phú Xuân | D90: Shop | E90: C001395857 | F90: Shop | G90: Trần Thị Mai Liên | H90: 35/92 Đặng Huy Trứ, Phường Phước Vĩnh, TP Huế | I90: 0702626909 | J90: Trần Thị Mai Liên | K90: C001395857 | M90: 105/2021/HĐBC/BĐTPH-TTML | N90: 44271 | O90: Không xác định | P90: Không có | Q90: Thanh toán cước khi chi trả cod | R90: Thanh toán bằng CK (t2/t4/t6) | S90: 1913542797600 Techcombank Trần Thị Mai Liên | T90: Đang hoạt động | U90: PHẠM THỊ THANH UYÊN | V90: CTN009 | W90: GTG071;GTG021 | X90: Saffron, mật ong, máy xay, dầu gội phủ bạc, kem chống nắng | Y90: 2.39 | Z90: 0.6 | AA90: 17795.1 | AC90: 536801 | AD90: 536801_tienttt | AF90: Theo quy định TCT | AG90: Không có yêu cầu khác. | AK90: 212112 | AL90: đang làm thanh toán | AN90: 35/92 Đặng Huy Trứ, Phường Phước Vĩnh, TP Huế | AO90: 15h00-16h00 | AP90: 2-3 lần/tuần | AQ90: 18 | AR90: Xe máy | AT90: 45869 | BC90: X | BE90: 192000 | BF90: 872130 | BG90: 581125 | BH90: 1645255 | BI90: Hồ sơ vật lý và hồ sơ điện tử | BJ90: Rà soát để điều chỉnh lại bàn giao trên CMS | BK90: 536801 | BL90: Phú Thượng | BM90: Phường Mỹ Thượng | BQ90: X | BR90: X | BS90: Bưu điện TT Thuận Hóa - Phú Xuân
A91: 89 | B91: 5310 | C91: Bưu điện TT Thuận Hóa - Phú Xuân | D91: SME | E91: T001864878 | F91: SME | G91: CÔNG TY TNHH IN ẤN NGỌC TẤN | H91: X. Phú Thượng H. Phú Vang Tỉnh Thừa Thiên Huế | I91: 0935567636 | K91: T001864878 | L91: 3301605082 | P91: Không có | Q91: Thanh toán vào tháng sau | T91: Đang hoạt động | U91: HỒ VĂN KỲ | V91: CTN007 | W91: GTG071;GTG021 | X91: HỘP | Y91: 2.64 | Z91: 0.03 | AA91: 1837.63 | AC91: 536801 | AD91: 536801_tienttt | AE91: BƯU TÁ LIÊN HỆ SĐT TRÊN VẬN ĐƠN | AF91: Theo quy định TCT | AG91: Không có yêu cầu khác. | AK91: Đã thanh toán | AN91: X. Phú Thượng H. Phú Vang Tỉnh Thừa Thiên Huế | AO91: 08h00-10h00; 14h00-16h00 | AP91: 1-2 lần/tuần | AQ91: 1 | AR91: Xe máy | AT91: 45869 | BD91: X | BE91: 384970 | BF91: 57090 | BG91: 58445 | BH91: 500505 | BI91: Hồ sơ vật lý và hồ sơ điện tử | BJ91: Bảo + Ni | BK91: 536801 | BL91: Phú Thượng | BM91: Phường Mỹ Thượng | BQ91: X | BR91: R | BS91: Bưu điện TT Thuận Hóa - Phú Xuân
A92: 90 | B92: 5310 | C92: Bưu điện TT Thuận Hóa - Phú Xuân | D92: Cá Nhân | E92: C008012733 | F92: Cá Nhân | G92: Đê Car | H92: 01 Hồng Khẳng Vĩ Dạ THừa Thiên Huế | I92: 0796536793 | K92: C008012733 | M92: HĐ049.2024-HĐBC-BĐTPH-ĐC | N92: 45351 | T92: Đang hoạt động | U92: PHẠM THỊ THANH UYÊN | V92: CK344118117VN | X92: mâm ô tô^1^0^0 | AC92: 536801 | AD92: 536801_tienttt | BE92: 1092545 | BF92: 683545 | BG92: 0 | BH92: 1776090 | BI92: Hồ sơ vật lý và hồ sơ điện tử | BJ92: Bảo + Ni | BK92: 536801 | BL92: Phú Thượng | BM92: Phường Mỹ Thượng | BQ92: X | BR92: R | BS92: Bưu điện TT Thuận Hóa - Phú Xuân
A93: 91 | B93: 5310 | C93: Bưu điện TT Thuận Hóa - Phú Xuân | D93: Cá Nhân | E93: C008302404 | F93: Cá Nhân | G93: Sĩ Sạc Ác Quy | H93: Lô A8- KĐT Phú Mỹ Thượng | I93: 0352177110 | K93: C008302404 | M93: HĐ89.2024_HĐBC_BĐTPH_SSA | N93: 45404 | T93: Đang hoạt động | U93: PHẠM THỊ THANH UYÊN | V93: 0 | X93: ÁC QUY;1;0;0 | AC93: 536801 | AD93: 536801_tienttt | BE93: 108600 | BF93: 21000 | BG93: 0 | BH93: 129600 | BI93: Hồ sơ vật lý và hồ sơ điện tử | BJ93: Bảo + Ni | BK93: 536801 | BL93: Phú Thượng | BM93: Phường Mỹ Thượng | BQ93: X | BR93: R | BS93: Bưu điện TT Thuận Hóa - Phú Xuân
A94: 92 | B94: 5310 | C94: Bưu điện TT Thuận Hóa - Phú Xuân | D94: Tổ Chức | E94: T018726408 | F94: Tổ Chức | G94: CÔNG TY TNHH NGHIÊN CỨU VÀ PHÁT TRIỂN HUEFARM | H94: Kiệt 8, Xuân Hòa | I94: 0934927575 | K94: T018726408 | M94: HĐ260/BC-PHBC/BĐTP-HUEFARM | N94: 45952 | T94: Đang thực hiện | U94: HOÀNG HỮU QUANG | AC94: 536801 | AD94: 536801_tienttt | BE94: 269800 | BF94: 0 | BG94: 0 | BH94: 269800 | BI94: Hồ sơ vật lý và hồ sơ điện tử | BJ94: Bảo + Ni | BK94: 536801 | BL94: Phú Thượng | BM94: Phường Mỹ Thượng | BQ94: X | BR94: R | BS94: Bưu điện TT Thuận Hóa - Phú Xuân
A95: 93 | B95: 5310 | C95: Bưu điện TT Thuận Hóa - Phú Xuân | D95: Tổ Chức | E95: T019251782 | F95: Tổ Chức | G95: Công Ty TNHH MTV Sản Xuất Và Thương Mại Ba Hưng | H95: 222 Phạm Văn Đồng, Phường Mỹ Thượng, TP Huế | I95: 02342470004 | K95: T019251782 | M95: HĐ04.2026 | N95: 46035 | T95: Đang hoạt động | U95: Phan Thị Hoài Phương | V95: ETN001 | Y95: 40 | Z95: 1 | AA95: 48600 | AC95: 536801 | AD95: 536801_tienttt | AE95: 0 | BE95: 0 | BF95: 48600 | BG95: 132000 | BH95: 180600 | BJ95: Rà soát để bàn giao trên CMS | BK95: 536801 | BL95: Phú Thượng | BM95: Phường Mỹ Thượng | BQ95: X | BS95: Bưu điện TT Thuận Hóa - Phú Xuân
A96: 94 | B96: 5310 | C96: Bưu điện TT Thuận Hóa - Phú Xuân | D96: Key Account | E96: T017959635 | F96: Key Account | G96: Trung Tâm HCC Phường Mỹ Thượng | H96: 449 Phạm Văn Đồng, phường Mỹ Thượng,TP. Huế | J96: Nguyễn Hữu Toàn | K96: T017959635 | M96: 174/2025/HĐ_BC-PHBC/BĐTT-TTPVHCCPMT | N96: 45839 | O96: Không xác định | P96: Không có | Q96: 01 tháng/lần Trong 03 - 05 ngày làm việc tiếp theo kể từ ngày nhận được hoá đơn GTGT hợp lệ | T96: Đang hoạt động | U96: ĐẶNG TUẤN VŨ | V96: Dịch vụ HCC, luân chuyển hồ sơ HCC, KT1, EMS, Chuyển phát bưu phẩm trong nước và quốc tế | X96: Tài liệu | Y96: 0.0375 | Z96: 0.066666667 | AA96: 2050 | AB96: My VNP | AC96: 536801 | AD96: 536801_tienttt | AF96: Thực hiện theo quy định của TCT | AK96: 66420 | AL96: Đang làm thanh toán | BC96: X | BE96: 399500 | BF96: 61000 | BG96: 90500 | BH96: 551000 | BI96: Hồ sơ vật lý và hồ sơ điện tử | BJ96: Bảo + Ni | BK96: 536801 | BL96: Phú Thượng | BM96: Phường Mỹ Thượng | BQ96: X | BR96: X | BS96: Bưu điện TT Thuận Hóa - Phú Xuân
A97: 95 | B97: 5310 | C97: Bưu điện TT Thuận Hóa - Phú Xuân | D97: Shop | E97: C005879192 | F97: Shop | G97: Đặng Nhật Linh | H97: tỉnh lộ 10 | I97: 0906546112 | J97: Đặng Nhật Linh | K97: C005879192 | M97: HĐ05.2023-HĐBC-BĐTPH-CX | N97: 44963 | O97: Không xác định | Q97: Nhận tiền COD thanh toán cước | R97: Chuyển khoản | S97: 100006662680 Vietinbank Đặng Nhật Linh | T97: Đang hoạt động | U97: PHẠM THỊ THANH UYÊN | V97: CTN007, CTN009 | W97: GTG021 | X97: Đồ gia dụng, mỹ phẩm, đồ ăn, gia vị | Y97: 2.59 | Z97: 0.9 | AA97: 20057 | AC97: 536810 | AD97: 536810_laint | AE97: 0 | AF97: Theo quy định của TCT | AK97: đã thanh toán | AN97: tỉnh lộ 10 | AO97: 08h00-09h00 và 14h00-15hh0 | AP97: 1 lân / ngày | AQ97: 27 | AR97: Xe máy | AT97: 45862 | AW97: Hàng tuần | BC97: X | BE97: 869227 | BF97: 216315 | BG97: 465715 | BH97: 1551257 | BI97: Hồ sơ vật lý và hồ sơ điện tử | BJ97: Bảo + Ni | BK97: 536810 | BL97: Trung Đông | BM97: Phường Mỹ Thượng | BN97: X | BQ97: X | BR97: X | BS97: Bưu điện TT Thuận Hóa - Phú Xuân
A98: 96 | B98: 5310 | C98: Bưu điện TT Thuận Hóa - Phú Xuân | D98: Shop | E98: C017231723 | F98: Shop | G98: Lê Văn Bảo | H98: trung đông, X. Phú Thượng H. Phú Vang Tỉnh Thừa Thiên Huế | I98: 0868821121 | J98: Lê Văn Bảo | K98: C017231723 | M98: HĐ97.2025-HĐBC-BĐTPH-DH | N98: 45748 | O98: Không xác định | Q98: 1-2 lần/tháng | T98: Đang hoạt động | U98: VÕ KHẮC QUÝ | V98: CTN001 CTN007 | X98: Thuốc men | Y98: 0.93 | Z98: 2 | AA98: 121585 | AC98: 536810 | AD98: 536810_laint | AE98: Bưu tá liên hệ phát theo sdt trên đơn hàng, KHông phát được liên hệ ngay người gủi, kb | AF98: Thực hiện theo quy định của TCT | AK98: Đã thanh toán công nợ | AN98: trung đông, X. Phú Thượng H. Phú Vang Tỉnh Thừa Thiên Huế | AO98: 15h00-17h00 | AP98: 1 lần/ngày | AQ98: 68 | AR98: xe máy | AT98: 45855 | BD98: X | BE98: 1400067 | BF98: 325200 | BG98: 0 | BH98: 1725267 | BI98: Hồ sơ vật lý và hồ sơ điện tử | BJ98: Bảo + Ni | BK98: 536810 | BL98: Trung Đông | BM98: Phường Mỹ Thượng | BQ98: X | BR98: X | BS98: Bưu điện TT Thuận Hóa - Phú Xuân
A99: 97 | B99: 5310 | C99: Bưu điện TT Thuận Hóa - Phú Xuân | D99: Shop | E99: C001411475 | F99: Shop | G99: Bùi ngọc tân | H99: Phú Mậu, Phú Vang, TT Huế | I99: 0702644663 | J99: Bùi ngọc tân | K99: C001411475 | M99: HĐ:82/HĐBC/BĐHPV-BNT | N99: 44501 | O99: Không xác định | Q99: Thanh toán cước KHi chi trả cod | R99: Thanh toán TM theo yều cầu KH | T99: Đang hoạt động | U99: HỒ VĂN KỲ | V99: CTN009 | W99: GTG021 | X99: Nhông sên | Y99: 14.712424 | Z99: 1.1 | AA99: 90806.667 | AC99: 536810 | AD99: 536810_laint | AF99: Thực hiện theo quy định của TCT | AK99: Đã thanh toán công nợ | AN99: Phú Mậu, Phú Vang, TT Huế | AO99: 15h00-17h00 | AP99: 1 lần/ngày | AQ99: 33 | AR99: xe máy | AT99: 45853 | BD99: X | BE99: 3619000 | BF99: 4010470 | BG99: 664000 | BH99: 8293470 | BI99: Hồ sơ vật lý và hồ sơ điện tử | BJ99: Bảo + Ni | BK99: 536810 | BL99: Trung Đông | BM99: Phường Mỹ Thượng | BN99: X | BQ99: X | BR99: X | BS99: Bưu điện TT Thuận Hóa - Phú Xuân
A100: 98 | B100: 5310 | C100: Bưu điện TT Thuận Hóa - Phú Xuân | D100: Shop | E100: C007575168 | F100: Shop | G100: Dương Thị Diệu Hoà | H100: Xóm 2 Thôn Phò an, X. Phú Dương H. Phú Vang Tỉnh Thừa Thiên Huế | I100: 0388848023 | K100: C007575168 | M100: HĐ005.2024-HĐBC-BĐTPH-DH | N100: 45300 | O100: Không xác định | P100: Không có | Q100: Thanh toán cước ngay khi gửi | S100: Chuyển khoản | T100: Đang hoạt động | U100: PHẠM THỊ THANH UYÊN | V100: CTN009 | W100: GTG021 | X100: hoa kẽm nhung | Y100: 4.71 | Z100: 0.2 | AA100: 7596 | AC100: 536810 | AD100: 536810_laint | AE100: Bưu tá liên hệ phát theo sdt trên đơn hàng, kb | AF100: Theo quy định TCT | AG100: Không có yêu cầu khác. | AK100: Đã thanh toán | AN100: Xóm 2 Thôn Phò an, X. Phú Dương H. Phú Vang Tỉnh Thừa Thiên Huế | AQ100: 6 | AS100: Khách hàng tự mang đến bưu cục | AT100: 45869 | BC100: X | BE100: 1714000 | BF100: 1250000 | BG100: 103400 | BH100: 3067400 | BI100: Hồ sơ vật lý và hồ sơ điện tử | BJ100: Bảo + Ni | BK100: 536810 | BL100: Trung Đông | BM100: Phường Mỹ Thượng | BQ100: X | BR100: x | BS100: Bưu điện TT Thuận Hóa - Phú Xuân
...

Sheet CT KH
A1: DANH SÁCH KHÁCH HÀNG HIỆN HỮU VÀ KHÁCH HÀNG MỚI TẠI TTVH
B2: =SUBTOTAL(3,B4:B5000) -> 1447 | X2: 1447 | Y2: 1447
A3: STT | B3: Mã CRM/CMS | D3: Loại KHách hàng | E3: Nhóm KH | F3: Tên KH | G3: Tên BC/VHX | H3: Dia_chi | I3: Dien_thoai | J3: Nguoi_lien_he | K3: so_hop_dong | L3: Thoi_han_hop_dong | M3: Thoi_han_ket_thuc | N3: BĐP/X | O3: DT Tháng 1 | P3: DT Tháng 2 | Q3: DT Tháng 3 | R3: Tổng cộng | S3: Cước đặc thù | T3: Người rà soát bàn giao TTKD | U3: Người rà soát bàn giao TTVH | V3: Đơn vị đã gắn HĐ trên CMS | W3: Đã gửi HĐ vật lý lên TTKD | X3: Tình hình rà soát | Y3: Tình hình bàn giao trên CMS | Z3: Đơn vị
A4: 1 | B4: T004890545 | C4: =VLOOKUP(B4,Sheet6!$C$80:$C$88,1,0) -> #N/A | D4: SME | E4: KHHH | F4: Công Ty Cổ Phần Toyota Huế | G4: Thuỷ An | H4: Lô C, KĐT Phú Mỹ An, Đường Tố Hữu, An Đông, TP Huế | I4: 02436299696 | J4: Lê Thế Vỹ | K4: HĐ54-2022_HĐBC_BĐTPH-MTL | L4: 01/5/2022 | M4: Không xác định | N4: Phường An Cựu | O4: =SUMIFS('T1'!$P$5:$P$2700,'T1'!$B$5:$B$2700,'CT KH'!$B4) -> 2619152 | P4: =SUMIFS('T2'!$P$5:$P$2700,'T2'!$B$5:$B$2700,'CT KH'!$B4) -> 1191054 | Q4: =SUMIFS('T3'!$P$5:$P$2700,'T3'!$B$5:$B$2700,'CT KH'!$B4) -> 1614165 | R4: =SUM(O4:Q4) -> 5424371 | S4: Không | T4: Long | U4: Phát | V4: Có | W4: Có | X4: Đã rà soát | Y4: Đã bàn giao | Z4: Thuận Hóa - Phú Xuân
A5: 2 | B5: C001395675 | C5: =VLOOKUP(B5,Sheet6!$C$80:$C$88,1,0) -> #N/A | D5: Shop | E5: KHHH | F5: VÕ HOÀNG MINH | G5: Thuỷ An | H5: Đường số 7, An Cựu City, P An Đông, TP Huế | I5: 0932436536 | J5: VÕ HOÀNG MINH | K5: 151/HĐBC-BĐTP/VHM | L5: 43685 | M5: Không xác định | N5: Phường An Cựu | O5: =SUMIFS('T1'!$P$5:$P$2700,'T1'!$B$5:$B$2700,'CT KH'!$B5) -> 189384 | P5: =SUMIFS('T2'!$P$5:$P$2700,'T2'!$B$5:$B$2700,'CT KH'!$B5) -> 0 | Q5: =SUMIFS('T3'!$P$5:$P$2700,'T3'!$B$5:$B$2700,'CT KH'!$B5) -> 121716 | R5: =SUM(O5:Q5) -> 311100 | S5: Không | T5: Long | U5: Phát | V5: Có | W5: Có | X5: Đã rà soát | Y5: Đã bàn giao | Z5: Thuận Hóa - Phú Xuân
A6: 3 | B6: T001799661 | C6: =VLOOKUP(B6,Sheet6!$C$80:$C$88,1,0) -> #N/A | D6: SME | E6: KHHH | F6: CÔNG TY TNHH TM QUỐC HÙNG | G6: Thuỷ An | H6: 86 HÙNG VƯƠNG, TP HUẾ | I6: 0989020237 | J6: Nguyễn Trần Như Ý | K6: 384/HĐBC/BĐTPH-CTQUOCHUNG | L6: 44169 | M6: Không xác định | N6: Phường An Cựu | O6: =SUMIFS('T1'!$P$5:$P$2700,'T1'!$B$5:$B$2700,'CT KH'!$B6) -> 0 | P6: =SUMIFS('T2'!$P$5:$P$2700,'T2'!$B$5:$B$2700,'CT KH'!$B6) -> 19440 | Q6: =SUMIFS('T3'!$P$5:$P$2700,'T3'!$B$5:$B$2700,'CT KH'!$B6) -> 0 | R6: =SUM(O6:Q6) -> 19440 | S6: Không | T6: Long | U6: Phát | V6: Có | W6: Có | X6: Đã rà soát | Y6: Đã bàn giao | Z6: Thuận Hóa - Phú Xuân
A7: 4 | B7: T001456556 | C7: =VLOOKUP(B7,Sheet6!$C$80:$C$88,1,0) -> #N/A | D7: SME | E7: KHHH | F7: Công ty luật TNHH Nhật Nam và cộng sự | G7: Thuỷ An | H7: 52 Hoàng Văn Thụ, P An Đông, TP Huế | I7: 0234.3936155 | J7: Trần Nhật Nam | K7: 149/HĐBC-BĐTP/TNN | L7: 43685 | M7: Không xác định | N7: Phường An Cựu | O7: =SUMIFS('T1'!$P$5:$P$2700,'T1'!$B$5:$B$2700,'CT KH'!$B7) -> 241056 | P7: =SUMIFS('T2'!$P$5:$P$2700,'T2'!$B$5:$B$2700,'CT KH'!$B7) -> 161568 | Q7: =SUMIFS('T3'!$P$5:$P$2700,'T3'!$B$5:$B$2700,'CT KH'!$B7) -> 394767 | R7: =SUM(O7:Q7) -> 797391 | S7: Không | T7: Long | U7: Phát | V7: Có | W7: Có | X7: Đã rà soát | Y7: Đã bàn giao | Z7: Thuận Hóa - Phú Xuân
A8: 5 | B8: T001799967 | C8: =VLOOKUP(B8,Sheet6!$C$80:$C$88,1,0) -> #N/A | D8: SME | E8: KHHH | F8: CÔNG TY TNHH MTV PHÁT LÊ | G8: Thuỷ An | H8: 108 TRƯỜNG CHINH, P. An Đông TP. Huế Tỉnh Thừa Thiên Huế | I8: 0234.3934999 | J8: Trần Thị Thúy Nhi | K8: 391/HĐBC/BĐTPH-PL | L8: 44168 | M8: Không xác định | N8: Phường An Cựu | O8: =SUMIFS('T1'!$P$5:$P$2700,'T1'!$B$5:$B$2700,'CT KH'!$B8) -> 245060 | P8: =SUMIFS('T2'!$P$5:$P$2700,'T2'!$B$5:$B$2700,'CT KH'!$B8) -> 234333 | Q8: =SUMIFS('T3'!$P$5:$P$2700,'T3'!$B$5:$B$2700,'CT KH'!$B8) -> 240919 | R8: =SUM(O8:Q8) -> 720312 | S8: Không | T8: Long | U8: Phát | V8: Có | W8: Có | X8: Đã rà soát | Y8: Đã bàn giao | Z8: Thuận Hóa - Phú Xuân
A9: 6 | B9: C001929335 | C9: =VLOOKUP(B9,Sheet6!$C$80:$C$88,1,0) -> #N/A | D9: SME | E9: KHHH | F9: Công Ty Tnhh Tm Tân Quốc Hùng | G9: Thuỷ An | H9: 128 hùng vương, P. Phú Hội TP. Huế Tỉnh Thừa Thiên Huế | I9: 02343811015 | J9: Võ Văn Hùng | K9: 389/HĐBC | L9: 44228 | M9: Không xác định | N9: Phường An Cựu | O9: =SUMIFS('T1'!$P$5:$P$2700,'T1'!$B$5:$B$2700,'CT KH'!$B9) -> 108216 | P9: =SUMIFS('T2'!$P$5:$P$2700,'T2'!$B$5:$B$2700,'CT KH'!$B9) -> 26352 | Q9: =SUMIFS('T3'!$P$5:$P$2700,'T3'!$B$5:$B$2700,'CT KH'!$B9) -> 56268 | R9: =SUM(O9:Q9) -> 190836 | S9: Không | T9: Long | U9: Phát | V9: Có | W9: Có | X9: Đã rà soát | Y9: Đã bàn giao | Z9: Thuận Hóa - Phú Xuân
A10: 7 | B10: T002490015 | C10: =VLOOKUP(B10,Sheet6!$C$80:$C$88,1,0) -> #N/A | D10: SME | E10: KHHH | F10: Công Ty Cổ Phần Tập Đoàn IUC | G10: Thuỷ An | H10: Tầng 3, Tòa nhà Vinaconex 7, số 64 Đường Nguyễn Văn Giáp , phường Cầu Diễn, Quận Nam Từ Liêm, Hà Nội | I10: 0908576568 | J10: Nguyễn Thành Công | K10: 383.2021/HĐBC-BĐTPH-IUC | L10: 44389 | M10: Không xác định | N10: Phường An Cựu | O10: =SUMIFS('T1'!$P$5:$P$2700,'T1'!$B$5:$B$2700,'CT KH'!$B10) -> 91368 | P10: =SUMIFS('T2'!$P$5:$P$2700,'T2'!$B$5:$B$2700,'CT KH'!$B10) -> 264771 | Q10: =SUMIFS('T3'!$P$5:$P$2700,'T3'!$B$5:$B$2700,'CT KH'!$B10) -> 212004 | R10: =SUM(O10:Q10) -> 568143 | S10: Không | T10: Long | U10: Phát | V10: Có | W10: Có | X10: Đã rà soát | Y10: Đã bàn giao | Z10: Thuận Hóa - Phú Xuân
A11: 8 | B11: C005695891 | C11: =VLOOKUP(B11,Sheet6!$C$80:$C$88,1,0) -> #N/A | D11: Shop | E11: KHHH | F11: Lê Thị Mỹ Hiền | G11: Thuỷ An | H11: 04 Hoàng Văn Thụ, P. Xuân Phú TP. Huế Tỉnh Thừa Thiên Huế | I11: 0775555986 | J11: 0 | K11: HĐ170-HĐBC-BĐTP-LTMH | L11: 44890 | M11: Không xác định | N11: Phường An Cựu | O11: =SUMIFS('T1'!$P$5:$P$2700,'T1'!$B$5:$B$2700,'CT KH'!$B11) -> 1277100 | P11: =SUMIFS('T2'!$P$5:$P$2700,'T2'!$B$5:$B$2700,'CT KH'!$B11) -> 1266300 | Q11: =SUMIFS('T3'!$P$5:$P$2700,'T3'!$B$5:$B$2700,'CT KH'!$B11) -> 53460 | R11: =SUM(O11:Q11) -> 2596860 | S11: Không | T11: Long | U11: Phát | V11: Có | W11: Có | X11: Đã rà soát | Y11: Đã bàn giao | Z11: Thuận Hóa - Phú Xuân
A12: 9 | B12: T001799573 | C12: =VLOOKUP(B12,Sheet6!$C$80:$C$88,1,0) -> #N/A | D12: SME | E12: KHHH | F12: CTY CP BĐS MINH ĐIỀN VITAL | G12: Thuỷ An | H12: Khu đô thị The Manor Crown, Xuân Phú, TP huế | I12: 0907024029 | J12: Đặng Mạnh Cường | K12: HĐ394-HĐBC-BĐTPH-VITAL | L12: 44169 | M12: Không xác định | N12: Phường An Cựu | O12: =SUMIFS('T1'!$P$5:$P$2700,'T1'!$B$5:$B$2700,'CT KH'!$B12) -> 394416 | P12: =SUMIFS('T2'!$P$5:$P$2700,'T2'!$B$5:$B$2700,'CT KH'!$B12) -> 271512 | Q12: =SUMIFS('T3'!$P$5:$P$2700,'T3'!$B$5:$B$2700,'CT KH'!$B12) -> 93312 | R12: =SUM(O12:Q12) -> 759240 | S12: Không | T12: Long | U12: Phát | V12: Có | W12: Có | X12: Đã rà soát | Y12: Chưa bàn giao | Z12: Thuận Hóa - Phú Xuân
A13: 10 | B13: T001399385 | C13: =VLOOKUP(B13,Sheet6!$C$80:$C$88,1,0) -> #N/A | D13: SME | E13: KHHH | F13: CÔNG TY CỔ PHẦN VẬN TẢI VÀ DỊCH VỤ PETROLIMEX THỪA THIÊN HUẾ | G13: Thuỷ An | H13: 0 | I13: 02343812117 | J13: Chị Trang | K13: 100/HĐBC-BĐTP/CTY PERTOLIMEX | L13: 06/06/2017 | M13: Không xác định | N13: Phường An Cựu | O13: =SUMIFS('T1'!$P$5:$P$2700,'T1'!$B$5:$B$2700,'CT KH'!$B13) -> 1520145 | P13: =SUMIFS('T2'!$P$5:$P$2700,'T2'!$B$5:$B$2700,'CT KH'!$B13) -> 611496 | Q13: =SUMIFS('T3'!$P$5:$P$2700,'T3'!$B$5:$B$2700,'CT KH'!$B13) -> 1378350 | R13: =SUM(O13:Q13) -> 3509991 | S13: Không | T13: Vũ | U13: Lan | V13: Có | W13: Có | X13: Đã rà soát | Y13: Đã bàn giao | Z13: Thuận Hóa - Phú Xuân
A14: 11 | B14: T001799834 | C14: =VLOOKUP(B14,Sheet6!$C$80:$C$88,1,0) -> #N/A | D14: SME | E14: KHHH | F14: CÔNG TY CỔ PHẦN XÂY DỰNG VÀ ĐẦU TƯ XUÂN PHÚ | G14: Thuỷ An | H14: NHÀ 17 ĐƯỜNG SỐ 4 AN CỰU CITY, P. An Cựu TP. Huế Tỉnh Thừa Thiên Huế | I14: 0705358292 | J14: Lê Thanh Hà | K14: HĐ377-HĐBC-BĐTPH-CTCPVXDĐTXP | L14: 44169 | M14: Không xác định | N14: Phường An Cựu | O14: =SUMIFS('T1'!$P$5:$P$2700,'T1'!$B$5:$B$2700,'CT KH'!$B14) -> 10368 | P14: =SUMIFS('T2'!$P$5:$P$2700,'T2'!$B$5:$B$2700,'CT KH'!$B14) -> 40176 | Q14: =SUMIFS('T3'!$P$5:$P$2700,'T3'!$B$5:$B$2700,'CT KH'!$B14) -> 14850 | R14: =SUM(O14:Q14) -> 65394 | S14: Không | T14: Hương | U14: Bảo | V14: Có | W14: Có | X14: Đã rà soát | Y14: Đã bàn giao | Z14: Thuận Hóa - Phú Xuân
A15: 12 | B15: T001800268 | C15: =VLOOKUP(B15,Sheet6!$C$80:$C$88,1,0) -> #N/A | D15: SME | E15: KHHH | F15: TRƯỜNG CAO ĐẲNG Y TẾ | G15: Thuỷ An | H15: 1 NGUYỄN TRƯỜNG TỘ, TP HUẾ | I15: 0234.3822414 | J15: Văn Thư | K15: 253/2021/HĐBC/BĐTP-CĐYTE | L15: 44272 | M15: Không xác định | N15: Phường An Cựu | O15: =SUMIFS('T1'!$P$5:$P$2700,'T1'!$B$5:$B$2700,'CT KH'!$B15) -> 0 | P15: =SUMIFS('T2'!$P$5:$P$2700,'T2'!$B$5:$B$2700,'CT KH'!$B15) -> 0 | Q15: =SUMIFS('T3'!$P$5:$P$2700,'T3'!$B$5:$B$2700,'CT KH'!$B15) -> 0 | R15: =SUM(O15:Q15) -> 0 | S15: Không | T15: Thy | U15: Dũng | V15: Có | W15: Có | X15: Đã rà soát | Y15: Đã bàn giao | Z15: Thuận Hóa - Phú Xuân
A16: 13 | B16: C016607629 | C16: =VLOOKUP(B16,Sheet6!$C$80:$C$88,1,0) -> #N/A | D16: Shop | E16: KHHH | F16: Cánh Buồm | G16: Thuỷ An | H16: Lô A34 Đường số 2 KĐT An Cựu City, P. An Đông TP. Huế Tỉnh Thừa Thiên Huế | I16: 0 | J16: Cánh Buồm | K16: 0 | L16: 0 | M16: 0 | N16: Phường An Cựu | O16: =SUMIFS('T1'!$P$5:$P$2700,'T1'!$B$5:$B$2700,'CT KH'!$B16) -> 519951 | P16: =SUMIFS('T2'!$P$5:$P$2700,'T2'!$B$5:$B$2700,'CT KH'!$B16) -> 120547 | Q16: =SUMIFS('T3'!$P$5:$P$2700,'T3'!$B$5:$B$2700,'CT KH'!$B16) -> 1401206 | R16: =SUM(O16:Q16) -> 2041704 | S16: Không | T16: Long | U16: Phát | V16: Có | W16: Có | X16: Đã rà soát | Y16: Đã bàn giao | Z16: Thuận Hóa - Phú Xuân
A17: 14 | B17: T005217327 | C17: =VLOOKUP(B17,Sheet6!$C$80:$C$88,1,0) -> #N/A | D17: SME | E17: KHHH | F17: Công Ty Cổ Phần BWB-chi Nhánh Huế | G17: Thuỷ An | H17: Tầng 6 tháp The Manor Crown | I17: 0 | J17: Tuyết | K17: 0 | L17: 0 | M17: 0 | N17: Phường An Cựu | O17: =SUMIFS('T1'!$P$5:$P$2700,'T1'!$B$5:$B$2700,'CT KH'!$B17) -> 19440 | P17: =SUMIFS('T2'!$P$5:$P$2700,'T2'!$B$5:$B$2700,'CT KH'!$B17) -> 0 | Q17: =SUMIFS('T3'!$P$5:$P$2700,'T3'!$B$5:$B$2700,'CT KH'!$B17) -> 0 | R17: =SUM(O17:Q17) -> 19440 | S17: Không | T17: Long | U17: Phát | V17: Có | W17: Có | X17: Đã rà soát | Y17: Đã bàn giao | Z17: Thuận Hóa - Phú Xuân
A18: 15 | B18: C018726221 | C18: =VLOOKUP(B18,Sheet6!$C$80:$C$88,1,0) -> #N/A | D18: Cá Nhân | E18: KHHH | F18: Nguyễn Huyền Tôn Nữ Ái Vân | G18: Thuỷ An | H18: 08 Tố Hữu, P. Xuân Phú , Quận Thuận Hóa, TP. Huế | I18: 0899489952 | J18: 0 | K18: 259.202TH5/HĐBC/BĐKVTHPX-NHTNAV | L18: 45952 | N18: Phường An Cựu | O18: =SUMIFS('T1'!$P$5:$P$2700,'T1'!$B$5:$B$2700,'CT KH'!$B18) -> 126680 | P18: =SUMIFS('T2'!$P$5:$P$2700,'T2'!$B$5:$B$2700,'CT KH'!$B18) -> 186949 | Q18: =SUMIFS('T3'!$P$5:$P$2700,'T3'!$B$5:$B$2700,'CT KH'!$B18) -> 335789 | R18: =SUM(O18:Q18) -> 649418 | S18: Có | T18: Thy | U18: Dũng | V18: Có | W18: Có | X18: Đã rà soát | Y18: Đã bàn giao | Z18: Thuận Hóa - Phú Xuân
A19: 16 | B19: C018656707 | C19: =VLOOKUP(B19,Sheet6!$C$80:$C$88,1,0) -> #N/A | D19: Cá Nhân | E19: KHHH | F19: Nguyễn Ngọc Phú | G19: Thuỷ An | H19: 189 Bà Triệu - Thuận Hóa - Thành Phố Huế | I19: 0898254999 | J19: 0 | K19: 0 | L19: 0 | M19: 0 | N19: Phường An Cựu | O19: =SUMIFS('T1'!$P$5:$P$2700,'T1'!$B$5:$B$2700,'CT KH'!$B19) -> 0 | P19: =SUMIFS('T2'!$P$5:$P$2700,'T2'!$B$5:$B$2700,'CT KH'!$B19) -> 0 | Q19: =SUMIFS('T3'!$P$5:$P$2700,'T3'!$B$5:$B$2700,'CT KH'!$B19) -> 0 | R19: =SUM(O19:Q19) -> 0 | S19: Không | T19: Thắm | U19: Lan | V19: Có | W19: Có | X19: Đã rà soát | Y19: Đã bàn giao | Z19: Thuận Hóa - Phú Xuân
A20: 17 | B20: C018477419 | C20: =VLOOKUP(B20,Sheet6!$C$80:$C$88,1,0) -> #N/A | D20: Cá Nhân | E20: KHHH | F20: Nhà May Duy Tuấn | G20: Thuỷ An | H20: 134 Trường Chinh - Phường An Cựu - Thành Phố Huế | I20: 0908680906 | J20: 0 | N20: Phường An Cựu | O20: =SUMIFS('T1'!$P$5:$P$2700,'T1'!$B$5:$B$2700,'CT KH'!$B20) -> 157360 | P20: =SUMIFS('T2'!$P$5:$P$2700,'T2'!$B$5:$B$2700,'CT KH'!$B20) -> 156541 | Q20: =SUMIFS('T3'!$P$5:$P$2700,'T3'!$B$5:$B$2700,'CT KH'!$B20) -> 0 | R20: =SUM(O20:Q20) -> 313901 | S20: Không | T20: Thắm | U20: Lan | V20: Có | W20: Có | X20: Đã rà soát | Y20: Đã bàn giao | Z20: Thuận Hóa - Phú Xuân
A21: 18 | B21: T018318911 | C21: =VLOOKUP(B21,Sheet6!$C$80:$C$88,1,0) -> #N/A | D21: Tổ Chức | E21: KHHH | F21: CÔNG AN PHƯỜNG AN CỰU | G21: Thuỷ An | H21: 18 Hoàng Quốc Việt | I21: 02343817234 | J21: 0 | K21: HĐ230.2025-HĐBC-PHBC-BĐTP-CAPHUONGANCUU | L21: 45887 | N21: Phường An Cựu | O21: =SUMIFS('T1'!$P$5:$P$2700,'T1'!$B$5:$B$2700,'CT KH'!$B21) -> 542533 | P21: =SUMIFS('T2'!$P$5:$P$2700,'T2'!$B$5:$B$2700,'CT KH'!$B21) -> 339090 | Q21: =SUMIFS('T3'!$P$5:$P$2700,'T3'!$B$5:$B$2700,'CT KH'!$B21) -> 945716 | R21: =SUM(O21:Q21) -> 1827339 | S21: Không | T21: Long | U21: Phát | V21: Có | W21: Có | X21: Đã rà soát | Y21: Đã bàn giao | Z21: Thuận Hóa - Phú Xuân
A22: 19 | B22: C018568551 | C22: =VLOOKUP(B22,Sheet6!$C$80:$C$88,1,0) -> #N/A | D22: Cá Nhân | E22: KHHH | F22: CÔNG TY CỔ PHẦN TẬP ĐOÀN BẢO HIỂM DBV - CN HUẾ | G22: Thuỷ An | H22: Tầng 2 tòa nhà 189 Phạm Văn Đồng, Phường Vỹ Dạ, Thành Phố Huế | I22: 097258523 | J22: 0 | K22: 249.202TH5/HĐBC/BĐKVTHPX-DBV | L22: 45931 | N22: Phường An Cựu | O22: =SUMIFS('T1'!$P$5:$P$2700,'T1'!$B$5:$B$2700,'CT KH'!$B22) -> 620244 | P22: =SUMIFS('T2'!$P$5:$P$2700,'T2'!$B$5:$B$2700,'CT KH'!$B22) -> 410184 | Q22: =SUMIFS('T3'!$P$5:$P$2700,'T3'!$B$5:$B$2700,'CT KH'!$B22) -> 480951 | R22: =SUM(O22:Q22) -> 1511379 | S22: Không | T22: Thy | U22: Dũng | V22: Có | W22: Có | X22: Đã rà soát | Y22: Đã bàn giao | Z22: Thuận Hóa - Phú Xuân
A23: 20 | B23: C018272260 | C23: =VLOOKUP(B23,Sheet6!$C$80:$C$88,1,0) -> #N/A | D23: Cá Nhân | E23: KHHH | F23: đinh thị phượng | G23: Thuỷ An | H23: bến xe phía nam phường an cựu | I23: 0814767134 | J23: 0 | K23: HĐ232.2025_HĐBC_BĐH_ĐTP | L23: 45887 | N23: Phường An Cựu | O23: =SUMIFS('T1'!$P$5:$P$2700,'T1'!$B$5:$B$2700,'CT KH'!$B23) -> 649080 | P23: =SUMIFS('T2'!$P$5:$P$2700,'T2'!$B$5:$B$2700,'CT KH'!$B23) -> 0 | Q23: =SUMIFS('T3'!$P$5:$P$2700,'T3'!$B$5:$B$2700,'CT KH'!$B23) -> 744120 | R23: =SUM(O23:Q23) -> 1393200 | S23: Không | T23: Thy | U23: Dũng | V23: Có | W23: Có | X23: Đã rà soát | Y23: Đã bàn giao | Z23: Thuận Hóa - Phú Xuân
A24: 21 | B24: T018411531 | C24: =VLOOKUP(B24,Sheet6!$C$80:$C$88,1,0) -> #N/A | D24: Tổ Chức | E24: KHHH | F24: Phú Xuân Travel | G24: Thuỷ An | H24: 51 Bà Triệu, Vỹ Dạ, Thành Phố Huế | I24: 0902882168 | J24: 0 | K24: 239.2025/HĐBC/BĐKVTHPX-PXT | L24: 45909 | N24: Phường An Cựu | O24: =SUMIFS('T1'!$P$5:$P$2700,'T1'!$B$5:$B$2700,'CT KH'!$B24) -> 0 | P24: =SUMIFS('T2'!$P$5:$P$2700,'T2'!$B$5:$B$2700,'CT KH'!$B24) -> 0 | Q24: =SUMIFS('T3'!$P$5:$P$2700,'T3'!$B$5:$B$2700,'CT KH'!$B24) -> 0 | R24: =SUM(O24:Q24) -> 0 | S24: Không | T24: Thắm | U24: Lan | V24: Có | W24: Có | X24: Đã rà soát | Y24: Đã bàn giao | Z24: Thuận Hóa - Phú Xuân
A25: 22 | B25: T018894468 | C25: =VLOOKUP(B25,Sheet6!$C$80:$C$88,1,0) -> #N/A | D25: Tổ Chức | E25: KHHH | F25: Văn Phòng HĐND Và UBND Phường An Cựu | G25: Thuỷ An | H25: 67A Đường Hoàng Quốc Việt, P. An Cựu, Quận Phú Xuân | I25: 0 | J25: 0 | K25: 262.2025/HĐBC/BĐKVTHPX-HĐN-UBNDPAC | L25: 45976 | M25: 0 | N25: Phường An Cựu | O25: =SUMIFS('T1'!$P$5:$P$2700,'T1'!$B$5:$B$2700,'CT KH'!$B25) -> 538645 | P25: =SUMIFS('T2'!$P$5:$P$2700,'T2'!$B$5:$B$2700,'CT KH'!$B25) -> 117072 | Q25: =SUMIFS('T3'!$P$5:$P$2700,'T3'!$B$5:$B$2700,'CT KH'!$B25) -> 151740 | R25: =SUM(O25:Q25) -> 807457 | S25: Không | T25: Thy | U25: Dũng | V25: Có | W25: Có | X25: Đã rà soát | Y25: Đã bàn giao | Z25: Thuận Hóa - Phú Xuân
A26: 23 | B26: C001395300 | C26: =VLOOKUP(B26,Sheet6!$C$80:$C$88,1,0) -> #N/A | D26: Cá Nhân | E26: KHHH | F26: Cô Lộc | G26: Thuỷ An | H26: 4/4/4 Kiệt 33 An Dương Vương An Cựu TP Huế | I26: 0918581215 | J26: 0 | K26: 49/HĐBC/BĐTPH-CL | L26: 44256 | N26: Phường An Cựu | O26: =SUMIFS('T1'!$P$5:$P$2700,'T1'!$B$5:$B$2700,'CT KH'!$B26) -> 2132990 | P26: =SUMIFS('T2'!$P$5:$P$2700,'T2'!$B$5:$B$2700,'CT KH'!$B26) -> 1414768 | Q26: =SUMIFS('T3'!$P$5:$P$2700,'T3'!$B$5:$B$2700,'CT KH'!$B26) -> 2495338 | R26: =SUM(O26:Q26) -> 6043096 | S26: Không | T26: Long | U26: Phát | V26: Có | W26: Không | X26: Đã rà soát | Y26: Đã bàn giao | Z26: Thuận Hóa - Phú Xuân
A27: 24 | B27: T017963860 | C27: =VLOOKUP(B27,Sheet6!$C$80:$C$88,1,0) -> #N/A | D27: Key Account | E27: KHHH | F27: Trung Tâm HCC Phường An Cựu | G27: Thuỷ An | H27: 67A Hoàng Quốc Việt, Phường An Cựu, TP Huế | I27: 0 | J27: Phan Đăng Phú Khánh | K27: 175/2025/HĐ_BC-PHBC/BĐTT-TTPVHCCPAC | L27: 45839 | M27: Không xác định | N27: Phường An Cựu | O27: =SUMIFS('T1'!$P$5:$P$2700,'T1'!$B$5:$B$2700,'CT KH'!$B27) -> 1068856 | P27: =SUMIFS('T2'!$P$5:$P$2700,'T2'!$B$5:$B$2700,'CT KH'!$B27) -> 439700 | Q27: =SUMIFS('T3'!$P$5:$P$2700,'T3'!$B$5:$B$2700,'CT KH'!$B27) -> 1197940 | R27: =SUM(O27:Q27) -> 2706496 | S27: Có | T27: Thắm | U27: Lan | V27: Có | W27: Có | X27: Đã rà soát | Y27: Đã bàn giao | Z27: Thuận Hóa - Phú Xuân
A28: 25 | B28: C017177801 | C28: =VLOOKUP(B28,Sheet6!$C$80:$C$88,1,0) -> #N/A | D28: Shop | E28: KHHH | F28: Duyên Trần | G28: Phú Mậu | H28: xóm 11, X. Phú Mậu H. Phú Vang Tỉnh Thừa Thiên Huế | I28: 0775875875 | J28: Trần Thị Ái Duyên | K28: HĐ56.2025.HĐBC-BĐTTTHPX-DT | L28: 45740 | M28: Không xác định | N28: Phường Dương Nỗ | O28: =SUMIFS('T1'!$P$5:$P$2700,'T1'!$B$5:$B$2700,'CT KH'!$B28) -> 89461 | P28: =SUMIFS('T2'!$P$5:$P$2700,'T2'!$B$5:$B$2700,'CT KH'!$B28) -> 30520 | Q28: =SUMIFS('T3'!$P$5:$P$2700,'T3'!$B$5:$B$2700,'CT KH'!$B28) -> 30000 | R28: =SUM(O28:Q28) -> 149981 | S28: Có | T28: Ni | U28: Bảo | V28: Có | W28: Có | X28: Đã rà soát | Y28: Đã bàn giao | Z28: Thuận Hóa - Phú Xuân
A29: 26 | B29: C016429937 | C29: =VLOOKUP(B29,Sheet6!$C$80:$C$88,1,0) -> #N/A | D29: Shop | E29: KHHH | F29: Nguyễn Thị Phương Thảo | G29: Phú Mậu | H29: xóm 11, làng Thanh Tiên, xã Phú Mậu, TP Huế | I29: 0898194881 | J29: 0 | K29: HĐ221-HĐBC-BĐTP-NTPT | L29: 45637 | M29: Không xác định | N29: Phường Dương Nỗ | O29: =SUMIFS('T1'!$P$5:$P$2700,'T1'!$B$5:$B$2700,'CT KH'!$B29) -> 5593644 | P29: =SUMIFS('T2'!$P$5:$P$2700,'T2'!$B$5:$B$2700,'CT KH'!$B29) -> 2518128 | Q29: =SUMIFS('T3'!$P$5:$P$2700,'T3'!$B$5:$B$2700,'CT KH'!$B29) -> 0 | R29: =SUM(O29:Q29) -> 8111772 | S29: Không | T29: Ni | U29: Bảo | V29: Có | W29: Có | X29: Đã rà soát | Y29: Đã bàn giao | Z29: Thuận Hóa - Phú Xuân
A30: 27 | B30: C016227458 | C30: =VLOOKUP(B30,Sheet6!$C$80:$C$88,1,0) -> #N/A | D30: Shop | E30: KHHH | F30: Võ Thị Mỹ Phố | G30: Phú Mậu | H30: kiệt 5 nguyễn hữu cảnh | I30: 0346429532 | J30: Võ Thị Mỹ Phố | K30: HĐ190.2024_HĐBC_BĐTPH-VTMP | L30: 45607 | M30: Không xác định | N30: Phường Dương Nỗ | O30: =SUMIFS('T1'!$P$5:$P$2700,'T1'!$B$5:$B$2700,'CT KH'!$B30) -> 0 | P30: =SUMIFS('T2'!$P$5:$P$2700,'T2'!$B$5:$B$2700,'CT KH'!$B30) -> 20000 | Q30: =SUMIFS('T3'!$P$5:$P$2700,'T3'!$B$5:$B$2700,'CT KH'!$B30) -> 0 | R30: =SUM(O30:Q30) -> 20000 | S30: Có | T30: Thy | U30: Dũng | V30: Có | W30: Có | X30: Đã rà soát | Y30: Đã bàn giao | Z30: Thuận Hóa - Phú Xuân
